Workbook
Name _1Excel_BuiltIn__FilterDatabase_12_1: Real_2007!$A$1:$F$4604
Name dois: IF(#REF!="X",0,#REF!)
Name Excel_BuiltIn__FilterDatabase_10_1: ItaU!$A$1:$E$1390
Name Excel_BuiltIn__FilterDatabase_12_1: ItauVisa!$A$1:$F$21
Name Excel_BuiltIn__FilterDatabase_13: ItauMasterCard!$A$1:$F$471
Name Excel_BuiltIn__FilterDatabase_16: RealVisa_2007!$A$1:$F$621
Name Excel_BuiltIn__FilterDatabase_16_1: Parcelamentos!$A$1:$G$662
Name Excel_BuiltIn__FilterDatabase_18: ItauVisa!$A$1:$F$1421
Name Excel_BuiltIn__FilterDatabase_19: ItauMasterCard!$A$1:$F$477
Name Excel_BuiltIn__FilterDatabase_25_1: PoupanCaItau!$A$1:$E$1
Name Excel_BuiltIn__FilterDatabase_44: Banespa!$A$1:$F$78
Name Excel_BuiltIn__FilterDatabase_45: HSBC!$A$1:$E$943
Name Excel_BuiltIn__FilterDatabase_47: HSBCVisa!$A$1:$F$94
Name Excel_BuiltIn__FilterDatabase_49: Banco1MasterCard!$A$1:$F$160
Name Excel_BuiltIn__FilterDatabase_5: CARTOES!$A$1:$K$25
Name Excel_BuiltIn__FilterDatabase_50: Banco1!$A$1:$E$795
Name Excel_BuiltIn__FilterDatabase_52: Banco1MasterCard!$A$1:$F$160
Name Excel_BuiltIn__FilterDatabase_53: UnibancoVisa!$A$1:$F$62
Name Excel_BuiltIn__FilterDatabase_56: Amex!$A$1:$F$1
Name Excel_BuiltIn__FilterDatabase_57: CitiBank!$A$1:$E$475
Name Excel_BuiltIn__FilterDatabase_60: CitibankVisa!$A$1:$F$209
Name Excel_BuiltIn__FilterDatabase_61: CitiBankMastercard!$A$1:$F$180
Name Excel_BuiltIn__FilterDatabase_62: Real!$A$1:$E$581
Name Excel_BuiltIn__FilterDatabase_63: RealVisa!$A$1:$F$277
Name Excel_BuiltIn__FilterDatabase_7: TiposLancamentos!$A$1:$B$105
Name Excel_BuiltIn__FilterDatabase_8: Despesas!$A$1:$E$4128
Name SHARED_FORMULA_0: IF(#REF!="X",0,#REF!)
Name SHARED_FORMULA_0: IF(#REF!="X",0,#REF!)
Name SHARED_FORMULA_0: IF(#REF!="X",0,#REF!)
Name SHARED_FORMULA_0: IF(#REF!="X",0,#REF!)
Name SHARED_FORMULA_0: IF(#REF!="X",0,#REF!)
Name SHARED_FORMULA_0: IF(#REF!="X",0,#REF!)
Name SHARED_FORMULA_1: IF(#REF!="X",0,#REF!)
Name SHARED_FORMULA_1: IF(#REF!="X",0,#REF!)
Name SHARED_FORMULA_1: IF(#REF!="X",0,#REF!)
Name SHARED_FORMULA_1: IF(#REF!="X",0,#REF!)
Name SHARED_FORMULA_1: IF(#REF!="X",0,#REF!)
Name SHARED_FORMULA_1: IF(#REF!="X",0,#REF!)
Name SHARED_FORMULA_2: IF(#REF!="X",0,#REF!)
Name SHARED_FORMULA_2: IF(#REF!="X",0,#REF!)
Name SHARED_FORMULA_2: IF(#REF!="X",0,#REF!)
Name SHARED_FORMULA_2: IF(#REF!="X",0,#REF!)
Name SHARED_FORMULA_2: IF(#REF!="X",0,#REF!)
Name SHARED_FORMULA_2: IF(#REF!="X",0,#REF!)
Name SHARED_FORMULA_3: #REF!+1
Name SHARED_FORMULA_3: #REF!+1
Name SHARED_FORMULA_3: #REF!+1
Name SHARED_FORMULA_3: #REF!+1
Name SHARED_FORMULA_3: #REF!+1
Name SHARED_FORMULA_3: #REF!+1
Name SHARED_FORMULA_4: #REF!+1
Name SHARED_FORMULA_4: #REF!+1
Name SHARED_FORMULA_4: #REF!+1
Name SHARED_FORMULA_4: #REF!+1
Name SHARED_FORMULA_4: #REF!+1
Name SHARED_FORMULA_4: #REF!+1
Name SHARED_FORMULA_5: #REF!+1
Name SHARED_FORMULA_5: #REF!+1
Name SHARED_FORMULA_5: #REF!+1
Name SHARED_FORMULA_5: #REF!+1

Sheet TEMPLATE_empty
A1: Data | B1: TIPO | C1: DESCRICAO | D1: Credito | E1: Debito | F1: Subtotais | G1: Check
C2: Dezembro/2019
A3: 43800 | B3: =TiposLancamentos!B77 -> Esporádico | C3: Teste | D3: 0.01 | G3: X
A4: 43800 | B4: =TiposLancamentos!B78 -> Diferenças | C4: Teste | E4: 0.01 | G4: X
C5: CORTE DE FATURAMENTO | G5: ???
G20: ???
C21: Totais: | D21: =SUM(D2:D20) -> 0.01 | E21: =SUM(E2:E20) -> 0.01
C22: Saldo Presumido | E22: =D21-E21 -> 0
D24: Limite | E24: Posição | F24: Disponivel
B25: Valor Parcial da Fatura | E25: =E22 -> 0 | F25: =D25+E25 -> 0

Sheet GUIDING
A1: TABLE_NAME | B1: LOADABLE | C1: ACCOUNTING | D1: CLEANABLE
A2: GUIDING | B2: X
A3: GamesWishList | B3: X
A4: TiposLancamentos | B4: X
A5: Despesas | B5: X | C5: X | D5: X
A6: Banco1MasterCard | B6: X | C6: X | D6: X
A7: Banespa | B7: X | C7: X | D7: X
A8: ItauUniclassVisa | B8: X | C8: X | D8: X
A9: ItaU | B9: X | C9: X | D9: X
A10: Amazon_Master | B10: X | C10: X | D10: X
A11: BTG_Pactual | B11: X | C11: X | D11: X
A12: Santander | B12: X | C12: X | D12: X
A13: CrediCard_Master | B13: X | C13: X | D13: X
A14: XP_Inv_ContaC | B14: X | C14: X | D14: X
A15: NUBank_Master | B15: X | C15: X | D15: X
A16: XP_Inv_Visa | B16: X | C16: X | D16: X
... A20: RealVisa | B20: X | C20: X | D20: X
A21: Faturas de Cartão | B21: X
A22: PortoSeguro_Master | B22: X | C22: X | D22: X
A23: MagaLu_Visa_Plat | B23: X | C23: X | D23: X
A24: Filmes | B24: X
A25: Livros | B25: X
A26: Games | B26: X
A27: Lista de CDs | B27: X
A28: Lista de DVDs | B28: X
A29: Amex | B29: X | C29: X | D29: X
A30: Amex_2010 | B30: X | C30: X | D30: X
A31: Banco1 | B31: X | C31: X | D31: X
A32: Carefour | B32: X | C32: X | D32: X
A33: CartaoSubMaRiNo | B33: X | C33: X | D33: X
A34: CEF | B34: X | C34: X | D34: X
A35: CitiBank | B35: X | C35: X | D35: X
A36: CitiBankMastercard | B36: X | C36: X | D36: X
A37: CitibankVisa | B37: X | C37: X | D37: X
A38: DigioVisa | B38: X | C38: X | D38: X
A39: HSBC | B39: X | C39: X | D39: X
A40: HSBCVisa | B40: X | C40: X | D40: X
... A44: Nubank_ContaC | B44: X | C44: X | D44: X
A45: Parcelamentos | B45: X
A46: PortoSeguroVisa | B46: X | C46: X | D46: X
A47: PoupanCaItau | B47: X | C47: X | D47: X
A48: Real_2007 | B48: X | C48: X | D48: X
A49: RealVisa_2007 | B49: X | C49: X | D49: X
A50: Santander_Master | B50: X | C50: X | D50: X
A51: Senhas | B51: X
A52: Trigg_Visa | B52: X | C52: X | D52: X
A53: UnibancoVisa | B53: X | C53: X | D53: X
A54: Vendas_diversas | B54: X
A55: Tarot_Decks | B55: X
A56: FGTS | B56: X
A57: Financ_NuBank_2025 | B57: X
A58: Vendas_diversas | B58: X
A59: Resumo_Parcelamentos | B59: X

Sheet General_din_reports
A1: DEST_TABLE | B1: SHEETY | C1: REPORT_NAME
A2: LIVING_COSTS | B2: DR_001 | C2: Custos Com Moradia
A3: FUNNY_COSTS | B3: DR_002 | C3: Entreterimento

Sheet DR_001
A1: COLUMN_NAME
A2: AnoMes
A3: =TiposLancamentos!B2 -> Telefonia
A4: =TiposLancamentos!B3 -> Internet
A5: =TiposLancamentos!B8 -> Aluguel
A6: =TiposLancamentos!B9 -> Condominio
A7: =TiposLancamentos!B12 -> IPTU
A8: =TiposLancamentos!B6 -> Energia Eletrica
A9: =TiposLancamentos!B11 -> Coleta Municipal Lixo
A10: =TiposLancamentos!B10 -> Distr. Água Municipal
A11: =TiposLancamentos!B35 -> Tv à Cabo
A12: =TiposLancamentos!B14 -> Gás de cozinha
A13: =TiposLancamentos!B13 -> Moradia

Sheet DR_002
A1: COLUMN_NAME
A2: AnoMes
A3: =TiposLancamentos!B25 -> CD_DVD_BD
A4: =TiposLancamentos!B26 -> LIVROS
A5: =TiposLancamentos!B27 -> Jornais e revistas
A6: =TiposLancamentos!B28 -> ComicBook
A7: =TiposLancamentos!B29 -> Mangá
A8: =TiposLancamentos!B30 -> Cinema
A9: =TiposLancamentos!B90 -> Locadora
A10: =TiposLancamentos!B45 -> Online Services
A11: =TiposLancamentos!B36 -> Playstation 2
A12: =TiposLancamentos!B37 -> Playstation 3
A13: =TiposLancamentos!B38 -> Playstation 4
A14: =TiposLancamentos!B39 -> Playstation 5
A15: =TiposLancamentos!B42 -> PSP FAT 1K
A16: =TiposLancamentos!B91 -> PSP Slim 2000
A17: =TiposLancamentos!B40 -> PS Vita Slim 2k
A18: =TiposLancamentos!B41 -> PSP Slim 3k

Sheet GamesWishList
A1: Title | B1: Platform | C1: comprado | D1: data | E1: onde
A2: Bayonetta 2 | B2: Nintendo Switch
A3: Bayonetta 3 | B3: Nintendo Switch
A4: Bloodrayne | B4: PS2 | C4: X | D4: 45563 | E4: eBay.com US&A
A5: Bloodrayne 2 | B5: PS2 | C5: X | D5: 45549 | E5: Game collection Show
A6: Castlevania: lament of Innocence | B6: PS2 | C6: X | D6: 45917 | E6: gvl Games - whatsApp
A7: Devil May Cry | B7: PS2 | C7: X | D7: 45549 | E7: Game collection Show
A8: Devil May Cry 2 JP | B8: PS2 | C8: X | D8: 45549 | E8: Game collection Show
A9: Devil May Cry 3 Dante´s Awakening | B9: PS2 | C9: X | D9: 45549 | E9: Game collection Show
A10: Final Fantasy X | B10: PS2 | C10: X | D10: 45780 | E10: Pororó Games no Yabacura
A11: Final Fantasy X-2 | B11: PS2 | C11: X | D11: 45780 | E11: Old Tete Sound no Yabacuara
A12: Final Fantasy XII | B12: PS2 | C12: X | D12: 45554 | E12: eBay.com US&A
A13: Final Fantasy XII -COM LATA E DVD EXTRA | B13: PS2 | C13: X | D13: 45598 | E13: Number 1 Games na ExpoCanal3
A14: God of War (2005) | B14: PS2 | C14: X | D14: 45061 | E14: eBay.com US&A
A15: God of War II (2007) | B15: PS2 | C15: X | D15: 45058 | E15: eBay.com US&A
... A32: Resident Evil 4 Greatest Hits | B32: PS2 | C32: X | D32: 45534 | E32: AdautoWorld Colecionaveis
A33: Spawn: Armageddon | B33: PS2
A34: Syphn filterDark Mirror | B34: PS2 | C34: X | D34: 45549 | E34: Game collection Show
A35: Tourist trophy | B35: PS2 | C35: X | D35: 46058 | E35: Direto do Nelson Loia JR
A36: Alice: Madness Returns | B36: PS3 | C36: X | D36: 45078 | E36: Gabriel FB Market
A37: Alone In The Dark Inferno | B37: PS3 | C37: X | D37: 45068 | E37: MeuGameUsado
A38: Anarchy Reigns | B38: PS3 | C38: X | D38: 46004 | E38: HouseOfGames Taubate : Yabacuara
A39: Assassin´s Creed´s II | B39: PS3 | C39: x | D39: 45137 | E39: RetroCon 2023
A40: Assassin´s Creed´s III | B40: PS3 | C40: X | D40: 45353 | E40: Grupo Facebook PS3
A41: Assassin´s Creed´s IV Black Flag | B41: PS3 | C41: X | D41: 45353 | E41: Grupo Facebook PS3
A42: Asura's Wrath | B42: PS3 | C42: X | D42: 45078 | E42: Mercadolibre
A43: Bayonetta | B43: PS3 | C43: X | D43: 45182 | E43: Mercadolibre
A44: Berserk and the band of the Hawk | B44: PS3
A45: Beyond: Two Souls | B45: PS3 | C45: X | D45: 45059 | E45: Dika Games
A46: Bioshock | B46: PS3 | C46: X | D46: 45111 | E46: Anderson Pinto
A47: Bioshock Infinite | B47: PS3 | C47: X | D47: 45059 | E47: Dika Games
A48: Blades of Time | B48: PS3 | C48: X | D48: 45068 | E48: MeuGameUsado
A49: Body Count | B49: PS3 | C49: X | D49: 45742 | E49: Pereira Retro Games
A50: Bound by Flame | B50: PS3 | C50: X | D50: 45203 | E50: Mercadolibre
A51: Brütal Legend | B51: PS3 | C51: X | D51: 45073 | E51: Dika Games
A52: Bullet Storm | B52: PS3 | C52: X | D52: 45682 | E52: Natan Games no Atrium
A53: BulletStorm (Alternative cover) | B53: PS3 | C53: X | D53: 45789 | E53: Glaukera Games
A54: Burnout Paradise | B54: PS3
A55: Castlevania Lord of The Shadows | B55: PS3 | C55: X | D55: 45549 | E55: Game collection Show
A56: Castlevania Lord of The Shadows 2 | B56: PS3 | C56: X | D56: 45549 | E56: Game collection Show
A57: Catherine (EUR) | B57: PS3 | C57: X | D57: 45852 | E57: Glaukera Games PS3
A58: Clive Barker's Jericho | B58: PS3 | C58: X | D58: 45885 | E58: Pororó Classic Games no GCSHOW Yabacuara
A59: Conan | B59: PS3 | C59: X | D59: 45116 | E59: João Paulo
A60: Cyrsis 3 | B60: PS3 | C60: X | D60: 45619 | E60: MarcosGames - Feira Jabaquara
A61: Damnation | B61: PS3 | C61: X | D61: 46004 | E61: HouseOfGames Taubate : Yabacuara
A62: Dark Sector | B62: PS3 | C62: X | D62: 45059 | E62: Dika Games
A63: DarkSiders | B63: PS3 | C63: X | D63: 45059 | E63: Dika Games
A64: Dead Space | B64: PS3 | C64: x | D64: 45372 | E64: FaceBook Market Rodrigo Moska
A65: Dead to rights retribution | B65: PS3
A66: Deadfall Adventures | B66: PS3
A67: Deadfall Adventurs: the fall of Atlantis | B67: PS3
A68: Deadly premonition | B68: ps3
A69: Diablo III | B69: PS3 | C69: X | D69: 45549 | E69: Game collection Show
A70: DmC | B70: PS3 | C70: X | D70: 45475 | E70: MeuGameUsado
A71: Eat Lead | B71: PS3 | C71: X | D71: 46004 | E71: HouseOfGames Taubate : Yabacuara
A72: Enchanted Arms | B72: PS3
A73: Enslaved | B73: PS3 | C73: X | D73: 45068 | E73: MeuGameUsado
A74: Final Fantasy X/X-2 | B74: PS3 | C74: x | D74: 45796 | E74: Glauquera direto
A75: Final Fantasy XIII | B75: PS3 | C75: X | D75: 45682 | E75: Ronirvi Games Atriu
A76: Final Fantasy XIII-2 | B76: PS3 | C76: X | D76: 45682 | E76: Ronirvi Games Atriu
A77: Folklore | B77: PS3 | C77: X | D77: 45100 | E77: Leandro Souza Bass OLX
A78: Genji Days of the blade | B78: PS3 | C78: x | D78: 45796 | E78: Glauquera direto
A79: God Mode | B79: PS3
A80: Gran Turismo 5 XL Editiom | B80: PS3 | C80: X | D80: 45745 | E80: Golden Games 90 na GCShow
A81: Guitar Hero aEROsMITH | B81: PS3 | C81: X | D81: 45549 | E81: Game collection Show
A82: Guitar Hero V - Warriors of rock | B82: PS3 | C82: X | D82: 45549 | E82: Game collection Show
A83: Heavy Rain | B83: PS3 | C83: X | D83: 45073 | E83: storm Games centro
A84: Hitman Absolution | B84: PS3 | C84: X | D84: 45711 | E84: Ronivir Games Atrium
A85: Hunted: The Demon's Forge | B85: PS3 | C85: X | D85: 46004 | E85: HouseOfGames Taubate : Yabacuara
A86: I Am Alive | B86: PS3
A87: ICO & Shadow of The Colossus Collection | B87: PS3 | C87: X | D87: 45059 | E87: Dika Games
A88: inFamous | B88: PS3 | C88: X | D88: 45682 | E88: Ronirvi Games Atriu
A89: inFamous PS3 | B89: PS3 | C89: X | D89: 45734 | E89: Storm games do centro
A90: inFamous Second Son Limited Ed. | B90: PS3 | C90: X | D90: 45682 | E90: Ronirvi Games Atriu
A91: inFamous2 | B91: PS3 | C91: X | D91: 45682 | E91: G3 Games Atrium
A92: L.A. Noir | B92: PS3 | C92: X | D92: 45570 | E92: GameTechZone
A93: Lightning Returns: Final Fantasy XIII | B93: PS3 | C93: X | D93: 45710 | E93: CW Games no Atrium
A94: Lollipop ChainSaw | B94: PS3 | C94: X | D94: 45100 | E94: Leandro Souza Bass OLX
A95: Marvel Ultimate Alliance II | B95: PS3 | C95: X | D95: 45927 | E95: Pororó Games no Yabacura
A96: Mercenaries 2 World in Flames | B96: PS3 | C96: X | D96: 45872 | E96: Gold Games em SCS
A97: Metal Gear Solid 4 | B97: PS3 | C97: X | D97: 45059 | E97: Dika Games
A98: Metal Gear V Ground Zero | B98: PS3 | C98: x | D98: 45633 | E98: Ferinha do Jabaquara
... A101: Mirror's Edge | B101: PS3 | C101: X | D101: 45381 | E101: GameTechZone
A102: Murdered: Soul Suspect | B102: PS3
A103: Nail'd | B103: PS3
A104: Need For Speed: Hot Pursuit | B104: PS3 | C104: X | D104: 45745 | E104: Pororó Classic Games no GCSHOW
A105: Need For Speed: Most Wanted | B105: PS3
A106: Nier | B106: PS3 | C106: X | D106: 45140 | E106: João Paulo
A107: Outlast | B107: PS3
A108: PlayStation Move Sharp Shooter | B108: PS3 | C108: X | D108: 45480 | E108: Evento Galpão Games
A109: Prince of Persia | B109: PS3 | C109: X | D109: 45111 | E109: Anderson Pinto
A110: Quantun Theory | B110: PS3 | C110: X | D110: 45140 | E110: João Paulo
A111: Red Dead Redemption | B111: PS3 | C111: X | D111: 45280 | E111: Do Suguimoto
A112: Remember ME | B112: PS3 | C112: X | D112: 45059 | E112: Dika Games
A113: Resident Evil 5 | B113: PS3 | C113: x | D113: 45475 | E113: MeuGameUsado
A114: Resonance Of Fate | B114: PS3 | C114: x | D114: 45203 | E114: Mercadolibre
A115: Rock Band | B115: PS3 | C115: X | D115: 45742 | E115: Pereira RetroGames
A116: Rock Band 2 | B116: PS3 | C116: X | D116: 45742 | E116: Pereira RetroGames
A117: Shadows of the damned | B117: PS3 | C117: X | D117: 45073 | E117: Dika Games
A118: Siren Blood Curse | B118: PS3
...

Sheet Tarot_Decks
A1: # | B1: Nome do Deck | C1: Editora | D1: Autor(es) | E1: Livreto | F1: Digital | G1: Data da Compra | H1: Valor | I1: Onde foi Adquirido | J1: Tipo | K1: Chave Primária
A2: 1 | B2: Marselha Generico | C2: Alfabeto | D2: Brigite Zuraá | E2: SIM | F2: SIM | G2: 41836 | H2: 44.9 | I2: Saraiva de SCS | J2: Full Tarot Deck | K2: =CONCATENATE(TEXT(A2,"0000"),(TEXT(G2,"aaaammdd"))) -> 000120140716
A3: 2 | B3: O Tarô Universal de Waite | C3: Isis Brasil | D3: Edith Waite | E3: SIM | F3: Não | G3: 41836 | H3: 44.9 | I3: Saraiva de SCS | J3: Full Tarot Deck | K3: =CONCATENATE(TEXT(A3,"0000"),(TEXT(G3,"aaaammdd"))) -> 000220140716
A4: 3 | B4: Crowley Thoth | C4: US Games Inc. | D4: Aleister Crowley / Frieda Harris | E4: SIM | F4: SIM | G4: 41878 | H4: 74 | I4: Simbólika | J4: Full Tarot Deck | K4: =CONCATENATE(TEXT(A4,"0000"),(TEXT(G4,"aaaammdd"))) -> 000320140827
A5: 4 | B5: Renaissance | C5: US Games Inc. | D5: Brian Willians | E5: SIM | F5: SIM | G5: 41878 | H5: 74 | I5: Simbólika | J5: Full Tarot Deck | K5: =CONCATENATE(TEXT(A5,"0000"),(TEXT(G5,"aaaammdd"))) -> 000420140827
A6: 5 | B6: Mitológico | C6: Madras Brasil | D6: Juliet Sharman-Burke, Liz Greene | E6: SIM | F6: Não | G6: 41880 | H6: 72.9 | I6: Madras da Bienal do Livro | J6: Full Tarot Deck | K6: =CONCATENATE(TEXT(A6,"0000"),(TEXT(G6,"aaaammdd"))) -> 000520140829
A7: 6 | B7: Nei Naiff | C7: Nova Era | D7: Thais Linhares / Nei Naiff | E7: SIM | F7: Não | G7: 41900 | H7: 69 | I7: Direto da Editora | J7: Full Tarot Deck | K7: =CONCATENATE(TEXT(A7,"0000"),(TEXT(G7,"aaaammdd"))) -> 000620140918
A8: 7 | B8: Tarô Intuitivo | C8: Isis Brasil | D8: DAVID MILES | E8: SIM | F8: Não | G8: 41974 | H8: 59.92 | I8: Simbólika | J8: Full Tarot Deck | K8: =CONCATENATE(TEXT(A8,"0000"),(TEXT(G8,"aaaammdd"))) -> 000720141201
A9: 8 | B9: Lo Scarabeo | C9: Lo Scarabeo | D9: Mark McElroy, Anna Lazzarini | E9: SIM | F9: SIM | G9: 41974 | H9: 71.25 | I9: Simbólika | J9: Full Tarot Deck | K9: =CONCATENATE(TEXT(A9,"0000"),(TEXT(G9,"aaaammdd"))) -> 000820141201
A10: 9 | B10: Rider Waite classical Original Tarot | C10: US Games Inc. | D10: A.E. Waite / P. C. Smith | E10: SIM | F10: SIM | G10: 41984 | H10: 72 | I10: US Games Brasil | J10: Full Tarot Deck | K10: =CONCATENATE(TEXT(A10,"0000"),(TEXT(G10,"aaaammdd"))) -> 000920141211
A11: 10 | B11: Hermetic Kaballah Tarot 2 | C11: Daemon Editora | D11: Marcelo Deldebbio / Rodrigo Grola | E11: Não | F11: Não | G11: 41996 | H11: 103.7 | I11: Daemon Editora | J11: Full Tarot Deck | K11: =CONCATENATE(TEXT(A11,"0000"),(TEXT(G11,"aaaammdd"))) -> 001020141223
A12: 11 | B12: Fenestra tarot | C12: US Games Inc. | D12: Chatriya | E12: SIM | F12: SIM | G12: 42020 | H12: 69 | I12: Simbólika | J12: Full Tarot Deck | K12: =CONCATENATE(TEXT(A12,"0000"),(TEXT(G12,"aaaammdd"))) -> 001120150116
A13: 12 | B13: Namur TaroT | C13: N/A | D13: Namur Gopalla / Martha Leyrós | E13: Não | F13: Não | G13: 42059 | H13: 100 | I13: Direto do Autor | J13: Full Tarot Deck | K13: =CONCATENATE(TEXT(A13,"0000"),(TEXT(G13,"aaaammdd"))) -> 001220150224
A14: 13 | B14: The B.O.T.A. Full Tarot Deck | C14: B.O.T.A. | E14: Não | F14: Não | G14: 42102 | H14: 69.93 | I14: Direto do Autor | J14: Full Tarot Deck | K14: =CONCATENATE(TEXT(A14,"0000"),(TEXT(G14,"aaaammdd"))) -> 001320150408
A15: 14 | B15: Visconti Sforza | C15: US Games Inc. | D15: Pierpont Morgan | E15: SIM | F15: SIM | G15: 42113 | H15: 200 | I15: O Argonauta - Feira Mistica Paulista | J15: Full Tarot Deck | K15: =CONCATENATE(TEXT(A15,"0000"),(TEXT(G15,"aaaammdd"))) -> 001420150419
A16: 15 | B16: Radiant Rider Waite (Lata) Cristaiane | C16: US Games Inc. | D16: A.E. Waite / P. C. Smith | E16: SIM | F16: SIM | G16: 42113 | H16: 80 | I16: O Argonauta - Feira Mistica Paulista | J16: Full Tarot Deck | K16: =CONCATENATE(TEXT(A16,"0000"),(TEXT(G16,"aaaammdd"))) -> 001520150419
A17: 16 | B17: BIG B.O.T.A. Major Arcanas | C17: B.O.T.A. | E17: Não | F17: Não | G17: 42119 | H17: 88.34 | I17: Direto do Autor | J17: Full Tarot Deck | K17: =CONCATENATE(TEXT(A17,"0000"),(TEXT(G17,"aaaammdd"))) -> 001620150425
A18: 17 | B18: Pirates Tarot | C18: Lo Scarabeo | D18: Bepi Vigna, Michele Benevento, | E18: SIM | F18: SIM | G18: 42122 | H18: 63.81 | I18: Editora Pressagio | J18: Full Tarot Deck | K18: =CONCATENATE(TEXT(A18,"0000"),(TEXT(G18,"aaaammdd"))) -> 001720150428
A19: 18 | B19: Dark Royo tarot | C19: Lo Scarabeo | D19: Luis Royo | E19: SIM | F19: SIM | G19: 42122 | H19: 63.81 | I19: Editora Pressagio | J19: Full Tarot Deck | K19: =CONCATENATE(TEXT(A19,"0000"),(TEXT(G19,"aaaammdd"))) -> 001820150428
A20: 19 | B20: The Secrets Tarot | C20: Lo Scarabeo | D20: Marco Nizzoli | E20: SIM | F20: SIM | G20: 42122 | H20: 63.81 | I20: Editora Pressagio | J20: Full Tarot Deck | K20: =CONCATENATE(TEXT(A20,"0000"),(TEXT(G20,"aaaammdd"))) -> 001920150428
A21: 20 | B21: The Golden TSAR Tarot | C21: Lo Scarabeo | D21: Pietro Alligo, Atanas A. Atanassov | E21: SIM | F21: SIM | G21: 42133 | H21: 0 | I21: Presente | J21: Full Tarot Deck | K21: =CONCATENATE(TEXT(A21,"0000"),(TEXT(G21,"aaaammdd"))) -> 002020150509
A22: 21 | B22: Golden Dawn Tarot | C22: US Games Inc. | D22: Robert Wang / Israel Regardie | E22: SIM | F22: SIM | G22: 42176 | H22: 100 | I22: Simbólika | J22: Full Tarot Deck | K22: =CONCATENATE(TEXT(A22,"0000"),(TEXT(G22,"aaaammdd"))) -> 002120150621
A23: 22 | B23: New Visions of Rider Waite | C23: Lo Scarabeo | D23: Pietro Alligo, Raul Cestaro, Gianluca Cestaro | E23: SIM | F23: SIM | G23: 42176 | H23: 82 | I23: Simbólika | J23: Full Tarot Deck | K23: =CONCATENATE(TEXT(A23,"0000"),(TEXT(G23,"aaaammdd"))) -> 002220150621
A24: 23 | B24: Crowley Thoth Grande | C24: US Games Inc. | D24: Aleister Crowley / Frieda Harris | E24: SIM | F24: SIM | G24: 42183 | H24: 150 | I24: O Argonauta - Feira Mistica Paulista | J24: Full Tarot Deck | K24: =CONCATENATE(TEXT(A24,"0000"),(TEXT(G24,"aaaammdd"))) -> 002320150628
A25: 24 | B25: Russian Tarot of St. Petersburg Deck | C25: US Games Inc. | D25: Yury Shakov | E25: SIM | F25: SIM | G25: 42183 | H25: 100 | I25: O Argonauta - Feira Mistica Paulista | J25: Full Tarot Deck | K25: =CONCATENATE(TEXT(A25,"0000"),(TEXT(G25,"aaaammdd"))) -> 002420150628
A26: 25 | B26: ISIS Version of Tarot de Marseille | C26: ISIS Osiris | D26: TADAHIRO ONUMA / SUMI ONUMA | E26: Não | F26: Não | G26: 42145 | H26: 127.2 | I26: Direto do Autor | J26: Full Tarot Deck | K26: =CONCATENATE(TEXT(A26,"0000"),(TEXT(G26,"aaaammdd"))) -> 002520150521
A27: 26 | B27: Harmonious Tarot - Taro da Harmonia | C27: Lo Scarabeo | D27: Walter Crane, Ernest Fitzpatrick | E27: SIM | F27: SIM | G27: 42212 | H27: 98 | I27: Simbólika | J27: Full Tarot Deck | K27: =CONCATENATE(TEXT(A27,"0000"),(TEXT(G27,"aaaammdd"))) -> 002620150727
A28: 27 | B28: Tarot of the Mystic Spiral - Taro da Espiral Mistica | C28: Lo Scarabeo | D28: Giovanni Pelosini, Giuseppe Palumbo | E28: SIM | F28: SIM | G28: 42212 | H28: 79 | I28: Simbólika | J28: Full Tarot Deck | K28: =CONCATENATE(TEXT(A28,"0000"),(TEXT(G28,"aaaammdd"))) -> 002720150727
A29: 28 | B29: El Gran Tarot Esoterico | C29: Naipes Heraclio Fournier | E29: SIM | F29: SIM | G29: 42212 | H29: 77.4 | I29: Simbólika | J29: Full Tarot Deck | K29: =CONCATENATE(TEXT(A29,"0000"),(TEXT(G29,"aaaammdd"))) -> 002820150727
A30: 29 | B30: The Hermetic Tarot from Golden Dawn | C30: US Games Inc. | D30: Godfrey Dowson | E30: SIM | F30: SIM | G30: 42218 | H30: 145 | I30: O Argonauta - Feira Mistica Paulista | J30: Full Tarot Deck | K30: =CONCATENATE(TEXT(A30,"0000"),(TEXT(G30,"aaaammdd"))) -> 002920150802
A31: 30 | B31: Symbolon Grande | C31: AGM Müller Urania | D31: Ingrid Zinnel, Peter Orban & Thea Weller | E31: SIM | F31: SIM | G31: 42218 | H31: 130 | I31: O Argonauta - Feira Mistica Paulista | J31: Oracle 78 Cards | K31: =CONCATENATE(TEXT(A31,"0000"),(TEXT(G31,"aaaammdd"))) -> 003020150802
A32: 31 | B32: Tarot de Marseille de Francois Chosson 1736 | C32: Yves Reynaud | D32: Yves Reynaud | E32: Não | F32: Não | G32: 42225 | H32: 200 | I32: O Argonauta - Feira Mistica Paulista | J32: Full Tarot Deck | K32: =CONCATENATE(TEXT(A32,"0000"),(TEXT(G32,"aaaammdd"))) -> 003120150809
A33: 32 | B33: Le Tarot de Marseille | C33: Naipes Heraclio Fournier | E33: SIM | F33: SIM | G33: 42240 | H33: 93 | I33: Simbólika | J33: Full Tarot Deck | K33: =CONCATENATE(TEXT(A33,"0000"),(TEXT(G33,"aaaammdd"))) -> 003220150824
A34: 33 | B34: Morgan-Greer | C34: US Games Inc. | D34: Bill F. Greer with Lloyd Morgan | E34: SIM | F34: SIM | G34: 42248 | H34: 89 | I34: O Argonauta - Feira Mistica Paulista | J34: Full Tarot Deck | K34: =CONCATENATE(TEXT(A34,"0000"),(TEXT(G34,"aaaammdd"))) -> 003320150901
A35: 34 | B35: Rider Waite Tarot | C35: US Games Inc. | D35: Pamela Colman Smith | E35: SIM | F35: SIM | G35: 42248 | H35: 89 | I35: O Argonauta - Feira Mistica Paulista | J35: Full Tarot Deck | K35: =CONCATENATE(TEXT(A35,"0000"),(TEXT(G35,"aaaammdd"))) -> 003420150901
A36: 35 | B36: Tarot de marseille 1760 | C36: CAMOIN | D36: Alexandre JODOROWSKY / Philippe CAMOIN | E36: SIM | F36: SIM | G36: 42256 | H36: 174.9 | I36: Direto com o Editor | J36: Full Tarot Deck | K36: =CONCATENATE(TEXT(A36,"0000"),(TEXT(G36,"aaaammdd"))) -> 003520150909
A37: 36 | B37: Haindl Tarot | C37: US Games Inc. | D37: Hermann Haindl | E37: SIM | F37: SIM | G37: 42265 | H37: 79 | I37: Casa de Bruxa de Sto. André | J37: Full Tarot Deck | K37: =CONCATENATE(TEXT(A37,"0000"),(TEXT(G37,"aaaammdd"))) -> 003620150918
A38: 37 | B38: O Tarot dos Boêmios Tarot Papus-Goulinat | C38: N/A | D38: Papus | E38: Não | F38: Não | G38: 42266 | H38: 40 | I38: Sebo Poesia Santo André | J38: Full Tarot Deck | K38: =CONCATENATE(TEXT(A38,"0000"),(TEXT(G38,"aaaammdd"))) -> 003720150919
A39: 38 | B39: Marselha Generico | C39: Editora Planeta | E39: Não | F39: Não | G39: 42266 | H39: 15 | I39: Sebo Poesia Santo André | J39: Full Tarot Deck | K39: =CONCATENATE(TEXT(A39,"0000"),(TEXT(G39,"aaaammdd"))) -> 003820150919
A40: 39 | B40: Tarot Universal Salvador dalí | C40: Ever Green | D40: Johannes Iebig | E40: SIM | F40: Não | G40: 42270 | H40: 95 | I40: Sebo Poesia Santo André | J40: Full Tarot Deck | K40: =CONCATENATE(TEXT(A40,"0000"),(TEXT(G40,"aaaammdd"))) -> 003920150923
A41: 40 | B41: Hanson-Roberts Tarot | C41: US Games Inc. | D41: Mary Hanson-Roberts | E41: SIM | F41: SIM | G41: 42274 | H41: 110 | I41: O Argonauta - Feira Mistica Paulista | J41: Full Tarot Deck | K41: =CONCATENATE(TEXT(A41,"0000"),(TEXT(G41,"aaaammdd"))) -> 004020150927
A42: 41 | B42: Deviant Moon Tarot Borderless Edition | C42: US Games Inc. | D42: Patrick Valenza | E42: SIM | F42: SIM | G42: 42274 | H42: 110 | I42: O Argonauta - Feira Mistica Paulista | J42: Full Tarot Deck | K42: =CONCATENATE(TEXT(A42,"0000"),(TEXT(G42,"aaaammdd"))) -> 004120150927
A43: 42 | B43: The Golden Tarot | C43: US Games Inc. | D43: Kat Black | E43: SIM | F43: Não | G43: 42274 | H43: 135 | I43: O Argonauta - Feira Mistica Paulista | J43: Full Tarot Deck | K43: =CONCATENATE(TEXT(A43,"0000"),(TEXT(G43,"aaaammdd"))) -> 004220150927
A44: 43 | B44: O Livro de Thoth Etteilla | C44: Madras Brasil | D44: Etteilla | E44: SIM | F44: Não | G44: 42280 | H44: 40 | I44: Sebo Poesia Santo André | J44: Full Tarot Deck | K44: =CONCATENATE(TEXT(A44,"0000"),(TEXT(G44,"aaaammdd"))) -> 004320151003
A45: 44 | B45: The Archeon Tarot | C45: US Games Inc. | D45: Timoty Lantz | E45: SIM | F45: SIM | G45: 42287 | H45: 110 | I45: Casa de Bruxa de Sto. André | J45: Full Tarot Deck | K45: =CONCATENATE(TEXT(A45,"0000"),(TEXT(G45,"aaaammdd"))) -> 004420151010
A46: 45 | B46: O Tarot Illuminati | C46: Madras Brasil | D46: Kim Huggens & Erik C Dunne | E46: SIM | F46: Não | G46: 42297 | H46: 29.91 | I46: Amazon Brasil | J46: Full Tarot Deck | K46: =CONCATENATE(TEXT(A46,"0000"),(TEXT(G46,"aaaammdd"))) -> 004520151020
A47: 46 | B47: O tarô carbônico | C47: Gnose Brasil | D47: Adriano Camargo Monteiro | E47: SIM | F47: Não | G47: 42297 | H47: 40.8 | I47: Simbólika | J47: Major Arcanas only | K47: =CONCATENATE(TEXT(A47,"0000"),(TEXT(G47,"aaaammdd"))) -> 004620151020
A48: 47 | B48: The Labyrinth Tarot | C48: Naipes Heraclio Fournier | D48: Luis Royo | E48: SIM | F48: SIM | G48: 42297 | H48: 98 | I48: Simbólika | J48: Full Tarot Deck | K48: =CONCATENATE(TEXT(A48,"0000"),(TEXT(G48,"aaaammdd"))) -> 004720151020
A49: 48 | B49: Medieval tarot | C49: Lo Scarabeo | D49: Guido Zirbodi Marchesi | E49: SIM | F49: SIM | G49: 42297 | H49: 98 | I49: Simbólika | J49: Full Tarot Deck | K49: =CONCATENATE(TEXT(A49,"0000"),(TEXT(G49,"aaaammdd"))) -> 004820151020
A50: 49 | B50: Kama Sutra Tarot | C50: Madras Brasil | D50: A.R. Madan | E50: SIM | F50: Não | G50: 42308 | H50: 30 | I50: Sebo Poesia Santo André | J50: Full Tarot Deck | K50: =CONCATENATE(TEXT(A50,"0000"),(TEXT(G50,"aaaammdd"))) -> 004920151031
A51: 50 | B51: Mantegna Tarot | C51: Lo Scarabeo | D51: Könings Furt | E51: SIM | F51: Não | G51: 42318 | H51: 0 | I51: Presente | J51: Full Tarot Deck | K51: =CONCATENATE(TEXT(A51,"0000"),(TEXT(G51,"aaaammdd"))) -> 005020151110
... A66: 65 | B66: Tarô de Marselha | C66: Madras Brasil | D66: Vera Martins | E66: SIM | F66: Não | G66: 42389 | H66: 40.83 | I66: Amazon Brasil | J66: Major Arcanas only | K66: =CONCATENATE(TEXT(A66,"0000"),(TEXT(G66,"aaaammdd"))) -> 006520160120
A67: 66 | B67: Ancient Enlightened Tarot (Sola Busca) | C67: Lo Scarabeo | E67: SIM | F67: SIM | G67: 42428 | H67: 150 | I67: Exotérica RJ | J67: Full Tarot Deck | K67: =CONCATENATE(TEXT(A67,"0000"),(TEXT(G67,"aaaammdd"))) -> 006620160228
A68: 67 | B68: Tarot de Thoth de Aleister Crowley | C68: AGM Müller Urania | D68: Aleister Crowley / Frieda Harris | E68: SIM | F68: SIM | G68: 42428 | H68: 150 | I68: Exotérica RJ | J68: Full Tarot Deck | K68: =CONCATENATE(TEXT(A68,"0000"),(TEXT(G68,"aaaammdd"))) -> 006720160228
A69: 68 | B69: Merlin Tarot | C69: Aquarian Press | D69: RJ Stewart | E69: SIM | F69: Não | G69: 42426 | H69: 110 | I69: Sebo Poesia Santo André | J69: Full Tarot Deck | K69: =CONCATENATE(TEXT(A69,"0000"),(TEXT(G69,"aaaammdd"))) -> 006820160226
A70: 69 | B70: The Pamela Colman Smith Commemorative Set | C70: US Games Inc. | D70: A.E. Waite / P. C. Smith | E70: Não | F70: Não | G70: 42429 | H70: 179 | I70: O Argonauta - Direto | J70: Full Tarot Deck | K70: =CONCATENATE(TEXT(A70,"0000"),(TEXT(G70,"aaaammdd"))) -> 006920160229
A71: 70 | B71: Pixie´s Astounding Lenormand - Em Lata | C71: US Games Inc. | D71: Edmund Zebrowski & Pamela Colman Smith | E71: SIM | F71: Não | G71: 42436 | H71: 145.8 | I71: Simbólika | J71: Full Tarot Deck | K71: =CONCATENATE(TEXT(A71,"0000"),(TEXT(G71,"aaaammdd"))) -> 007020160307
A72: 71 | B72: Baralho para ver a Sorte | C72: Copag Brasil | D72: Copag Brasil / Emanuel J. Santos | E72: SIM | F72: SIM | G72: 42448 | H72: 0 | I72: Espaço Merkaba | J72: Lenormand | K72: =CONCATENATE(TEXT(A72,"0000"),(TEXT(G72,"aaaammdd"))) -> 007120160319
A73: 72 | B73: The New Palladini tarot | C73: US Games Inc. | D73: David Palladini | E73: SIM | F73: SIM | G73: 42464 | H73: 155 | I73: Simbólika | J73: Full Tarot Deck | K73: =CONCATENATE(TEXT(A73,"0000"),(TEXT(G73,"aaaammdd"))) -> 007220160404
A74: 73 | B74: Old English Tarot | C74: US Games Inc. | D74: Maggie Kneen | E74: SIM | F74: SIM | G74: 42490 | H74: 70 | I74: Espaço Merkaba | J74: Full Tarot Deck | K74: =CONCATENATE(TEXT(A74,"0000"),(TEXT(G74,"aaaammdd"))) -> 007320160430
A75: 74 | B75: William Blake Tarot of the Creative Imagination | C75: Harper san Francisco | D75: Ed Buryn / Mary K. Greer | E75: SIM | F75: SIM | G75: 42495 | H75: 230 | I75: Sebo Poesia Santo André | J75: Full Tarot Deck | K75: =CONCATENATE(TEXT(A75,"0000"),(TEXT(G75,"aaaammdd"))) -> 007420160505
A76: 75 | B76: Antica Sibilla Italiana | C76: Lo Scarabeo | D76: Gina Pace / Franco Rivolli | E76: Não | F76: Não | G76: 42515 | H76: 64 | I76: Simbólika | J76: 54 Cards | K76: =CONCATENATE(TEXT(A76,"0000"),(TEXT(G76,"aaaammdd"))) -> 007520160525
A77: 76 | B77: Ancient Italian Tarot | C77: Lo Scarabeo | D77: Cartiera Italiana | E77: SIM | F77: SIM | G77: 42515 | H77: 100 | I77: Simbólika | J77: Full Tarot Deck | K77: =CONCATENATE(TEXT(A77,"0000"),(TEXT(G77,"aaaammdd"))) -> 007620160525
A78: 77 | B78: Decameron Tarot | C78: Lo Scarabeo | D78: Luciano Spadanuda, Giacinto Gaudenzi | E78: SIM | F78: Não | G78: 42532 | H78: 99 | I78: Pressagio Editora - Cartomância | J78: Full Tarot Deck | K78: =CONCATENATE(TEXT(A78,"0000"),(TEXT(G78,"aaaammdd"))) -> 007720160611
A79: 78 | B79: Casanova Tarot | C79: Lo Scarabeo | D79: Giacomo Casanova, Mario Pignatiello, Luca Raimondo | E79: SIM | F79: Não | G79: 42532 | H79: 99 | I79: Pressagio Editora - Cartomância | J79: Full Tarot Deck | K79: =CONCATENATE(TEXT(A79,"0000"),(TEXT(G79,"aaaammdd"))) -> 007820160611
... A123: 122 | B123: The Druid Craft Tarot: Use the Magic of Wicca and Druidry to Guide Your Life | C123: St. Martin's Press | D123: Philip Carr-Gomm (Autor), Stephanie Carr-Gomm (Autor), William Worthington (Ilustrador) | E123: SIM | F123: Não | G123: 42958 | H123: 66.01 | I123: Amazon Brasil | J123: Full Tarot Deck | K123: =CONCATENATE(TEXT(A123,"0000"),(TEXT(G123,"aaaammdd"))) -> 012220170811
A124: 123 | B124: Tarot Estilo Marsellés | D124: Belén Lombardi / Agustín Murias | E124: SIM | F124: Não | G124: 42974 | H124: 90 | I124: Feira San Telmo Argentina | J124: Full Tarot Deck | K124: =CONCATENATE(TEXT(A124,"0000"),(TEXT(G124,"aaaammdd"))) -> 012320170827
A125: 124 | B125: Crowley Thoth Grande Green | C125: US Games Inc. | D125: Aleister Crowley / Frieda Harris | E125: SIM | F125: SIM | G125: 42980 | H125: 520 | I125: Leonardo Chioda | J125: Full Tarot Deck | K125: =CONCATENATE(TEXT(A125,"0000"),(TEXT(G125,"aaaammdd"))) -> 012420170902
A126: 125 | B126: Legacy Of The Divine Tarot | C126: Llewellyn | D126: Ciro Marchetti | E126: SIM | F126: Não | G126: 42999 | H126: 139 | I126: Amazon Brasil | J126: Full Tarot Deck | K126: =CONCATENATE(TEXT(A126,"0000"),(TEXT(G126,"aaaammdd"))) -> 012520170921
A127: 126 | B127: Legend: Arthurian Tarot | C127: Llewellyn | D127: Anna-Marie Ferguson | E127: SIM | F127: Não | G127: 42999 | H127: 112.23 | I127: Amazon Brasil | J127: Full Tarot Deck | K127: =CONCATENATE(TEXT(A127,"0000"),(TEXT(G127,"aaaammdd"))) -> 012620170921
A128: 127 | B128: Tarot of Dreams | C128: US Games Inc. | D128: Ciro Marchetti / Lee Bursten | E128: SIM | F128: Não | G128: 43001 | H128: 145 | I128: Us Games Brasil - Mistic Fair - Paulista | J128: Full Tarot Deck | K128: =CONCATENATE(TEXT(A128,"0000"),(TEXT(G128,"aaaammdd"))) -> 012720170923
A129: 128 | B129: Smith-Waite Tarot Deck Borderless | C129: US Games Inc. | D129: A.E. Waite / P. C. Smith | E129: SIM | F129: Não | G129: 43001 | H129: 110 | I129: Us Games Brasil - Mistic Fair - Paulista | J129: Full Tarot Deck | K129: =CONCATENATE(TEXT(A129,"0000"),(TEXT(G129,"aaaammdd"))) -> 012820170923
A130: 129 | B130: Mystical Manga Tarot | C130: Llewellyn | D130: RANN / Barbara Moore | E130: SIM | F130: Não | G130: 43006 | H130: 102 | I130: Amazon US | J130: Full Tarot Deck | K130: =CONCATENATE(TEXT(A130,"0000"),(TEXT(G130,"aaaammdd"))) -> 012920170928
A131: 130 | B131: ShadowScapes Tarot | C131: Llewellyn | D131: Stephanie Pui-Mun Law / Barbara Moore | E131: SIM | F131: Não | G131: 43030 | H131: 108.9 | I131: Saraiva de SCS | J131: Full Tarot Deck | K131: =CONCATENATE(TEXT(A131,"0000"),(TEXT(G131,"aaaammdd"))) -> 013020171022
A132: 131 | B132: Rosa Chá Tarot Infitity of Stars | C132: Rosa Chá | D132: N/A | E132: SIM | F132: Não | G132: 43032 | H132: 37.8 | I132: Mercado Livre | J132: Major Arcanas only | K132: =CONCATENATE(TEXT(A132,"0000"),(TEXT(G132,"aaaammdd"))) -> 013120171024
A133: 132 | B133: Magickal Spellcards: Craft - Cast - Activate - Empower | C133: Llewellyn | D133: Lucy Cavendish, | E133: SIM | F133: Não | G133: 43035 | H133: 62.55 | I133: Amazon Brasil | J133: Oracle 45 Cards | K133: =CONCATENATE(TEXT(A133,"0000"),(TEXT(G133,"aaaammdd"))) -> 013220171027
A134: 133 | B134: The Steampunk Tarot | C134: Llewellyn | D134: Barbara Moore / Aly Fell | E134: SIM | F134: Não | G134: 43043 | H134: 137.1 | I134: Saraiva Shopping ABC | J134: Full Tarot Deck | K134: =CONCATENATE(TEXT(A134,"0000"),(TEXT(G134,"aaaammdd"))) -> 013320171104
A135: 134 | B135: Kalciferun Tarot | C135: N/A | D135: Andrei Fernandes | E135: Não | F135: Não | G135: 43046 | H135: 85 | I135: Mundo Freak | J135: Major Arcanas only | K135: =CONCATENATE(TEXT(A135,"0000"),(TEXT(G135,"aaaammdd"))) -> 013420171107
A136: 135 | B136: The Enchanted Tarot: 25th Anniversary Edition | C136: Race Point Publishing | D136: Amy Zerner / ‎ Monte Farber | E136: SIM | F136: Não | G136: 43053 | H136: 81.32 | I136: Amazon Brasil | J136: Full Tarot Deck | K136: =CONCATENATE(TEXT(A136,"0000"),(TEXT(G136,"aaaammdd"))) -> 013520171114
... A151: 150 | B151: Mystical Tarot | C151: Lo Scarabeo | D151: Giuliano Costa | E151: SIM | F151: Não | G151: 43208 | H151: 101.7 | I151: Saraiva.com.br | J151: Full Tarot Deck | K151: =CONCATENATE(TEXT(A151,"0000"),(TEXT(G151,"aaaammdd"))) -> 015020180418
A152: 151 | B152: Alchemy 1977 England Tarot | C152: Naipes Heraclio Fournier | D152: Alchemy 1977 | E152: SIM | F152: Não | G152: 43223 | H152: =126.72+4.74 -> 131.46 | I152: Simbólika | J152: Full Tarot Deck | K152: =CONCATENATE(TEXT(A152,"0000"),(TEXT(G152,"aaaammdd"))) -> 015120180503
A153: 152 | B153: Crystal Tarot | C153: Lo Scarabeo | D153: Elisabetta Trevisan | E153: SIM | F153: Não | G153: 43223 | H153: =111.02+4.74 -> 115.76 | I153: Simbólika | J153: Full Tarot Deck | K153: =CONCATENATE(TEXT(A153,"0000"),(TEXT(G153,"aaaammdd"))) -> 015220180503
A154: 153 | B154: Zillich Tarot - Em Lata | C154: US Games Inc. | D154: Christine Zillich / Johan Von Kirschner | E154: SIM | F154: Não | G154: 43245 | H154: 145.9 | I154: Simbólika | J154: Full Tarot Deck | K154: =CONCATENATE(TEXT(A154,"0000"),(TEXT(G154,"aaaammdd"))) -> 015320180525
A155: 154 | B155: Sibila Della Zingara | C155: Lo Scarabeo | E155: SIM | F155: Não | G155: 43260 | H155: 110 | I155: Espaço Merkaba | J155: Gipsy oracle cards | K155: =CONCATENATE(TEXT(A155,"0000"),(TEXT(G155,"aaaammdd"))) -> 015420180609
A156: 155 | B156: Tarot Illuminati - Kit Edition | C156: Lo Scarabeo | D156: Erik C. Dunne / Kim Huggens | E156: SIM | F156: Não | G156: 43272 | H156: 136.17 | I156: Saraiva Shopping ABC | J156: Full Tarot Deck | K156: =CONCATENATE(TEXT(A156,"0000"),(TEXT(G156,"aaaammdd"))) -> 015520180621
A157: 156 | B157: Tarô Adivinhatório | C157: Pensamento | D157: Diversos (???) | E157: SIM | F157: Não | G157: 43284 | H157: 37.97 | I157: Grupo Pensamento Site | J157: Full Tarot Deck | K157: =CONCATENATE(TEXT(A157,"0000"),(TEXT(G157,"aaaammdd"))) -> 015620180703
A158: 157 | B158: Tarô Egípcio Kier | C158: Pensamento | D158: Bibiana Rovira | E158: SIM | F158: Não | G158: 43284 | H158: 37.97 | I158: Grupo Pensamento Site | J158: Full Tarot Deck | K158: =CONCATENATE(TEXT(A158,"0000"),(TEXT(G158,"aaaammdd"))) -> 015720180703
A159: 158 | B159: o Tarô Maçonico | C159: Madras Brasil | D159: Patricio Diaz Silva | E159: SIM | F159: Não | G159: 43286 | H159: 129.9 | I159: Nobel Shopping Atrium | J159: Full Tarot Deck | K159: =CONCATENATE(TEXT(A159,"0000"),(TEXT(G159,"aaaammdd"))) -> 015820180705
A160: 159 | B160: Game Of Thrones Tarot | C160: Chronicle Books | D160: Michel Morris / Liz Dean / Graig Coss | E160: SIM | F160: Não | G160: 43296 | H160: 137.27 | I160: Saraiva Shopping ABC | J160: Full Tarot Deck | K160: =CONCATENATE(TEXT(A160,"0000"),(TEXT(G160,"aaaammdd"))) -> 015920180715
A161: 160 | B161: Oráculo Sibillus | D161: Pettrus SaLes | E161: SIM | F161: Não | G161: 43297 | H161: 62 | I161: Casa de Bruxa de Sto. André | J161: Gipsy oracle cards | K161: =CONCATENATE(TEXT(A161,"0000"),(TEXT(G161,"aaaammdd"))) -> 016020180716
A162: 161 | B162: Tibet Dark Gothic Tarot | C162: Master Book | D162: Elizabeth Queiroz | E162: SIM | F162: Não | G162: 43302 | H162: 90 | I162: Faces da Lua com o Emanuel | J162: Full Tarot Deck | K162: =CONCATENATE(TEXT(A162,"0000"),(TEXT(G162,"aaaammdd"))) -> 016120180721
A163: 162 | B163: Tarot Apolakypsis | C163: Lo Scarabeo | D163: Eric C. Dunne, Kim Huggens | E163: SIM | F163: Não | G163: 43318 | H163: 132 | I163: CaldeiraoMistico.com.br | J163: Full Tarot Deck | K163: =CONCATENATE(TEXT(A163,"0000"),(TEXT(G163,"aaaammdd"))) -> 016220180806
A164: 163 | B164: Universal Goddess Tarot | C164: Lo Scarabeo | D164: Maria Caratti | E164: SIM | F164: Não | G164: 43318 | H164: 122 | I164: CaldeiraoMistico.com.br | J164: Full Tarot Deck | K164: =CONCATENATE(TEXT(A164,"0000"),(TEXT(G164,"aaaammdd"))) -> 016320180806
A165: 164 | B165: Tarot Melefic by Luis Royo | C165: Naipes Heraclio Fournier | D165: Luis Royo / Romulo Royo | E165: SIM | F165: Não | G165: 43318 | H165: 134 | I165: CaldeiraoMistico.com.br | J165: Full Tarot Deck | K165: =CONCATENATE(TEXT(A165,"0000"),(TEXT(G165,"aaaammdd"))) -> 016420180806
A166: 165 | B166: Tarot Balbi | C166: N/A | D166: N/A | E166: SIM | F166: Não | G166: 43333 | H166: 46.8 | I166: Maxi Kiosko em B.A. | J166: Full Tarot Deck | K166: =CONCATENATE(TEXT(A166,"0000"),(TEXT(G166,"aaaammdd"))) -> 016520180821
A167: 166 | B167: Tarot de Maesella redondo | C167: N/A | D167: N/A | E167: SIM | F167: Não | G167: 43333 | H167: 46.8 | I167: Maxi Kiosko em B.A. | J167: Full Tarot Deck | K167: =CONCATENATE(TEXT(A167,"0000"),(TEXT(G167,"aaaammdd"))) -> 016620180821
A168: 167 | B168: Tarot RDR Iluminarte | C168: Iluminarte Argentina | D168: A.E. Waite / P. C. Smith | E168: SIM | F168: Não | G168: 43335 | H168: 46.8 | I168: Somos FE B.A. | J168: Full Tarot Deck | K168: =CONCATENATE(TEXT(A168,"0000"),(TEXT(G168,"aaaammdd"))) -> 016720180823
A169: 168 | B169: Tarot de Marseilla | C169: Iluminarte Argentina | D169: N/A | E169: SIM | F169: Não | G169: 43335 | H169: 46.8 | I169: Somos FE B.A. | J169: Full Tarot Deck | K169: =CONCATENATE(TEXT(A169,"0000"),(TEXT(G169,"aaaammdd"))) -> 016820180823
A170: 169 | B170: Tarot Atalla | C170: N/A | D170: Daniel Atalla / Maria Inês Bastos | E170: SIM | F170: Não | G170: 43365 | H170: 80 | I170: Escola Esotérica - Mistic Fair - Paulista | J170: Full Tarot Deck | K170: =CONCATENATE(TEXT(A170,"0000"),(TEXT(G170,"aaaammdd"))) -> 016920180922
A171: 170 | B171: Oracle of Visions | C171: US Games Inc. | D171: Ciro marchetti | E171: SIM | F171: Não | G171: 43365 | H171: =310/2 -> 155 | I171: Us Games Brasil - Mistic Fair - Paulista | J171: Oracle Deck | K171: =CONCATENATE(TEXT(A171,"0000"),(TEXT(G171,"aaaammdd"))) -> 017020180922
...

Sheet CdBr
A1: Sequencial | B1: =Tarot_Decks!K1 -> Chave Primária
A2: =Tarot_Decks!A2 -> 1 | B2: =Tarot_Decks!K2 -> 000120140716
A3: =Tarot_Decks!A3 -> 2 | B3: =Tarot_Decks!K3 -> 000220140716
A4: =Tarot_Decks!A4 -> 3 | B4: =Tarot_Decks!K4 -> 000320140827
A5: =Tarot_Decks!A5 -> 4 | B5: =Tarot_Decks!K5 -> 000420140827
A6: =Tarot_Decks!A6 -> 5 | B6: =Tarot_Decks!K6 -> 000520140829
A7: =Tarot_Decks!A7 -> 6 | B7: =Tarot_Decks!K7 -> 000620140918
A8: =Tarot_Decks!A8 -> 7 | B8: =Tarot_Decks!K8 -> 000720141201
A9: =Tarot_Decks!A9 -> 8 | B9: =Tarot_Decks!K9 -> 000820141201
A10: =Tarot_Decks!A10 -> 9 | B10: =Tarot_Decks!K10 -> 000920141211
A11: =Tarot_Decks!A11 -> 10 | B11: =Tarot_Decks!K11 -> 001020141223
A12: =Tarot_Decks!A12 -> 11 | B12: =Tarot_Decks!K12 -> 001120150116
A13: =Tarot_Decks!A13 -> 12 | B13: =Tarot_Decks!K13 -> 001220150224
... A194: =Tarot_Decks!A194 -> 193 | B194: =Tarot_Decks!K194 -> 019320231117

Sheet Action Figures
A1: Nome do Action | B1: Data | C1: Onde comprei | D1: Valor | E1: Status | F1: OBS
A2: Kriska Barchenowa Lingerie ver. (PVC Figure) Alphamax 1/7 Sky Tube | B2: 40587 | C2: http://www.1999.co.jp/eng/ | D2: 5,780 yen | E2: Received | F2: Aguardando CORREIOS
A3: Ghostbusters Bishoujo Lucy Complete | B3: 40605 | C3: http://www.amiami.com | D3: 5,430 Yen | E3: Received | F3: Aguardando Envio
A4: Androids Miniactions | B4: 40629 | C4: http://www.deadzebra.com | D4: $24.14 USD | E4: Received
A5: Sexy girl "Canal" 6" | B5: 40694 | C5: http://myworld.ebay.com/ekinyangyiwei | D5: $26.50 USD | E5: Received
A6: Marvel Bishoujo Statue ELEKTRA Kotobukiya 1/7 Bishoujo Statue | B6: 40738 | C6: http://www.1999.co.jp/eng/ | D6: 5,270 yen | E6: Received | F6: Late September 2011
A7: Marvel Bishoujo Mystique Kotobukiya 1/7 Bishoujo Statue | B7: 40738 | C7: http://www.1999.co.jp/eng/ | D7: 5,270 yen | E7: Received | F7: Late December 2011
A8: MARVEL BISHOUJO - X-23 Complete Figure | B8: 40774 | C8: http://www.amiami.com | D8: 4,950 Yen | E8: Canceled | F8: March 2012
A9: Marvel Bishoujo Statue Emma Frost Kotobukiya 1/8 Bishoujo Statue | B9: 40777 | C9: http://www.1999.co.jp/eng/ | D9: 5,580 Yen | E9: Received | F9: Aguardando CORREIOS
A10: Nariko | B10: 40973 | C10: http://myworld.ebay.com/toymania168/ | D10: $26,95 USD | E10: Received | F10: No Tracking ID
A11: Super Sonico -Nurse Ver.- (PVC Figure) | B11: 40978 | C11: http://www.1999.co.jp/eng/ | D11: 7,043 yen | E11: Canceled | F11: Late Aug 2012
A12: Megurine Luka Tony ver. *Special Price 20%OFF (PVC Figure) | B12: 40978 | C12: http://www.1999.co.jp/eng/ | D12: 6,704 yen | E12: Canceled | F12: Late Jul 2012
A13: Christie Monteiro Tekken Bishoujo - Kotobukiya | B13: 41023 | C13: http://www.allcenter.com.br | D13: 208.12 | E13: Received | F13: Barrado pela operação Maré Vermelha
A14: Batman - Wacky Wobbler | B14: 41031 | C14: http://www.allcenter.com.br | D14: 76.96 | E14: Received | F14: entrega errada. Devolvido
A15: Alisa Ilynichna Amiera (PVC Figure) | B15: 01/05/25012 | C15: http://www.1999.co.jp/eng/ | D15: 6,630 Yen | E15: Received | F15: Late Jul 2012
A16: Witchblade Estátua De Resina 30cm Altura Fantástica!!! | B16: 41053 | C16: http://www.mercadolivre.com.br/brasil/ml/org_prod.p_main?it_s=MLB&it_n=239082157 | D16: 175 | E16: Received
A17: Scott Pilgrim | B17: 41065 | C17: www.limitededition.com.br | D17: 109 | E17: Received
A18: Poison IVY Bishoujo | B18: 41065 | C18: www.limitededition.com.br | D18: 219 | E18: Received
A19: MegaHouse 814624 Yamato Girls Collection Space Battleship Yamato 2199 Mori Yuki Battleship Cloth Ver. (PVC Figure) 1/8 | B19: 41390 | C19: http://www.1999.co.jp/eng/ | D19: 9,070 yen | E19: Received

Sheet Planejamento 2014
A1: Item # | B1: Ano | C1: Descrição | D1: Status | F1: Item # | G1: Ano | H1: Certificações necessárias | I1: Status
A2: 1 | B2: 2014 | C2: Quitar débitos no banco, positivando as contas | D2: OK | F2: 1 | G2: 2014 | H2: Linux LPI-101
A3: 2 | B3: 2014 | C3: Pagar financiamento do Santander | D3: OK | F3: 2 | G3: 2014 | H3: Linux LPI-102
A4: 3 | B4: 2014 | C4: Trocar de Emprego | D4: OK | F4: 3 | G4: 2015 | H4: ITIL v3
A5: 4 | B5: 2014 | C5: Voltar a reter provisoes para imprevistos | F5: 4 | G5: 2015 | H5: Cobit 4.1
A6: 5 | B6: 2014 | C6: Cortar custos excedentes ?!?!?! | F6: 5 | G6: 2015 | H6: Scrum Master?
A7: 6 | B7: 2014 | C7: Terminar todas as materias MBA | D7: OK | F7: 6 | G7: 2015 | H7: SAP ???
A8: 7 | B8: 2014 | C8: Fazer o TCC do MBA | D8: OK | F8: 7 | G8: 2015 | H8: Protheus
A9: 8 | B9: 2014 | C9: Pagar GGM4 EchoSports | D9: OK | F9: 8 | G9: 2015 | H9: ERP ToTVS
A10: 9 | B10: 2014 | C10: Reduzir custos com moradia (Aluguel condominio) | F10: 9 | G10: 2015 | H10: PMI
A11: 10 | B11: 2014 | C11: Comprar um AP em SCS | F11: 10
A12: 1 | B12: 2015 | F12: 11
A13: 2 | B13: 2015 | F13: 12
A14: 3 | B14: 2015 | F14: 13
A15: 4 | B15: 2015 | F15: 14
A16: 5 | B16: 2015 | F16: 15
A17: 6 | B17: 2015 | F17: 16
A18: 7 | B18: 2015 | F18: 17
A19: 8 | B19: 2015 | F19: 18
A20: 9 | B20: 2015 | F20: 19
A21: 10 | B21: 2015 | F21: 20

Sheet Combustivel P208 Griffe Busines
A1: Seq | B1: Data | C1: Kilometragem | D1: Vlr Litro | E1: Valor total | F1: Tipo | G1: LtoTotal | H1: KmRodados | I1: Dias | J1: Km/Litro | K1: Km/Dia | L1: Lt/Dia | M1: R$/Dia | N1: R$/KM
A2: 1 | B2: 43381 | C2: 2 | D2: 4.789 | E2: 150 | F2: Gasolina | G2: =IF(E2<>"",E2/D2,"") -> 31.321779
A3: 2 | B3: 43400 | C3: 194 | D3: 4.899 | E3: 150 | F3: Gasolina | G3: =IF(E3<>"",E3/D3,"") -> 30.618494 | H3: =IF(C3="","",C3-C2) -> 192 | I3: =IF(B3="","",B3-B2) -> 19 | J3: =IF(H3="","",H3/G2) -> 6.12992 | K3: =IF(H3<>"",IF(I3>0,H3/I3,H3),"" ) -> 10.105263 | L3: =IF(I3="","",IF(I3=0,G3,G2/I3)) -> 1.6485147 | M3: =IF(I3="","",IF(I3=0,E2,E2/I3)) -> 7.8947368 | N3: =IF(H3="","",E2/H3) -> 0.78125
A4: 3 | B4: 43414 | C4: 419 | D4: 4.499 | E4: 235.66 | F4: Gasolina | G4: =IF(E4<>"",E4/D4,"") -> 52.380529 | H4: =IF(C4="","",C4-C3) -> 225 | I4: =IF(B4="","",B4-B3) -> 14 | J4: =IF(H4="","",H4/G3) -> 7.3485 | K4: =IF(H4<>"",IF(I4>0,H4/I4,H4),"" ) -> 16.071429 | L4: =IF(I4="","",IF(I4=0,G4,G3/I4)) -> 2.1870353 | M4: =IF(I4="","",IF(I4=0,E3,E3/I4)) -> 10.714286 | N4: =IF(H4="","",E3/H4) -> 0.66666667
A5: 4 | B5: 43434 | C5: 641 | D5: 4.599 | E5: 144.36 | F5: Gasolina | G5: =IF(E5<>"",E5/D5,"") -> 31.389432 | H5: =IF(C5="","",C5-C4) -> 222 | I5: =IF(B5="","",B5-B4) -> 20 | J5: =IF(H5="","",H5/G4) -> 4.2382161 | K5: =IF(H5<>"",IF(I5>0,H5/I5,H5),"" ) -> 11.1 | L5: =IF(I5="","",IF(I5=0,G5,G4/I5)) -> 2.6190265 | M5: =IF(I5="","",IF(I5=0,E4,E4/I5)) -> 11.783 | N5: =IF(H5="","",E4/H5) -> 1.0615315
A6: 5 | B6: 43436 | C6: 1045 | D6: 4.398 | E6: 122.07 | F6: Gasolina | G6: =IF(E6<>"",E6/D6,"") -> 27.755798 | H6: =IF(C6="","",C6-C5) -> 404 | I6: =IF(B6="","",B6-B5) -> 2 | J6: =IF(H6="","",H6/G5) -> 12.870574 | K6: =IF(H6<>"",IF(I6>0,H6/I6,H6),"" ) -> 202 | L6: =IF(I6="","",IF(I6=0,G6,G5/I6)) -> 15.694716 | M6: =IF(I6="","",IF(I6=0,E5,E5/I6)) -> 72.18 | N6: =IF(H6="","",E5/H6) -> 0.35732673
A7: 6 | B7: 43449 | C7: 1582 | D7: 4.399 | E7: 35 | F7: Gasolina | G7: =IF(E7<>"",E7/D7,"") -> 7.9563537 | H7: =IF(C7="","",C7-C6) -> 537 | I7: =IF(B7="","",B7-B6) -> 13 | J7: =IF(H7="","",H7/G6) -> 19.347309 | K7: =IF(H7<>"",IF(I7>0,H7/I7,H7),"" ) -> 41.307692 | L7: =IF(I7="","",IF(I7=0,G7,G6/I7)) -> 2.1350614 | M7: =IF(I7="","",IF(I7=0,E6,E6/I7)) -> 9.39 | N7: =IF(H7="","",E6/H7) -> 0.22731844
A8: 7 | B8: 43454 | C8: 1647 | D8: 4.399 | E8: 227.82 | F8: Gasolina | G8: =IF(E8<>"",E8/D8,"") -> 51.789043 | H8: =IF(C8="","",C8-C7) -> 65 | I8: =IF(B8="","",B8-B7) -> 5 | J8: =IF(H8="","",H8/G7) -> 8.1695714 | K8: =IF(H8<>"",IF(I8>0,H8/I8,H8),"" ) -> 13 | L8: =IF(I8="","",IF(I8=0,G8,G7/I8)) -> 1.5912707 | M8: =IF(I8="","",IF(I8=0,E7,E7/I8)) -> 7 | N8: =IF(H8="","",E7/H8) -> 0.53846154
A9: 8 | B9: 43467 | C9: 2148 | D9: 4.298 | E9: 188.19 | F9: Gasolina | G9: =IF(E9<>"",E9/D9,"") -> 43.785482 | H9: =IF(C9="","",C9-C8) -> 501 | I9: =IF(B9="","",B9-B8) -> 13 | J9: =IF(H9="","",H9/G8) -> 9.6738609 | K9: =IF(H9<>"",IF(I9>0,H9/I9,H9),"" ) -> 38.538462 | L9: =IF(I9="","",IF(I9=0,G9,G8/I9)) -> 3.9837725 | M9: =IF(I9="","",IF(I9=0,E8,E8/I9)) -> 17.524615 | N9: =IF(H9="","",E8/H9) -> 0.45473054
A10: 9 | B10: 43479 | C10: 2673 | D10: 4.287 | E10: 110 | F10: Gasolina | G10: =IF(E10<>"",E10/D10,"") -> 25.658969 | H10: =IF(C10="","",C10-C9) -> 525 | I10: =IF(B10="","",B10-B9) -> 12 | J10: =IF(H10="","",H10/G9) -> 11.990276 | K10: =IF(H10<>"",IF(I10>0,H10/I10,H10),"" ) -> 43.75 | L10: =IF(I10="","",IF(I10=0,G10,G9/I10)) -> 3.6487901 | M10: =IF(I10="","",IF(I10=0,E9,E9/I10)) -> 15.6825 | N10: =IF(H10="","",E9/H10) -> 0.35845714
A11: 10 | B11: 43493 | C11: 2855 | D11: 4.299 | E11: 50 | F11: Gasolina | G11: =IF(E11<>"",E11/D11,"") -> 11.630612 | H11: =IF(C11="","",C11-C10) -> 182 | I11: =IF(B11="","",B11-B10) -> 14 | J11: =IF(H11="","",H11/G10) -> 7.0930364 | K11: =IF(H11<>"",IF(I11>0,H11/I11,H11),"" ) -> 13 | L11: =IF(I11="","",IF(I11=0,G11,G10/I11)) -> 1.8327835 | M11: =IF(I11="","",IF(I11=0,E10,E10/I11)) -> 7.8571429 | N11: =IF(H11="","",E10/H11) -> 0.6043956
A12: 11 | B12: 43498 | C12: 2938 | D12: 4.299 | E12: 226 | F12: Gasolina | G12: =IF(E12<>"",E12/D12,"") -> 52.570365 | H12: =IF(C12="","",C12-C11) -> 83 | I12: =IF(B12="","",B12-B11) -> 5 | J12: =IF(H12="","",H12/G11) -> 7.13634 | K12: =IF(H12<>"",IF(I12>0,H12/I12,H12),"" ) -> 16.6 | L12: =IF(I12="","",IF(I12=0,G12,G11/I12)) -> 2.3261224 | M12: =IF(I12="","",IF(I12=0,E11,E11/I12)) -> 10 | N12: =IF(H12="","",E11/H12) -> 0.60240964
A13: 12 | B13: 43525 | C13: 3273 | D13: 3.999 | E13: 211.73 | F13: Gasolina | G13: =IF(E13<>"",E13/D13,"") -> 52.945736 | H13: =IF(C13="","",C13-C12) -> 335 | I13: =IF(B13="","",B13-B12) -> 27 | J13: =IF(H13="","",H13/G12) -> 6.3724115 | K13: =IF(H13<>"",IF(I13>0,H13/I13,H13),"" ) -> 12.407407 | L13: =IF(I13="","",IF(I13=0,G13,G12/I13)) -> 1.9470506 | M13: =IF(I13="","",IF(I13=0,E12,E12/I13)) -> 8.3703704 | N13: =IF(H13="","",E12/H13) -> 0.67462687
A14: 13 | B14: 43530 | C14: 3697 | D14: 4.199 | E14: 80 | F14: Gasolina | G14: =IF(E14<>"",E14/D14,"") -> 19.052155 | H14: =IF(C14="","",C14-C13) -> 424 | I14: =IF(B14="","",B14-B13) -> 5 | J14: =IF(H14="","",H14/G13) -> 8.0081991 | K14: =IF(H14<>"",IF(I14>0,H14/I14,H14),"" ) -> 84.8 | L14: =IF(I14="","",IF(I14=0,G14,G13/I14)) -> 10.589147 | M14: =IF(I14="","",IF(I14=0,E13,E13/I14)) -> 42.346 | N14: =IF(H14="","",E13/H14) -> 0.49936321
... A210: 209 | B210: 45949 | C210: 48077 | D210: 6.29 | E210: 150 | F210: Gasolina | G210: =IF(E210<>"",E210/D210,"") -> 23.847377 | H210: =IF(C210="","",C210-C209) -> 224 | I210: =IF(B210="","",B210-B209) -> 1 | J210: =IF(H210="","",H210/G209) -> 9.2437333 | K210: =IF(H210<>"",IF(I210>0,H210/I210,H210),"" ) -> 224 | L210: =IF(I210="","",IF(I210=0,G210,G209/I210)) -> 24.232633 | M210: =IF(I210="","",IF(I210=0,E209,E209/I210)) -> 150 | N210: =IF(H210="","",E209/H210) -> 0.66964286
A211: 210 | B211: 45957 | C211: =48493-120 -> 48373 | D211: 5.99 | E211: 150 | F211: Gasolina | G211: =IF(E211<>"",E211/D211,"") -> 25.041736 | H211: =IF(C211="","",C211-C210) -> 296 | I211: =IF(B211="","",B211-B210) -> 8 | J211: =IF(H211="","",H211/G210) -> 12.412267 | K211: =IF(H211<>"",IF(I211>0,H211/I211,H211),"" ) -> 37 | L211: =IF(I211="","",IF(I211=0,G211,G210/I211)) -> 2.9809221 | M211: =IF(I211="","",IF(I211=0,E210,E210/I211)) -> 18.75 | N211: =IF(H211="","",E210/H211) -> 0.50675676
A212: 211 | B212: 45978 | C212: 48645 | D212: 5.79 | E212: 120 | F212: Gasolina | G212: =IF(E212<>"",E212/D212,"") -> 20.725389 | H212: =IF(C212="","",C212-C211) -> 272 | I212: =IF(B212="","",B212-B211) -> 21 | J212: =IF(H212="","",H212/G211) -> 10.861867 | K212: =IF(H212<>"",IF(I212>0,H212/I212,H212),"" ) -> 12.952381 | L212: =IF(I212="","",IF(I212=0,G212,G211/I212)) -> 1.1924636 | M212: =IF(I212="","",IF(I212=0,E211,E211/I212)) -> 7.1428571 | N212: =IF(H212="","",E211/H212) -> 0.55147059
A213: 212 | B213: 45987 | C213: 48754 | D213: 5.79 | E213: 100 | F213: Gasolina | G213: =IF(E213<>"",E213/D213,"") -> 17.271157 | H213: =IF(C213="","",C213-C212) -> 109 | I213: =IF(B213="","",B213-B212) -> 9 | J213: =IF(H213="","",H213/G212) -> 5.25925 | K213: =IF(H213<>"",IF(I213>0,H213/I213,H213),"" ) -> 12.111111 | L213: =IF(I213="","",IF(I213=0,G213,G212/I213)) -> 2.302821 | M213: =IF(I213="","",IF(I213=0,E212,E212/I213)) -> 13.333333 | N213: =IF(H213="","",E212/H213) -> 1.1009174
A214: 213 | B214: 46003 | C214: 48892 | D214: 6.29 | E214: 100 | F214: Gasolina | G214: =IF(E214<>"",E214/D214,"") -> 15.898251 | H214: =IF(C214="","",C214-C213) -> 138 | I214: =IF(B214="","",B214-B213) -> 16 | J214: =IF(H214="","",H214/G213) -> 7.9902 | K214: =IF(H214<>"",IF(I214>0,H214/I214,H214),"" ) -> 8.625 | L214: =IF(I214="","",IF(I214=0,G214,G213/I214)) -> 1.0794473 | M214: =IF(I214="","",IF(I214=0,E213,E213/I214)) -> 6.25 | N214: =IF(H214="","",E213/H214) -> 0.72463768
A215: 214 | B215: 46007 | C215: 49000 | D215: 5.99 | E215: 100 | F215: Gasolina | G215: =IF(E215<>"",E215/D215,"") -> 16.694491 | H215: =IF(C215="","",C215-C214) -> 108 | I215: =IF(B215="","",B215-B214) -> 4 | J215: =IF(H215="","",H215/G214) -> 6.7932 | K215: =IF(H215<>"",IF(I215>0,H215/I215,H215),"" ) -> 27 | L215: =IF(I215="","",IF(I215=0,G215,G214/I215)) -> 3.9745628 | M215: =IF(I215="","",IF(I215=0,E214,E214/I215)) -> 25 | N215: =IF(H215="","",E214/H215) -> 0.92592593
A216: 215 | B216: 46011 | C216: 49025 | D216: 5.99 | E216: 200 | F216: Gasolina | G216: =IF(E216<>"",E216/D216,"") -> 33.388982 | H216: =IF(C216="","",C216-C215) -> 25 | I216: =IF(B216="","",B216-B215) -> 4 | J216: =IF(H216="","",H216/G215) -> 1.4975 | K216: =IF(H216<>"",IF(I216>0,H216/I216,H216),"" ) -> 6.25 | L216: =IF(I216="","",IF(I216=0,G216,G215/I216)) -> 4.1736227 | M216: =IF(I216="","",IF(I216=0,E215,E215/I216)) -> 25 | N216: =IF(H216="","",E215/H216) -> 4
A217: 216 | B217: 46024 | C217: 49423 | D217: 6.29 | E217: 200 | F217: Gasolina | G217: =IF(E217<>"",E217/D217,"") -> 31.796502 | H217: =IF(C217="","",C217-C216) -> 398 | I217: =IF(B217="","",B217-B216) -> 13 | J217: =IF(H217="","",H217/G216) -> 11.9201 | K217: =IF(H217<>"",IF(I217>0,H217/I217,H217),"" ) -> 30.615385 | L217: =IF(I217="","",IF(I217=0,G217,G216/I217)) -> 2.5683832 | M217: =IF(I217="","",IF(I217=0,E216,E216/I217)) -> 15.384615 | N217: =IF(H217="","",E216/H217) -> 0.50251256
A218: 217 | B218: 46055 | C218: 49914 | D218: 6.09 | E218: 150 | F218: Gasolina | G218: =IF(E218<>"",E218/D218,"") -> 24.630542 | H218: =IF(C218="","",C218-C217) -> 491 | I218: =IF(B218="","",B218-B217) -> 31 | J218: =IF(H218="","",H218/G217) -> 15.44195 | K218: =IF(H218<>"",IF(I218>0,H218/I218,H218),"" ) -> 15.83871 | L218: =IF(I218="","",IF(I218=0,G218,G217/I218)) -> 1.0256936 | M218: =IF(I218="","",IF(I218=0,E217,E217/I218)) -> 6.4516129 | N218: =IF(H218="","",E217/H218) -> 0.40733198
A219: 218 | B219: 46068 | C219: 50043 | D219: 5.89 | E219: 150 | F219: Gasolina | G219: =IF(E219<>"",E219/D219,"") -> 25.466893 | H219: =IF(C219="","",C219-C218) -> 129 | I219: =IF(B219="","",B219-B218) -> 13 | J219: =IF(H219="","",H219/G218) -> 5.2374 | K219: =IF(H219<>"",IF(I219>0,H219/I219,H219),"" ) -> 9.9230769 | L219: =IF(I219="","",IF(I219=0,G219,G218/I219)) -> 1.8946571 | M219: =IF(I219="","",IF(I219=0,E218,E218/I219)) -> 11.538462 | N219: =IF(H219="","",E218/H219) -> 1.1627907
A220: 219 | B220: 46074 | C220: 50175 | D220: 6.09 | E220: 150 | F220: Gasolina | G220: =IF(E220<>"",E220/D220,"") -> 24.630542 | H220: =IF(C220="","",C220-C219) -> 132 | I220: =IF(B220="","",B220-B219) -> 6 | J220: =IF(H220="","",H220/G219) -> 5.1832 | K220: =IF(H220<>"",IF(I220>0,H220/I220,H220),"" ) -> 22 | L220: =IF(I220="","",IF(I220=0,G220,G219/I220)) -> 4.2444822 | M220: =IF(I220="","",IF(I220=0,E219,E219/I220)) -> 25 | N220: =IF(H220="","",E219/H220) -> 1.1363636
A221: 220 | B221: 46075 | C221: 50439 | D221: 6.39 | E221: 150 | F221: Gasolina | G221: =IF(E221<>"",E221/D221,"") -> 23.474178 | H221: =IF(C221="","",C221-C220) -> 264 | I221: =IF(B221="","",B221-B220) -> 1 | J221: =IF(H221="","",H221/G220) -> 10.7184 | K221: =IF(H221<>"",IF(I221>0,H221/I221,H221),"" ) -> 264 | L221: =IF(I221="","",IF(I221=0,G221,G220/I221)) -> 24.630542 | M221: =IF(I221="","",IF(I221=0,E220,E220/I221)) -> 150 | N221: =IF(H221="","",E220/H221) -> 0.56818182
A222: 221 | B222: 46093 | C222: 50876 | D222: 6.89 | E222: 150 | F222: Gasolina | G222: =IF(E222<>"",E222/D222,"") -> 21.770682 | H222: =IF(C222="","",C222-C221) -> 437 | I222: =IF(B222="","",B222-B221) -> 18 | J222: =IF(H222="","",H222/G221) -> 18.6162 | K222: =IF(H222<>"",IF(I222>0,H222/I222,H222),"" ) -> 24.277778 | L222: =IF(I222="","",IF(I222=0,G222,G221/I222)) -> 1.304121 | M222: =IF(I222="","",IF(I222=0,E221,E221/I222)) -> 8.3333333 | N222: =IF(H222="","",E221/H222) -> 0.34324943
A223: 222 | B223: 46098 | C223: 50997 | D223: 6.39 | E223: 150 | F223: Gasolina | G223: =IF(E223<>"",E223/D223,"") -> 23.474178 | H223: =IF(C223="","",C223-C222) -> 121 | I223: =IF(B223="","",B223-B222) -> 5 | J223: =IF(H223="","",H223/G222) -> 5.5579333 | K223: =IF(H223<>"",IF(I223>0,H223/I223,H223),"" ) -> 24.2 | L223: =IF(I223="","",IF(I223=0,G223,G222/I223)) -> 4.3541364 | M223: =IF(I223="","",IF(I223=0,E222,E222/I223)) -> 30 | N223: =IF(H223="","",E222/H223) -> 1.2396694
... A230: 229 | B230: 46155 | C230: 52441 | D230: 6.19 | E230: 100 | F230: Gasolina | G230: =IF(E230<>"",E230/D230,"") -> 16.155089 | H230: =IF(C230="","",C230-C229) -> 474 | I230: =IF(B230="","",B230-B229) -> 10 | J230: =IF(H230="","",H230/G229) -> 16.0923 | K230: =IF(H230<>"",IF(I230>0,H230/I230,H230),"" ) -> 47.4 | L230: =IF(I230="","",IF(I230=0,G230,G229/I230)) -> 2.9455081 | M230: =IF(I230="","",IF(I230=0,E229,E229/I230)) -> 20 | N230: =IF(H230="","",E229/H230) -> 0.42194093
A231: 230 | G231: =IF(E231<>"",E231/D231,"") | H231: =IF(C231="","",C231-C230) | I231: =IF(B231="","",B231-B230) | J231: =IF(H231="","",H231/G230) | K231: =IF(H231<>"",IF(I231>0,H231/I231,H231),"" ) | L231: =IF(I231="","",IF(I231=0,G231,G230/I231)) | M231: =IF(I231="","",IF(I231=0,E230,E230/I231)) | N231: =IF(H231="","",E230/H231)
A232: 231 | G232: =IF(E232<>"",E232/D232,"") | H232: =IF(C232="","",C232-C231) | I232: =IF(B232="","",B232-B231) | J232: =IF(H232="","",H232/G231) | K232: =IF(H232<>"",IF(I232>0,H232/I232,H232),"" ) | L232: =IF(I232="","",IF(I232=0,G232,G231/I232)) | M232: =IF(I232="","",IF(I232=0,E231,E231/I232)) | N232: =IF(H232="","",E231/H232)
A233: 232 | G233: =IF(E233<>"",E233/D233,"") | H233: =IF(C233="","",C233-C232) | I233: =IF(B233="","",B233-B232) | J233: =IF(H233="","",H233/G232) | K233: =IF(H233<>"",IF(I233>0,H233/I233,H233),"" ) | L233: =IF(I233="","",IF(I233=0,G233,G232/I233)) | M233: =IF(I233="","",IF(I233=0,E232,E232/I233)) | N233: =IF(H233="","",E232/H233)
A234: 233 | G234: =IF(E234<>"",E234/D234,"") | H234: =IF(C234="","",C234-C233) | I234: =IF(B234="","",B234-B233) | J234: =IF(H234="","",H234/G233) | K234: =IF(H234<>"",IF(I234>0,H234/I234,H234),"" ) | L234: =IF(I234="","",IF(I234=0,G234,G233/I234)) | M234: =IF(I234="","",IF(I234=0,E233,E233/I234)) | N234: =IF(H234="","",E233/H234)
A235: 234 | G235: =IF(E235<>"",E235/D235,"") | H235: =IF(C235="","",C235-C234) | I235: =IF(B235="","",B235-B234) | J235: =IF(H235="","",H235/G234) | K235: =IF(H235<>"",IF(I235>0,H235/I235,H235),"" ) | L235: =IF(I235="","",IF(I235=0,G235,G234/I235)) | M235: =IF(I235="","",IF(I235=0,E234,E234/I235)) | N235: =IF(H235="","",E234/H235)
A236: 235 | G236: =IF(E236<>"",E236/D236,"") | H236: =IF(C236="","",C236-C235) | I236: =IF(B236="","",B236-B235) | J236: =IF(H236="","",H236/G235) | K236: =IF(H236<>"",IF(I236>0,H236/I236,H236),"" ) | L236: =IF(I236="","",IF(I236=0,G236,G235/I236)) | M236: =IF(I236="","",IF(I236=0,E235,E235/I236)) | N236: =IF(H236="","",E235/H236)
A237: 236 | G237: =IF(E237<>"",E237/D237,"") | H237: =IF(C237="","",C237-C236) | I237: =IF(B237="","",B237-B236) | J237: =IF(H237="","",H237/G236) | K237: =IF(H237<>"",IF(I237>0,H237/I237,H237),"" ) | L237: =IF(I237="","",IF(I237=0,G237,G236/I237)) | M237: =IF(I237="","",IF(I237=0,E236,E236/I237)) | N237: =IF(H237="","",E236/H237)
A238: 237 | G238: =IF(E238<>"",E238/D238,"") | H238: =IF(C238="","",C238-C237) | I238: =IF(B238="","",B238-B237) | J238: =IF(H238="","",H238/G237) | K238: =IF(H238<>"",IF(I238>0,H238/I238,H238),"" ) | L238: =IF(I238="","",IF(I238=0,G238,G237/I238)) | M238: =IF(I238="","",IF(I238=0,E237,E237/I238)) | N238: =IF(H238="","",E237/H238)
A239: 238 | G239: =IF(E239<>"",E239/D239,"") | H239: =IF(C239="","",C239-C238) | I239: =IF(B239="","",B239-B238) | J239: =IF(H239="","",H239/G238) | K239: =IF(H239<>"",IF(I239>0,H239/I239,H239),"" ) | L239: =IF(I239="","",IF(I239=0,G239,G238/I239)) | M239: =IF(I239="","",IF(I239=0,E238,E238/I239)) | N239: =IF(H239="","",E238/H239)
A240: 239 | G240: =IF(E240<>"",E240/D240,"") | H240: =IF(C240="","",C240-C239) | I240: =IF(B240="","",B240-B239) | J240: =IF(H240="","",H240/G239) | K240: =IF(H240<>"",IF(I240>0,H240/I240,H240),"" ) | L240: =IF(I240="","",IF(I240=0,G240,G239/I240)) | M240: =IF(I240="","",IF(I240=0,E239,E239/I240)) | N240: =IF(H240="","",E239/H240)
A241: 240 | G241: =IF(E241<>"",E241/D241,"") | H241: =IF(C241="","",C241-C240) | I241: =IF(B241="","",B241-B240) | J241: =IF(H241="","",H241/G240) | K241: =IF(H241<>"",IF(I241>0,H241/I241,H241),"" ) | L241: =IF(I241="","",IF(I241=0,G241,G240/I241)) | M241: =IF(I241="","",IF(I241=0,E240,E240/I241)) | N241: =IF(H241="","",E240/H241)
A242: 241 | G242: =IF(E242<>"",E242/D242,"") | H242: =IF(C242="","",C242-C241) | I242: =IF(B242="","",B242-B241) | J242: =IF(H242="","",H242/G241) | K242: =IF(H242<>"",IF(I242>0,H242/I242,H242),"" ) | L242: =IF(I242="","",IF(I242=0,G242,G241/I242)) | M242: =IF(I242="","",IF(I242=0,E241,E241/I242)) | N242: =IF(H242="","",E241/H242)
... A257: 256 | G257: =IF(E257<>"",E257/D257,"") | H257: =IF(C257="","",C257-C256) | I257: =IF(B257="","",B257-B256) | J257: =IF(H257="","",H257/G256) | K257: =IF(H257<>"",IF(I257>0,H257/I257,H257),"" ) | L257: =IF(I257="","",IF(I257=0,G257,G256/I257)) | M257: =IF(I257="","",IF(I257=0,E256,E256/I257)) | N257: =IF(H257="","",E256/H257)
G258: =IF(E258<>"",E258/D258,"") | H258: =IF(C258="","",C258-C244) | I258: =IF(B258="","",B258-B244) | J258: =IF(H258="","",H258/G244) | K258: =IF(H258<>"",IF(I258>0,H258/I258,H258),"" ) | L258: =IF(I258="","",IF(I258=0,G258,G244/I258)) | M258: =IF(I258="","",IF(I258=0,E244,E244/I258)) | N258: =IF(H258="","",E244/H258)
C259: Médias | D259: =AVERAGE(D2:D61) -> 4.2522817 | E259: =AVERAGE(E2:E61) -> 124.8015 | G259: =IF(E259<>"",E259/D259,"") -> 29.349302 | H259: =SUM(H2:H47) -> 12418 | I259: =AVERAGE(I2:I47) -> 11.533333 | J259: =AVERAGE(J2:J47) -> 9.5995674 | K259: =AVERAGE(K2:K47) -> 47.382813 | L259: =AVERAGE(L2:L47) -> 5.349875 | M259: =AVERAGE(M2:M47) -> 22.566783 | N259: =AVERAGE(N2:N47) -> 0.54307477
E260: =SUM(E2:E258) -> 29511.61 | G260: =SUM(G2:G258) -> 5757.5163 | I260: =SUM(I5:I258) -> 2741
C262: Tipos
C263: Alcool
C264: Gasolina
C265: Mistura

Sheet Senhas
A1: Local | B1: user ID | C1: Password | D1: Tipo | E1: Atualização Dados | F1: Ativo | G1: Exportado
A2: 404notfound.com.br | B2: GarGaMel | C2: sync750v | D2: Online Services | E2: 37249 | F2: N
A3: AIM | B3: Hardrappel | C3: p_280277 | D3: Instant Message | F3: Y
A4: americanas.com | B4: luizcarlin | C4: sync750v | D4: Shopping | E4: 39559 | F4: Y
A5: apinfo.com | B5: 274549748 | C5: sync750v | D5: Jobs | E5: 38913 | F5: N
A6: arquivo-x.com | B6: gargamel | C6: LAC280277 | D6: e-mail | F6: N
A7: arremate.com | B7: hardrappel | C7: sync750v | D7: Shopping | E7: 38854 | F7: Y
A8: unibanco.com.br | B8: 7007 -105877-3 | C8: 6478 | D8: Internet Banking | E8: 38715 | F8: N
A9: bancoreal.com.br | B9: luizcarlin 0247 9705879 | C9: sync750v | D9: Internet Banking | E9: 37249 | F9: N
A10: banespa.com.br | B10: acarlin - 920009805 | C10: 250680 | D10: Internet Banking | E10: 38715 | F10: Y
A11: blogger.com.br | B11: cyberspawn | C11: sync750v | D11: Blogger | E11: 37497 | F11: n
A12: Bol.com.br | B12: gargamel_lac | C12: sync750v | D12: e-mail | E12: 37249 | F12: N
A13: borland.com | B13: hardrappel | C13: sync750v | D13: Online Services | E13: 38715 | F13: Y
A14: Cdpoint.com.br | B14: hardrappel | C14: sync750v | D14: Video/Music | E14: 38715 | F14: Y
A15: Cell.com.br | B15: lcarlin | C15: 5876 | D15: Cell Services | F15: N
A16: ceviu.com.br | B16: luizcarlin | C16: sync750v | D16: Jobs | E16: 38715 | F16: Y
A17: cipsga.org.br | B17: gargamel | C17: sync750v | D17: Online Services | E17: 37258 | F17: N
A18: citibank.com.br | B18: luizcarlin | C18: luizao123 | D18: Internet Banking | E18: 38562 | F18: N
A19: cjb.net | B19: hardrappel | C19: sync750v | D19: URL redir | E19: 37249 | F19: N
A20: cjb.net | B20: luizao-gargamel | C20: sync750v | D20: URL redir | E20: 37249 | F20: N
A21: cjb.net | B21: marlboroman | C21: sync750v | D21: URL redir | E21: 37249 | F21: N
A22: Comvc | B22: gargamel -220213 | C22: 280277 | D22: Instant Message | F22: N
A23: counter.li.org | B23: 153198 | C23: 153198-84399 | D23: Counter | E23: 38715 | F23: Y
A24: digitis.com | B24: gargamel_do_rappel | C24: sync750v | D24: Counter | E24: 37249 | F24: N
A25: dromadario.com.br | B25: gargamel | C25: sync750v | D25: Online Services | E25: 37249 | F25: N
A26: ebit.com.br | B26: gargamel@ldapalm.com.br | C26: sync750v | D26: Shopping | E26: 37249 | F26: N
A27: elefante.com.br | B27: luiz.carlin@ibest.com.br | C27: sync750v | D27: Online Services | E27: 38660 | F27: N
A28: ezdir.com.br | B28: hardrappel@icqmail.com | C28: sync750v | D28: URL redir | E28: 37249 | F28: N
A29: freedrive.com | B29: hardrappel | C29: sync750v | D29: Online Services | E29: 37251 | F29: N
A30: gmail.com | B30: luiz.carlin | C30: bucet@69 | D30: e-mail | E30: 38562 | F30: Y | G30: Y
A31: Grupos.com.br | B31: gargamel@ldapalm.com.br | C31: sync750v | D31: Mailling | E31: 37249 | F31: N
A32: Grupos.com.br | B32: gargamel_do_rappel@yahoo.com | C32: sync750v | D32: Mailling | E32: 37249 | F32: N
A33: hotmail.com | B33: gargamel_lac | C33: sync750v | D33: e-mail/Mess | E33: 37249 | F33: N
A34: hotmail.com | B34: luiz_carlin | C34: bucet@69 | D34: e-mail/Mess | E34: 38715 | F34: Y
A35: hpg.com.br | B35: luizcarlin | C35: sync750v | D35: Hosting | E35: 37249 | F35: n | G35: Y
A36: hpg.com.br | B36: hardrappel | C36: sync750v | D36: Hosting | E36: 37249 | F36: N
A37: HSBC Wap | B37: 03650900434 | C37: 9230 | D37: WAP | F37: N
A38: Hsbc.com.br - Novo | B38: 0365 0900434 | C38: sync750 | D38: Internet Banking | E38: 37418 | F38: N
A39: Hsbc.com.br - Velho | B39: 0365 0900434 | C39: 5876 | D39: Internet Banking | F39: N
A40: mercadolivre.com.br | B40: gargamaiden | C40: sync750v | D40: Shopping | E40: 38715 | F40: Y
A41: ICQ | B41: gargamel - 11792390 | C41: bucet@69 | D41: Instant Message | E41: 37251 | F41: Y
A42: ICQ | B42: HardRappel-25012361 | C42: sync750v | D42: Instant Message | E42: 37251 | F42: Y
A43: ICQ | B43: marlboroman - 40934750 | C43: sync750v | D43: Instant Message | E43: 37251 | F43: Y
A44: ICQ | B44: gargamel-46302474 | C44: sync750v | D44: Instant Message | E44: 37251 | F44: Y
A45: icqmail | B45: hardrappel | C45: sync750v | D45: e-mail | E45: 37251 | F45: Y | G45: Y
A46: ieg.com.br | B46: luizcarlin | C46: sync750v | D46: e-mail | E46: 37249 | F46: N
A47: ieg.com.br | B47: hardrappel | C47: sync750v | D47: e-mail | E47: 37249 | F47: N
A48: ig.com.br | B48: hardrappel | C48: sync750v | D48: e-mail | E48: 37251 | F48: Y | G48: Y
A49: imesh.com.br | F49: N
A50: ironmaiden.com | B50: gargamel | C50: sync750v | D50: e-mail | E50: 37251 | F50: N
A51: ironmaiden.com.br | B51: gargamel | C51: sync750v | D51: Online Services | E51: 37251 | F51: N
A52: itraceyou.com | B52: marlboroman | C52: sync750v | D52: e-mail | E52: 37251 | F52: N
A53: jabbercentral.org | B53: GarGamel | C53: sync750v | D53: Online Services | E53: 37251 | F53: N
A54: LdaPalm.com.br | B54: gargamel | C54: sync750v | D54: e-mail | E54: 37242 | F54: N
A55: linuxmall.com.br | B55: luiz.carlin@gmail.com | C55: sync750v | D55: Shopping | E55: 39559 | F55: Y
A56: linuxsecurity.com.br | B56: Gargamel | C56: sync750v | D56: Online Services | E56: 37251 | F56: N
A57: magazineluiza.com | B57: luiz.carlin@gmail.com | C57: sync750v | D57: Shopping | E57: 38715 | F57: Y
A58: mailbr.com.br | B58: hardrappel | C58: sync750v | D58: e-mail | E58: 37251 | F58: N
A59: mailbr.com.br | B59: marlboroman | C59: sync750v | D59: e-mail | E59: 37251 | F59: N
A60: Napster | B60: Hardrappel | C60: lac280277 | D60: File Sharing | F60: N
A61: netcard.com.br | B61: hardrappel | C61: sync750v | D61: Cards | E61: 37251 | F61: N
A62: nextg.com.br | B62: luiz.carlin@gmail.com | C62: sync750v | D62: Online Services | E62: 39559 | F62: Y
A63: Odigo | B63: 423729 | C63: lac280277 | D63: Instant Message | F63: N
A64: olinux.com.br | B64: gargamel | C64: sync750v | D64: Online Services | E64: 37251 | F64: N
A65: oracle.com | B65: hardrappel | C65: sync750v | D65: Online Services | E65: 38715 | F65: Y
A66: orkut.com | B66: luiz.carlin | C66: bucet@69 | D66: Online Comunnity | E66: 38715 | F66: Y
A67: orkut.com | B67: luiz_carlin@yahoo.com.br | C67: luizao123 | D67: Online Comunnity | E67: 38562 | F67: n
A68: Osite.com.br | B68: gargpel | C68: lac2802 | D68: e-mail | F68: N
A69: Rational.com | B69: gargamel | C69: sync750v | D69: Online Services | E69: 37251 | F69: N
A70: Real Wap | B70: luizcarlin 0247 9705879 | C70: 20031979 | D70: WAP | F70: N
A71: redhat.com | B71: luizcarlin | C71: sync750v | D71: Online Services | E71: 38715 | F71: Y
A72: redsex.com.br | B72: hardrappel@ig.com.br | C72: sync750v | D72: Online Services | E72: 37251 | F72: N
A73: saraiva.com.br | B73: luiz.carlin@gmail.com | C73: sync750v | D73: Shopping | E73: 39559 | F73: Y
A74: sexway.com.br | B74: garmamel@ldapalm.com.br | C74: 072622cD | D74: Online Services | F74: N
A75: sexyclub.com.br | B75: gargamel@ldapalm.com.br | C75: garga3570 | D75: Online Services | E75: 37283 | F75: N
A76: sourceforge.org | B76: hardrappel | C76: sync750v | D76: Online Services | E76: 38715 | F76: Y
A77: submarino.com.br | B77: luiz.carlin@gmail.com | C77: sync750v | D77: Shopping | E77: 39559 | F77: Y
A78: sun.com | B78: luizcarlin | C78: sync750v | D78: Online Services | E78: 38715 | F78: Y
A79: super11.net | B79: hrdrapel | C79: lac280277 | D79: e-mail | F79: N
A80: techrepublic.com | B80: luizcarlin@uol.com.br | C80: sync750v | D80: Online Services | E80: 38915 | F80: N
A81: tecwork.com.br | B81: luiz.carlin@ibest.com.br | C81: sync750v | D81: Jobs | E81: 38566 | F81: N
A82: TheCountrer.com | B82: 135914 | C82: sync750v | D82: Counter | E82: 37251 | F82: N
A83: TempoReal.com.br | B83: luiz.carlin@gmail.com | C83: sync750v | D83: Books | E83: 39559 | F83: Y
A84: uol.com.br | B84: luizcarliN@uol.com.br | C84: kppt25 | D84: Online Services | E84: 38712 | F84: N
A85: TheCountrer.com | B85: 2418803 | C85: sync750v | D85: counter | E85: 37251 | F85: N
A86: TheCountrer.com | B86: 2419307 | C86: sync750v | D86: Counter | E86: 37251 | F86: N
A87: Unopar.br | B87: luiz.carlin | C87: IZ5O58 | D87: e-mail | F87: N
A88: uol.com.br | B88: luiz.carlin | C88: ky2cu-cf | D88: Online Services | F88: N
A89: WebOs.com | B89: gargamel | C89: sync750v | D89: e-mail | E89: 37251 | F89: N
A90: Yahoo!Br | B90: wergilio_antunes_fabrin | C90: sync750v | D90: e-mail | E90: 37251 | F90: N
A91: yahoo!geocities | B91: gargamel_do_rappel | C91: sync750v | D91: e-mail | E91: 37251 | F91: N
A92: yahoo.com.br | B92: luiz_carlin | C92: sync750v | D92: e-mail/Mess | E92: 38715 | F92: Y
A93: zipmail.com.br | B93: hardrappel | C93: sync750v | D93: e-mail | E93: 37251 | F93: N
A94: jobshopping.com.br | C94: sync750v | D94: Jobs | E94: 38715 | F94: N
A95: sulamerica.com.br/saudeonline | B95: 445 15054 0000 2316 0012 | C95: 654296 | D95: Online Services | E95: 38573 | F95: N
A96: sulamerica.com.br/saudeonline | B96: 755 63480 0000 2316 0012 | C96: 914352 | D96: Online Services | E96: 38573 | F96: N
A97: arcadenoeh.com.br | B97: luizcarlin | C97: sync750v | D97: Photos | E97: 38715 | F97: Y
A98: Skype | B98: luizcarlin | C98: sync750v | D98: Instant Message | E98: 38588 | F98: Y
A99: msdn.com.br | B99: luiz_carlin@hotmail.com / 103528 | C99: 9q5jycr5 | D99: Online Services | E99: 38715 | F99: y
A100: gazzag.com | B100: luizcarlin | C100: luizao123 | D100: Online Comunnity | E100: 38596 | F100: N
...

Sheet Documentos
A1: Tipo | B1: Numero | C1: Emissao | D1: Validade
A2: RG | B2: 27.454.974-8 ssp/SP | C2: 33367 | D2: 42692
A3: CPF | B3: 212.785.028-90 | C3: 34569
A4: PIS | B4: 127.17912.50.0 | C4: 36293
A5: CNH | B5: 1028869406 | C5: 38035 | D5: 39860
A6: Reservista | B6: RA 14123203556-0 | C6: 34928
A7: Titulo Eleitor | B7: 02373638601-16 Zn 307 Sec 0346 | C7: 38062 | D7: 237363860116
A8: CLT / CTPS | B8: nº 031175 Serie 00218-sp | C8: 35452
A9: CREA | B9: 12.855/D | C9: 38531
A10: Passaporte | B10: FR932650 | C10: 42690 | D10: 46342
A12: Rg Cris | B12: 7.262.861-6 | C12: 34661
A13: Rg Cris | B13: 2.717.198 SSP/DF | C13: 38429
A14: CPF Cris | B14: 041.568.599-08
A15: Titulo Eleitor | B15: 0073032550671
A16: Habilitação | B16: 01962042677
A19: CG Titan 125
A20: RENAVAN | B20: 82001972-0
A21: CHASSIS | B21: 9C2JC30104R067155
A22: MOTOR | B22: JC30E14067155
A23: PLACA | B23: ALL-9328
A25: Careca
A26: CPF | B26: 453.870.528-49
A27: RG | B27: 1.774.386-SSP/SP
B29: 195.378.368-60
A31: CBX Twister 250
A32: RENAVAN | B32: 894942670
A33: CHASSIS | B33: 9C2MC35007R00973
A34: MOTOR
A35: PLACA | B35: DPW-0854
A37: Peugeot 206
A38: RENAVAN | B38: 863321879
A39: CHASSIS | B39: 9362A7LZ96B013136
A40: MOTOR
A41: PLACA | B41: DQH-4141

Sheet FGTS
A1: Data | B1: act Digital | C1: Claro | D1: DXC | E1: Global Hitss | F1: Global Telecom | G1: NTT Data_Everis | H1: TIM | I1: UniTech | J1: Bearing Point | K1: Exactus | L1: Digitep | M1: Total | N1: Diff Mês Anterior | O1: Diff_Mes_Anterior | P1: Projecao | Q1: Total_Projecao | R1: Diff_Projecao | S1: Meta
A2: 41187 | F2: 6302.66 | G2: 0 | H2: 77117.46 | I2: 2920.83 | J2: 2922.37 | K2: 1310.51 | L2: 48.12 | M2: =SUM(H2:L2) -> 84319.29
A3: 41220 | F3: 6302.66 | G3: 0 | H3: 78098.13 | I3: 2928.03 | J3: 2929.57 | K3: 1313.74 | L3: 48.23 | M3: =SUM(H3:L3) -> 85317.7 | N3: =IF(M3<>0,M3-M2,"") -> 998.41 | O3: =IF(N3<>"",(N3/M3),"") -> 0.011702261
A4: 41253 | F4: 6333.78 | G4: 0 | H4: 78984.76 | I4: 2942.48 | J4: 2944.03 | K4: 1320.21 | L4: 48.45 | M4: =SUM(H4:L4) -> 86239.93 | N4: =IF(M4<>0,M4-M3,"") -> 922.23 | O4: =IF(N4<>"",(N4/M4),"") -> 0.01069377 | P4: =IF(N3<>"",M3+N3,"") -> 86316.11 | R4: =IF(M4>0,M4-P4,"") -> -76.18 | S4: =IF(M4>=P4,"SIM","Não") -> Não
A5: 41284 | F5: 6349.39 | G5: 0 | H5: 79679.93 | I5: 2949.73 | J5: 2951.28 | K5: 1323.46 | L5: 48.56 | M5: =SUM(H5:L5) -> 86952.96 | N5: =IF(M5<>0,M5-M4,"") -> 713.03 | O5: =IF(N5<>"",(N5/M5),"") -> 0.0082001809 | P5: =IF(N4<>"",M4+N4,"") -> 87162.16 | R5: =IF(M5>0,M5-P5,"") -> -209.2 | S5: =IF(M5>=P5,"SIM","Não") -> Não
A6: 41315 | F6: 6365.04 | G6: 0 | H6: 80647.67 | I6: 2957 | J6: 2958.55 | K6: 1326.72 | L6: 48.67 | M6: =SUM(H6:L6) -> 87938.61 | N6: =IF(M6<>0,M6-M5,"") -> 985.65 | O6: =IF(N6<>"",(N6/M6),"") -> 0.011208387 | P6: =IF(N5<>"",M5+N5,"") -> 87665.99 | R6: =IF(M6>0,M6-P6,"") -> 272.62 | S6: =IF(M6>=P6,"SIM","Não") -> SIM
A7: 41343 | F7: 6380.73 | G7: 0 | H7: 81869.12 | I7: 2964.29 | J7: 2965.84 | K7: 1329.99 | L7: 48.79 | M7: =SUM(H7:L7) -> 89178.03 | N7: =IF(M7<>0,M7-M6,"") -> 1239.42 | O7: =IF(N7<>"",(N7/M7),"") -> 0.013898266 | P7: =IF(N6<>"",M6+N6,"") -> 88924.26 | R7: =IF(M7>0,M7-P7,"") -> 253.77 | S7: =IF(M7>=P7,"SIM","Não") -> SIM
A8: 41374 | F8: 6396.46 | G8: 0 | H8: 83411.85 | I8: 2971.59 | J8: 2973.15 | K8: 1333.29 | L8: 48.91 | M8: =SUM(H8:L8) -> 90738.79 | N8: =IF(M8<>0,M8-M7,"") -> 1560.76 | O8: =IF(N8<>"",(N8/M8),"") -> 0.017200582 | P8: =IF(N7<>"",M7+N7,"") -> 90417.45 | R8: =IF(M8>0,M8-P8,"") -> 321.34 | S8: =IF(M8>=P8,"SIM","Não") -> SIM
A9: 41404 | F9: 6412.23 | G9: 0 | H9: 85712.45 | I9: 2978.91 | J9: 2980.48 | K9: 1336.54 | L9: 49.03 | M9: =SUM(H9:L9) -> 93057.41 | N9: =IF(M9<>0,M9-M8,"") -> 2318.62 | O9: =IF(N9<>"",(N9/M9),"") -> 0.024916017 | P9: =IF(N8<>"",M8+N8,"") -> 92299.55 | R9: =IF(M9>0,M9-P9,"") -> 757.86 | S9: =IF(M9>=P9,"SIM","Não") -> SIM
A10: 41435 | F10: 6428.04 | G10: 0 | H10: 87537.78 | I10: 2986.25 | J10: 2987.82 | K10: 1339.83 | L10: 49.15 | M10: =SUM(H10:L10) -> 94900.83 | N10: =IF(M10<>0,M10-M9,"") -> 1843.42 | O10: =IF(N10<>"",(N10/M10),"") -> 0.019424698 | P10: =IF(N9<>"",M9+N9,"") -> 95376.03 | R10: =IF(M10>0,M10-P10,"") -> -475.2 | S10: =IF(M10>=P10,"SIM","Não") -> Não
A11: 41465 | F11: 6443.89 | G11: 0 | H11: 88780.28 | I11: 2993.61 | J11: 2995.18 | K11: 1343.13 | L11: 49.27 | M11: =SUM(H11:L11) -> 96161.47 | N11: =IF(M11<>0,M11-M10,"") -> 1260.64 | O11: =IF(N11<>"",(N11/M11),"") -> 0.013109617 | P11: =IF(N10<>"",M10+N10,"") -> 96744.25 | R11: =IF(M11>0,M11-P11,"") -> -582.78 | S11: =IF(M11>=P11,"SIM","Não") -> Não
A12: 41496 | F12: 6461.12 | G12: 0 | H12: 91474.27 | I12: 3001.61 | J12: 3003.19 | K12: 1346.72 | L12: 49.4 | M12: =SUM(H12:L12) -> 98875.19 | N12: =IF(M12<>0,M12-M11,"") -> 2713.72 | O12: =IF(N12<>"",(N12/M12),"") -> 0.027445914 | P12: =IF(N11<>"",M11+N11,"") -> 97422.11 | R12: =IF(M12>0,M12-P12,"") -> 1453.08 | S12: =IF(M12>=P12,"SIM","Não") -> SIM
A13: 41527 | F13: 6477.05 | G13: 0 | H13: 92213.73 | I13: 3009.01 | J13: 3010.59 | K13: 1350.04 | L13: 49.52 | M13: =SUM(H13:L13) -> 99632.89 | N13: =IF(M13<>0,M13-M12,"") -> 757.7 | O13: =IF(N13<>"",(N13/M13),"") -> 0.0076049184 | P13: =IF(N12<>"",M12+N12,"") -> 101588.91 | R13: =IF(M13>0,M13-P13,"") -> -1956.02 | S13: =IF(M13>=P13,"SIM","Não") -> Não
A14: 41557 | F14: 6477.05 | G14: 0 | H14: 92213.73 | I14: 3009.01 | J14: 3010.59 | K14: 1350.04 | L14: 49.52 | M14: =SUM(H14:L14) -> 99632.89 | N14: =IF(M14<>0,M14-M13,"") -> 0 | O14: =IF(N14<>"",(N14/M14),"") -> 0 | P14: =IF(N13<>"",M13+N13,"") -> 100390.59 | R14: =IF(M14>0,M14-P14,"") -> -757.7 | S14: =IF(M14>=P14,"SIM","Não") -> Não
A15: 41588 | F15: 6515.53 | G15: 0 | H15: 94301.2 | I15: 3026.88 | J15: 3028.47 | K15: 1358.05 | L15: 49.8 | M15: =SUM(H15:L15) -> 101764.4 | N15: =IF(M15<>0,M15-M14,"") -> 2131.51 | O15: =IF(N15<>"",(N15/M15),"") -> 0.020945537 | P15: =IF(N14<>"",M14+N14,"") -> 99632.89 | R15: =IF(M15>0,M15-P15,"") -> 2131.51 | S15: =IF(M15>=P15,"SIM","Não") -> SIM
... A24: 42073 | F24: 6847.49 | G24: 0 | H24: 1234.34 | I24: 3181.05 | J24: 3182.74 | K24: 1427.16 | L24: 52.26 | M24: =SUM(H24:L24) -> 9077.55 | N24: =IF(M24<>0,M24-M23,"") -> 23.82 | O24: =IF(N24<>"",(N24/M24),"") -> 0.0026240561 | P24: =IF(N23<>"",M23+N23,"") -> 10338.24 | R24: =IF(M24>0,M24-P24,"") -> -1260.69 | S24: =IF(M24>=P24,"SIM","Não") -> Não
A25: 42104 | F25: 6873.27 | G25: 626.39 | H25: 1238.98 | I25: 3193.02 | J25: 3194.72 | K25: 1432.53 | L25: 52.45 | M25: =SUM(G25:L25) -> 9738.09 | N25: =IF(M25<>0,M25-M24,"") -> 660.54 | O25: =IF(N25<>"",(N25/M25),"") -> 0.06783055 | P25: =IF(N24<>"",M24+N24,"") -> 9101.37 | R25: =IF(M25>0,M25-P25,"") -> 636.72 | S25: =IF(M25>=P25,"SIM","Não") -> SIM
A26: 42134 | F26: 6897.61 | G26: 1276.61 | H26: 1243.36 | I26: 3204.32 | J26: 3206.03 | K26: 1437.6 | L26: 52.63 | M26: =SUM(G26:L26) -> 10420.55 | N26: =IF(M26<>0,M26-M25,"") -> 682.46 | O26: =IF(N26<>"",(N26/M26),"") -> 0.065491745 | P26: =IF(N25<>"",M25+N25,"") -> 10398.63 | R26: =IF(M26>0,M26-P26,"") -> 21.92 | S26: =IF(M26>=P26,"SIM","Não") -> SIM
A27: 42165 | F27: 6922.59 | G27: 2482.05 | H27: 1247.86 | I27: 3215.92 | J27: 3217.64 | K27: 1442.8 | L27: 52.82 | M27: =SUM(G27:L27) -> 11659.09 | N27: =IF(M27<>0,M27-M26,"") -> 1238.54 | O27: =IF(N27<>"",(N27/M27),"") -> 0.10622956 | P27: =IF(N26<>"",M26+N26,"") -> 11103.01 | R27: =IF(M27>0,M27-P27,"") -> 556.08 | S27: =IF(M27>=P27,"SIM","Não") -> SIM
A28: 42195 | F28: 6952.23 | G28: 3433.72 | H28: 1253.2 | I28: 3229.69 | J28: 3231.42 | K28: 1448.97 | L28: 53.04 | M28: =SUM(G28:L28) -> 12650.04 | N28: =IF(M28<>0,M28-M27,"") -> 990.95 | O28: =IF(N28<>"",(N28/M28),"") -> 0.078335721 | P28: =IF(N27<>"",M27+N27,"") -> 12897.63 | R28: =IF(M28>0,M28-P28,"") -> -247.59 | S28: =IF(M28>=P28,"SIM","Não") -> Não
A29: 42226 | F29: 6985.43 | G29: 5202.73 | H29: 1259.18 | I29: 3245.11 | J29: 3246.85 | K29: 1455.89 | L29: 53.29 | M29: =SUM(G29:L29) -> 14463.05 | N29: =IF(M29<>0,M29-M28,"") -> 1813.01 | O29: =IF(N29<>"",(N29/M29),"") -> 0.12535461 | P29: =IF(N28<>"",M28+N28,"") -> 13640.99 | R29: =IF(M29>0,M29-P29,"") -> 822.06 | S29: =IF(M29>=P29,"SIM","Não") -> SIM
A30: 42257 | F30: 7015.72 | G30: 6452.04 | H30: 1264.64 | I30: 3259.18 | J30: 3260.93 | K30: 1462.2 | L30: 53.52 | M30: =SUM(G30:L30) -> 15752.51 | N30: =IF(M30<>0,M30-M29,"") -> 1289.46 | O30: =IF(N30<>"",(N30/M30),"") -> 0.081857431 | P30: =IF(N29<>"",M29+N29,"") -> 16276.06 | R30: =IF(M30>0,M30-P30,"") -> -523.55 | S30: =IF(M30>=P30,"SIM","Não") -> Não
A31: 42287 | F31: 7046.51 | G31: 7653.62 | H31: 1270.19 | I31: 3273.48 | J31: 3275.24 | K31: 1468.61 | L31: 53.75 | M31: =SUM(G31:L31) -> 16994.89 | N31: =IF(M31<>0,M31-M30,"") -> 1242.38 | O31: =IF(N31<>"",(N31/M31),"") -> 0.07310315 | P31: =IF(N30<>"",M30+N30,"") -> 17041.97 | R31: =IF(M31>0,M31-P31,"") -> -47.08 | S31: =IF(M31>=P31,"SIM","Não") -> Não
A32: 42318 | F32: 7076.52 | G32: 8830.13 | H32: 1275.6 | I32: 3287.42 | J32: 3289.19 | K32: 1474.86 | L32: 53.97 | M32: =SUM(G32:L32) -> 18211.17 | N32: =IF(M32<>0,M32-M31,"") -> 1216.28 | O32: =IF(N32<>"",(N32/M32),"") -> 0.066787581 | P32: =IF(N31<>"",M31+N31,"") -> 18237.27 | R32: =IF(M32>0,M32-P32,"") -> -26.1 | S32: =IF(M32>=P32,"SIM","Não") -> Não
A33: 42348 | F33: 7103.17 | G33: 10094.8 | H33: 1280.4 | I33: 3299.8 | J33: 3301.57 | K33: 1480.41 | L33: 54.17 | M33: =SUM(G33:L33) -> 19511.15 | N33: =IF(M33<>0,M33-M32,"") -> 1299.98 | O33: =IF(N33<>"",(N33/M33),"") -> 0.066627544 | P33: =IF(N32<>"",M32+N32,"") -> 19427.45 | R33: =IF(M33>0,M33-P33,"") -> 83.7 | S33: =IF(M33>=P33,"SIM","Não") -> SIM
A34: 42379 | F34: 7136.7 | G34: 11922.27 | H34: 1286.44 | I34: 3315.37 | J34: 3317.15 | K34: 1487.39 | L34: 54.42 | M34: =SUM(G34:L34) -> 21383.04 | N34: =IF(M34<>0,M34-M33,"") -> 1871.89 | O34: =IF(N34<>"",(N34/M34),"") -> 0.087540874 | P34: =IF(N33<>"",M33+N33,"") -> 20811.13 | R34: =IF(M34>0,M34-P34,"") -> 571.91 | S34: =IF(M34>=P34,"SIM","Não") -> SIM
A35: 42410 | F35: 7163.74 | G35: 12864.11 | H35: 1291.31 | I35: 3327.93 | J35: 3329.71 | K35: 1493.02 | L35: 54.62 | M35: =SUM(G35:L35) -> 22360.7 | N35: =IF(M35<>0,M35-M34,"") -> 977.66 | O35: =IF(N35<>"",(N35/M35),"") -> 0.043722245 | P35: =IF(N34<>"",M34+N34,"") -> 23254.93 | R35: =IF(M35>0,M35-P35,"") -> -894.23 | S35: =IF(M35>=P35,"SIM","Não") -> Não
A36: 42439 | F36: 7188.27 | G36: 13665.53 | H36: 1295.73 | I36: 3339.32 | J36: 3341.11 | K36: 1498.13 | L36: 54.8 | M36: =SUM(G36:L36) -> 23194.62 | N36: =IF(M36<>0,M36-M35,"") -> 833.92 | O36: =IF(N36<>"",(N36/M36),"") -> 0.035953165 | P36: =IF(N35<>"",M35+N35,"") -> 23338.36 | R36: =IF(M36>0,M36-P36,"") -> -143.74 | S36: =IF(M36>=P36,"SIM","Não") -> Não
... A80: 43779 | F80: 8252.78 | G80: 0 | H80: 0 | I80: 0 | J80: 0 | K80: 0 | L80: 0 | M80: =SUM(G80:L80) -> 0 | N80: =IF(M80<>0,M80-M79,"") | O80: =IF(N80<>"",(N80/M80),"") | P80: =IF(N79<>"",M79+N79,"") | R80: =IF(M80>0,M80-P80,"") | S80: =IF(M80>=P80,"SIM","Não") -> Não
A81: 43809 | E81: 540.01 | F81: 8252.78 | G81: 0 | H81: 0 | I81: 0 | J81: 0 | K81: 0 | L81: 0 | M81: =SUM(E81:L81) -> 8792.79 | N81: =IF(M81<>0,M81-M80,"") -> 8792.79 | O81: =IF(N81<>"",(N81/M81),"") -> 1 | P81: =IF(N80<>"",M80+N80,"") | R81: =IF(M81>0,M81-P81,"") -> #VALUE! | S81: =IF(M81>=P81,"SIM","Não") -> Não
A82: 43840 | E82: 1321.35 | F82: 8293.53 | G82: 0 | H82: 0 | I82: 0 | J82: 0 | K82: 0 | L82: 0 | M82: =SUM(E82:L82) -> 9614.88 | N82: =IF(M82<>0,M82-M81,"") -> 822.09 | O82: =IF(N82<>"",(N82/M82),"") -> 0.085501847 | P82: =IF(N81<>"",AVERAGE(N79:N81),"") -> 8792.79 | Q82: =M81+P82 -> 17585.58 | R82: =IF(M82>0,M82-Q82,"") -> -7970.7 | S82: =IF(M82>=P82,"SIM","Não") -> SIM
A83: 43871 | E83: 2044.61 | F83: 8313.98 | G83: 0 | H83: 0 | I83: 0 | J83: 0 | K83: 0 | L83: 0 | M83: =SUM(E83:L83) -> 10358.59 | N83: =IF(M83<>0,M83-M82,"") -> 743.71 | O83: =IF(N83<>"",(N83/M83),"") -> 0.071796451 | P83: =IF(N82<>"",AVERAGE(N80:N82),"") -> 4807.44 | Q83: =M82+P83 -> 14422.32 | R83: =IF(M83>0,M83-Q83,"") -> -4063.73 | S83: =IF(M83>=P83,"SIM","Não") -> SIM
A84: 43900 | E84: 2769.66 | F84: 8334.48 | G84: 0 | H84: 0 | I84: 0 | J84: 0 | K84: 0 | L84: 0 | M84: =SUM(E84:L84) -> 11104.14 | N84: =IF(M84<>0,M84-M83,"") -> 745.55 | O84: =IF(N84<>"",(N84/M84),"") -> 0.067141625 | P84: =IF(N83<>"",AVERAGE(N81:N83),"") -> 3452.8633 | Q84: =M83+P84 -> 13811.453 | R84: =IF(M84>0,M84-Q84,"") -> -2707.3133 | S84: =IF(M84>=P84,"SIM","Não") -> SIM
A85: 43931 | E85: 0 | F85: 8355.03 | G85: 0 | H85: 0 | I85: 0 | J85: 0 | K85: 0 | L85: 0 | M85: =SUM(E85:L85) -> 8355.03 | N85: =IF(M85<>0,M85-M84,"") -> -2749.11 | O85: =IF(N85<>"",(N85/M85),"") -> -0.32903652 | P85: =IF(N84<>"",AVERAGE(N82:N84),"") -> 770.45 | Q85: =M84+P85 -> 11874.59 | R85: =IF(M85>0,M85-Q85,"") -> -3519.56 | S85: =IF(M85>=P85,"SIM","Não") -> SIM
A86: 44326 | E86: 10.14 | F86: 8782.83 | G86: 0 | H86: 0 | I86: 0 | J86: 0 | K86: 0 | L86: 0 | M86: =SUM(E86:L86) -> 8792.97 | N86: =IF(M86<>0,M86-M85,"") -> 437.94 | O86: =IF(N86<>"",(N86/M86),"") -> 0.049805697 | P86: =IF(N85<>"",AVERAGE(N83:N85),"") -> -419.95 | Q86: =M85+P86 -> 7935.08 | R86: =IF(M86>0,M86-Q86,"") -> 857.89 | S86: =IF(M86>=P86,"SIM","Não") -> SIM
A87: 44357 | D87: 660.81 | E87: 10.16 | F87: 8804.48 | G87: 0 | H87: 0 | I87: 0 | J87: 0 | K87: 0 | L87: 0 | M87: =SUM(D87:L87) -> 9475.45 | N87: =IF(M87<>0,M87-M86,"") -> 682.48 | O87: =IF(N87<>"",(N87/M87),"") -> 0.072026131 | P87: =IF(N86<>"",AVERAGE(N84:N86),"") -> -521.87333 | Q87: =M86+P87 -> 8271.0967 | R87: =IF(M87>0,M87-Q87,"") -> 1204.3533 | S87: =IF(M87>=Q87,"SIM","Não") -> SIM
A88: 44387 | D88: 1921.1 | E88: 10.18 | F88: 8826.19 | G88: 0 | H88: 0 | I88: 0 | J88: 0 | K88: 0 | L88: 0 | M88: =SUM(D88:L88) -> 10757.47 | N88: =IF(M88<>0,M88-M87,"") -> 1282.02 | O88: =IF(N88<>"",(N88/M88),"") -> 0.11917486 | P88: =IF(N87<>"",AVERAGE(N85:N87),"") -> -542.89667 | Q88: =M87+P88 -> 8932.5533 | R88: =IF(M88>0,M88-Q88,"") -> 1824.9167 | S88: =IF(M88>=Q88,"SIM","Não") -> SIM
A89: 44418 | D89: 2869.84 | E89: 10.2 | F89: 8847.95 | G89: 0 | H89: 0 | I89: 0 | J89: 0 | K89: 0 | L89: 0 | M89: =SUM(D89:L89) -> 11727.99 | N89: =IF(M89<>0,M89-M88,"") -> 970.52 | O89: =IF(N89<>"",(N89/M89),"") -> 0.082752458 | P89: =IF(N88<>"",AVERAGE(N86:N88),"") -> 800.81333 | Q89: =M88+P89 -> 11558.283 | R89: =IF(M89>0,M89-Q89,"") -> 169.70667 | S89: =IF(M89>=Q89,"SIM","Não") -> SIM
A90: 44449 | D90: 3820.92 | E90: 10.4 | F90: 9031.82 | G90: 0 | H90: 0 | I90: 0 | J90: 0 | K90: 0 | L90: 0 | M90: =SUM(D90:L90) -> 12863.14 | N90: =IF(M90<>0,M90-M89,"") -> 1135.15 | O90: =IF(N90<>"",(N90/M90),"") -> 0.088248282 | P90: =IF(N89<>"",AVERAGE(N87:N89),"") -> 978.34 | Q90: =M89+P90 -> 12706.33 | R90: =IF(M90>0,M90-Q90,"") -> 156.81 | S90: =IF(M90>=Q90,"SIM","Não") -> SIM
A91: 44479 | D91: 4774.35 | E91: 10.42 | F91: 9054.09 | G91: 0 | H91: 0 | I91: 0 | J91: 0 | K91: 0 | L91: 0 | M91: =SUM(D91:L91) -> 13838.86 | N91: =IF(M91<>0,M91-M90,"") -> 975.72 | O91: =IF(N91<>"",(N91/M91),"") -> 0.070505808 | P91: =IF(N90<>"",AVERAGE(N88:N90),"") -> 1129.23 | Q91: =IF(P91>0,M90+P91,"") -> 13992.37 | R91: =IF(M91>0,M91-Q91,"") -> -153.51 | S91: =IF(M91>=Q91,"SIM","Não") -> Não
A92: 44510 | D92: 5730.13 | E92: 10.44 | F92: 9076.41 | G92: 0 | H92: 0 | I92: 0 | J92: 0 | K92: 0 | L92: 0 | M92: =SUM(D92:L92) -> 14816.98 | N92: =IF(M92<>0,M92-M91,"") -> 978.12 | O92: =IF(N92<>"",(N92/M92),"") -> 0.066013452 | P92: =IF(N91<>"",AVERAGE(N89:N91),"") -> 1027.13 | Q92: =IF(M91>0,M91+P92,"") -> 14865.99 | R92: =IF(M92>0,M92-Q92,"") -> -49.01 | S92: =IF(M92>=Q92,"SIM","Não") -> Não
A93: 44540 | D93: 6688.27 | E93: 10.46 | F93: 9098.79 | M93: =SUM(D93:L93) -> 15797.52 | N93: =IF(M93<>0,M93-M92,"") -> 980.54 | O93: =IF(N93<>"",(N93/M93),"") -> 0.062069236 | P93: =IF(N92<>"",AVERAGE(N90:N92),"") -> 1029.6633 | Q93: =IF(M92>0,M92+P93,"") -> 15846.643 | R93: =IF(M93>0,M93-Q93,"") -> -49.123333 | S93: =IF(M93>=Q93,"SIM","Não") -> Não
A94: 44571 | D94: 7966.7 | E94: 10.49 | F94: 9125.67 | M94: =SUM(D94:L94) -> 17102.86 | N94: =IF(M94<>0,M94-M93,"") -> 1305.34 | O94: =IF(N94<>"",(N94/M94),"") -> 0.076322907 | P94: =IF(N93<>"",AVERAGE(N91:N93),"") -> 978.12667 | Q94: =IF(M93>0,M93+P94,"") -> 16775.647 | R94: =IF(M94>0,M94-Q94,"") -> 327.21333 | S94: =IF(M94>=Q94,"SIM","Não") -> SIM
A95: 44602 | D95: 8999.18 | E95: 10.52 | F95: 9153.7 | M95: =SUM(D95:L95) -> 18163.4 | N95: =IF(M95<>0,M95-M94,"") -> 1060.54 | O95: =IF(N95<>"",(N95/M95),"") -> 0.058388848 | P95: =IF(N94<>"",AVERAGE(N92:N94),"") -> 1088 | Q95: =IF(M94>0,M94+P95,"") -> 18190.86 | R95: =IF(M95>0,M95-Q95,"") -> -27.46 | S95: =IF(M95>=Q95,"SIM","Não") -> Não
A96: 44630 | D96: 10029.38 | E96: 10.54 | F96: 9176.27 | M96: =SUM(D96:L96) -> 19216.19 | N96: =IF(M96<>0,M96-M95,"") -> 1052.79 | O96: =IF(N96<>"",(N96/M96),"") -> 0.054786615 | P96: =IF(N95<>"",AVERAGE(N93:N95),"") -> 1115.4733 | Q96: =IF(M95>0,M95+P96,"") -> 19278.873 | R96: =IF(M96>0,M96-Q96,"") -> -62.683333 | S96: =IF(M96>=Q96,"SIM","Não") -> Não
A97: 44661 | D97: 11071.88 | E97: 10.57 | F97: 9207.82 | M97: =SUM(D97:L97) -> 20290.27 | N97: =IF(M97<>0,M97-M96,"") -> 1074.08 | O97: =IF(N97<>"",(N97/M97),"") -> 0.052935717 | P97: =IF(N96<>"",AVERAGE(N94:N96),"") -> 1139.5567 | Q97: =IF(M96>0,M96+P97,"") -> 20355.747 | R97: =IF(M97>0,M97-Q97,"") -> -65.476667 | S97: =IF(M97>=Q97,"SIM","Não") -> Não
A98: 44691 | D98: 12113.34 | E98: 10.6 | F98: 9235.64 | M98: =SUM(D98:L98) -> 21359.58 | N98: =IF(M98<>0,M98-M97,"") -> 1069.31 | O98: =IF(N98<>"",(N98/M98),"") -> 0.050062314 | P98: =IF(N97<>"",AVERAGE(N95:N97),"") -> 1062.47 | Q98: =IF(M97>0,M97+P98,"") -> 21352.74 | R98: =IF(M98>0,M98-Q98,"") -> 6.84 | S98: =IF(M98>=Q98,"SIM","Não") -> SIM
A99: 44722 | D99: 13171.41 | E99: 10.64 | F99: 9273.81 | M99: =SUM(D99:L99) -> 22455.86 | N99: =IF(M99<>0,M99-M98,"") -> 1096.28 | O99: =IF(N99<>"",(N99/M99),"") -> 0.048819328 | P99: =IF(N98<>"",AVERAGE(N96:N98),"") -> 1065.3933 | Q99: =IF(M98>0,M98+P99,"") -> 22424.973 | R99: =IF(M99>0,M99-Q99,"") -> 30.886667 | S99: =IF(M99>=Q99,"SIM","Não") -> SIM
A100: 44752 | D100: 14735.48 | E100: 10.68 | F100: 9310.46 | M100: =SUM(D100:L100) -> 24056.62 | N100: =IF(M100<>0,M100-M99,"") -> 1600.76 | O100: =IF(N100<>"",(N100/M100),"") -> 0.066541351 | P100: =IF(N99<>"",AVERAGE(N97:N99),"") -> 1079.89 | Q100: =IF(M99>0,M99+P100,"") -> 23535.75 | R100: =IF(M100>0,M100-Q100,"") -> 520.87 | S100: =IF(M100>=Q100,"SIM","Não") -> SIM
A101: 44783 | D101: 0 | E101: 11 | F101: 9599.76 | M101: =SUM(D101:L101) -> 9610.76 | N101: =IF(M101<>0,M101-M100,"") -> -14445.86 | O101: =IF(N101<>"",(N101/M101),"") -> -1.5030924 | P101: =IF(N100<>"",AVERAGE(N98:N100),"") -> 1255.45 | Q101: =IF(M100>0,M100+P101,"") -> 25312.07 | R101: =IF(M101>0,M101-Q101,"") -> -15701.31 | S101: =IF(M101>=Q101,"SIM","Não") -> Não
A102: 44814 | C102: 426.67 | E102: 11.05 | F102: 9646.61 | M102: =SUM(C102:L102) -> 10084.33 | N102: =IF(M102<>0,M102-M101,"") -> 473.57 | O102: =IF(N102<>"",(N102/M102),"") -> 0.046960978 | P102: =IF(N101<>"",AVERAGE(N99:N101),"") -> -3916.2733 | Q102: =IF(M101>0,M101+P102,"") -> 5694.4867 | R102: =IF(M102>0,M102-Q102,"") -> 4389.8433 | S102: =IF(M102>=Q102,"SIM","Não") -> SIM
A103: 44844 | C103: 1228.5 | E103: 11.09 | F103: 9687.84 | M103: =SUM(C103:L103) -> 10927.43 | N103: =IF(M103<>0,M103-M102,"") -> 843.1 | O103: =IF(N103<>"",(N103/M103),"") -> 0.077154464 | P103: =IF(N102<>"",AVERAGE(N100:N102),"") -> -4123.8433 | Q103: =IF(M102>0,M102+P103,"") -> 5960.4867 | R103: =IF(M103>0,M103-Q103,"") -> 4966.9433 | S103: =IF(M103>=Q103,"SIM","Não") -> SIM
A104: 44875 | C104: 2129.37 | E104: 11.13 | F104: 9726.23 | M104: =SUM(C104:L104) -> 11866.73 | N104: =IF(M104<>0,M104-M103,"") -> 939.3 | O104: =IF(N104<>"",(N104/M104),"") -> 0.079154072 | P104: =IF(N103<>"",AVERAGE(N101:N103),"") -> -4376.3967 | Q104: =IF(M103>0,M103+P104,"") -> 6551.0333 | R104: =IF(M104>0,M104-Q104,"") -> 5315.6967 | S104: =IF(M104>=Q104,"SIM","Não") -> SIM
A105: 44905 | C105: 3162.5 | E105: 11.17 | F105: 9764.9 | M105: =SUM(C105:L105) -> 12938.57 | N105: =IF(M105<>0,M105-M104,"") -> 1071.84 | O105: =IF(N105<>"",(N105/M105),"") -> 0.082840685 | P105: =IF(N104<>"",AVERAGE(N102:N104),"") -> 751.99 | Q105: =IF(M104>0,M104+P105,"") -> 12618.72 | R105: =IF(M105>0,M105-Q105,"") -> 319.85 | S105: =IF(M105>=Q105,"SIM","Não") -> SIM
A106: 44936 | C106: 4201.53 | E106: 11.22 | F106: 9809.26 | M106: =SUM(C106:L106) -> 14022.01 | N106: =IF(M106<>0,M106-M105,"") -> 1083.44 | O106: =IF(N106<>"",(N106/M106),"") -> 0.077267097 | P106: =IF(N105<>"",AVERAGE(N103:N105),"") -> 951.41333 | Q106: =IF(M105>0,M105+P106,"") -> 13889.983 | R106: =IF(M106>0,M106-Q106,"") -> 132.02667 | S106: =IF(M106>=Q106,"SIM","Não") -> SIM
A107: 44967 | C107: 5068.66 | E107: 11.27 | F107: 9853.91 | M107: =SUM(C107:L107) -> 14933.84 | N107: =IF(M107<>0,M107-M106,"") -> 911.83 | O107: =IF(N107<>"",(N107/M107),"") -> 0.061057973 | P107: =IF(N106<>"",AVERAGE(N104:N106),"") -> 1031.5267 | Q107: =IF(M106>0,M106+P107,"") -> 15053.537 | R107: =IF(M107>0,M107-Q107,"") -> -119.69667 | S107: =IF(M107>=Q107,"SIM","Não") -> Não
A108: 44995 | C108: 5933.38 | E108: 11.3 | F108: 9886.4 | M108: =SUM(C108:L108) -> 15831.08 | N108: =IF(M108<>0,M108-M107,"") -> 897.24 | O108: =IF(N108<>"",(N108/M108),"") -> 0.056675855 | P108: =IF(N107<>"",AVERAGE(N105:N107),"") -> 1022.37 | Q108: =IF(M107>0,M107+P108,"") -> 15956.21 | R108: =IF(M108>0,M108-Q108,"") -> -125.13 | S108: =IF(M108>=Q108,"SIM","Não") -> Não
A109: 45026 | C109: 6810.24 | E109: 11.35 | F109: 9934.48 | M109: =SUM(C109:L109) -> 16756.07 | N109: =IF(M109<>0,M109-M108,"") -> 924.99 | O109: =IF(N109<>"",(N109/M109),"") -> 0.055203279 | P109: =IF(N108<>"",AVERAGE(N106:N108),"") -> 964.17 | Q109: =IF(M108>0,M108+P109,"") -> 16795.25 | R109: =IF(M109>0,M109-Q109,"") -> -39.18 | S109: =IF(M109>=Q109,"SIM","Não") -> Não
A110: 45056 | C110: 7680.64 | E110: 11.38 | F110: 9967.15 | M110: =SUM(C110:L110) -> 17659.17 | N110: =IF(M110<>0,M110-M109,"") -> 903.1 | O110: =IF(N110<>"",(N110/M110),"") -> 0.051140569 | P110: =IF(N109<>"",AVERAGE(N107:N109),"") -> 911.35333 | Q110: =IF(M109>0,M109+P110,"") -> 17667.423 | R110: =IF(M110>0,M110-Q110,"") -> -8.2533333 | S110: =IF(M110>=Q110,"SIM","Não") -> Não
A111: 45087 | C111: 8564.11 | E111: 11.43 | F111: 10016.17 | M111: =SUM(C111:L111) -> 18591.71 | N111: =IF(M111<>0,M111-M110,"") -> 932.54 | O111: =IF(N111<>"",(N111/M111),"") -> 0.050158915 | P111: =IF(N110<>"",AVERAGE(N108:N110),"") -> 908.44333 | Q111: =IF(M110>0,M110+P111,"") -> 18567.613 | R111: =IF(M111>0,M111-Q111,"") -> 24.096667 | S111: =IF(M111>=Q111,"SIM","Não") -> SIM
A112: 45117 | C112: 9448.68 | E112: 11.47 | F112: 10055.91 | M112: =SUM(C112:L112) -> 19516.06 | N112: =IF(M112<>0,M112-M111,"") -> 924.35 | O112: =IF(N112<>"",(N112/M112),"") -> 0.047363556 | P112: =IF(N111<>"",AVERAGE(N109:N111),"") -> 920.21 | Q112: =IF(M111>0,M111+P112,"") -> 19511.92 | R112: =IF(M112>0,M112-Q112,"") -> 4.14 | S112: =IF(M112>=Q112,"SIM","Não") -> SIM
A113: 45148 | C113: 10413.12 | E113: 11.78 | F113: 10337.98 | M113: =SUM(C113:L113) -> 20762.88 | N113: =IF(M113<>0,M113-M112,"") -> 1246.82 | O113: =IF(N113<>"",(N113/M113),"") -> 0.060050436 | P113: =IF(N112<>"",AVERAGE(N110:N112),"") -> 919.99667 | Q113: =IF(M112>0,M112+P113,"") -> 20436.057 | R113: =IF(M113>0,M113-Q113,"") -> 326.82333 | S113: =IF(M113>=Q113,"SIM","Não") -> SIM
A114: 45179 | C114: 11309.35 | E114: 0 | F114: 10385.85 | M114: =SUM(C114:L114) -> 21695.2 | N114: =IF(M114<>0,M114-M113,"") -> 932.32 | O114: =IF(N114<>"",(N114/M114),"") -> 0.042973561 | P114: =IF(N113<>"",AVERAGE(N111:N113),"") -> 1034.57 | Q114: =IF(M113>0,M113+P114,"") -> 21797.45 | R114: =IF(M114>0,M114-Q114,"") -> -102.25 | S114: =IF(M114>=Q114,"SIM","Não") -> Não
A115: 45209 | C115: 12198.06 | F115: 10423.22 | M115: =SUM(C115:L115) -> 22621.28 | N115: =IF(M115<>0,M115-M114,"") -> 926.08 | O115: =IF(N115<>"",(N115/M115),"") -> 0.040938444 | P115: =IF(N114<>"",AVERAGE(N112:N114),"") -> 1034.4967 | Q115: =IF(M114>0,M114+P115,"") -> 22729.697 | R115: =IF(M115>0,M115-Q115,"") -> -108.41667 | S115: =IF(M115>=Q115,"SIM","Não") -> Não
A116: 45240 | C116: 13089.05 | F116: 10459.95 | M116: =SUM(C116:L116) -> 23549 | N116: =IF(M116<>0,M116-M115,"") -> 927.72 | O116: =IF(N116<>"",(N116/M116),"") -> 0.039395303 | P116: =IF(N115<>"",AVERAGE(N113:N115),"") -> 1035.0733 | Q116: =IF(M115>0,M115+P116,"") -> 23656.353 | R116: =IF(M116>0,M116-Q116,"") -> -107.35333 | S116: =IF(M116>=Q116,"SIM","Não") -> Não
A117: 45270 | C117: 14403.5 | F117: 10493.87 | M117: =SUM(C117:L117) -> 24897.37 | N117: =IF(M117<>0,M117-M116,"") -> 1348.37 | O117: =IF(N117<>"",(N117/M117),"") -> 0.054157126 | P117: =IF(N116<>"",AVERAGE(N114:N116),"") -> 928.70667 | Q117: =IF(M116>0,M116+P117,"") -> 24477.707 | R117: =IF(M117>0,M117-Q117,"") -> 419.66333 | S117: =IF(M117>=Q117,"SIM","Não") -> SIM
A118: 45301 | C118: 15720.98 | F118: 10526.99 | M118: =SUM(C118:L118) -> 26247.97 | N118: =IF(M118<>0,M118-M117,"") -> 1350.6 | O118: =IF(N118<>"",(N118/M118),"") -> 0.051455408 | P118: =IF(N117<>"",AVERAGE(N115:N117),"") -> 1067.39 | Q118: =IF(M117>0,M117+P118,"") -> 25964.76 | R118: =IF(M118>0,M118-Q118,"") -> 283.21 | S118: =IF(M118>=Q118,"SIM","Não") -> SIM
A119: 45332 | C119: 16647.48 | F119: 10562.18 | M119: =SUM(C119:L119) -> 27209.66 | N119: =IF(M119<>0,M119-M118,"") -> 961.69 | O119: =IF(N119<>"",(N119/M119),"") -> 0.035343698 | P119: =IF(N118<>"",AVERAGE(N116:N118),"") -> 1208.8967 | Q119: =IF(M118>0,M118+P119,"") -> 27456.867 | R119: =IF(M119>0,M119-Q119,"") -> -247.20667 | S119: =IF(M119>=Q119,"SIM","Não") -> Não
A120: 45361 | C120: 17563.79 | F120: 10589.06 | M120: =SUM(C120:L120) -> 28152.85 | N120: =IF(M120<>0,M120-M119,"") -> 943.19 | O120: =IF(N120<>"",(N120/M120),"") -> 0.03350247 | P120: =IF(N119<>"",AVERAGE(N117:N119),"") -> 1220.22 | Q120: =IF(M119>0,M119+P120,"") -> 28429.88 | R120: =IF(M120>0,M120-Q120,"") -> -277.03 | S120: =IF(M120>=Q120,"SIM","Não") -> Não
A121: 45404 | C121: 18504.9 | F121: 10629.55 | M121: =SUM(C121:L121) -> 29134.45 | N121: =IF(M121<>0,M121-M120,"") -> 981.6 | O121: =IF(N121<>"",(N121/M121),"") -> 0.033692072 | P121: =IF(N120<>"",AVERAGE(N118:N120),"") -> 1085.16 | Q121: =IF(M120>0,M120+P121,"") -> 29238.01 | R121: =IF(M121>0,M121-Q121,"") -> -103.56 | S121: =IF(M121>=Q121,"SIM","Não") -> Não
A122: 45434 | C122: 19443.44 | F122: 10666.65 | M122: =SUM(C122:L122) -> 30110.09 | N122: =IF(M122<>0,M122-M121,"") -> 975.64 | O122: =IF(N122<>"",(N122/M122),"") -> 0.032402427 | P122: =IF(N121<>"",AVERAGE(N119:N121),"") -> 962.16 | Q122: =IF(M121>0,M121+P122,"") -> 30096.61 | R122: =IF(M122>0,M122-Q122,"") -> 13.48 | S122: =IF(M122>=Q122,"SIM","Não") -> SIM
A123: 45465 | C123: 20382.28 | F123: 10702.25 | M123: =SUM(C123:L123) -> 31084.53 | N123: =IF(M123<>0,M123-M122,"") -> 974.44 | O123: =IF(N123<>"",(N123/M123),"") -> 0.031348069 | P123: =IF(N122<>"",AVERAGE(N120:N122),"") -> 966.81 | Q123: =IF(M122>0,M122+P123,"") -> 31076.9 | R123: =IF(M123>0,M123-Q123,"") -> 7.63 | S123: =IF(M123>=Q123,"SIM","Não") -> SIM
A124: 45495 | C124: 21313.94 | F124: 10732.55 | M124: =SUM(C124:L124) -> 32046.49 | N124: =IF(M124<>0,M124-M123,"") -> 961.96 | O124: =IF(N124<>"",(N124/M124),"") -> 0.03001764 | P124: =IF(N123<>"",AVERAGE(N121:N123),"") -> 977.22667 | Q124: =IF(M123>0,M123+P124,"") -> 32061.757 | R124: =IF(M124>0,M124-Q124,"") -> -15.266667 | S124: =IF(M124>=Q124,"SIM","Não") -> Não
A125: 45526 | C125: 22907.58 | F125: 11050.49 | M125: =SUM(C125:L125) -> 33958.07 | N125: =IF(M125<>0,M125-M124,"") -> 1911.58 | O125: =IF(N125<>"",(N125/M125),"") -> 0.056292363 | P125: =IF(N124<>"",AVERAGE(N122:N124),"") -> 970.68 | Q125: =IF(M124>0,M124+P125,"") -> 33017.17 | R125: =IF(M125>0,M125-Q125,"") -> 940.9 | S125: =IF(M125>=Q125,"SIM","Não") -> SIM
A126: 45557 | B126: 0 | C126: 23883.39 | F126: 11085.57 | M126: =SUM(B126:L126) -> 34968.96 | N126: =IF(M126<>0,M126-M125,"") -> 1010.89 | O126: =IF(N126<>"",(N126/M126),"") -> 0.028908209 | P126: =IF(N125<>"",AVERAGE(N123:N125),"") -> 1282.66 | Q126: =IF(M125>0,M125+P126,"") -> 35240.73 | R126: =IF(M126>0,M126-Q126,"") -> -271.77 | S126: =IF(M126>=Q126,"SIM","Não") -> Não
A127: 45587 | B127: 520 | C127: 24978.03 | F127: 11120.4 | M127: =SUM(B127:L127) -> 36618.43 | N127: =IF(M127<>0,M127-M126,"") -> 1649.47 | O127: =IF(N127<>"",(N127/M127),"") -> 0.045044804 | P127: =IF(N126<>"",AVERAGE(N124:N126),"") -> 1294.81 | Q127: =IF(M126>0,M126+P127,"") -> 36263.77 | R127: =IF(M127>0,M127-Q127,"") -> 354.66 | S127: =IF(M127>=Q127,"SIM","Não") -> SIM
A128: 45618 | B128: 1561.79 | C128: 25064.07 | F128: 11158.7 | M128: =SUM(B128:L128) -> 37784.56 | N128: =IF(M128<>0,M128-M127,"") -> 1166.13 | O128: =IF(N128<>"",(N128/M128),"") -> 0.030862606 | P128: =IF(N127<>"",AVERAGE(N125:N127),"") -> 1523.98 | Q128: =IF(M127>0,M127+P128,"") -> 38142.41 | R128: =IF(M128>0,M128-Q128,"") -> -357.85 | S128: =IF(M128>=Q128,"SIM","Não") -> Não
A129: 45648 | B129: 693.33 | C129: 25142.16 | F129: 11193.47 | M129: =SUM(B129:L129) -> 37028.96 | N129: =IF(M129<>0,M129-M128,"") -> -755.6 | O129: =IF(N129<>"",(N129/M129),"") -> -0.02040565 | P129: =IF(N128<>"",AVERAGE(N126:N128),"") -> 1275.4967 | Q129: =IF(M128>0,M128+P129,"") -> 39060.057 | R129: =IF(M129>0,M129-Q129,"") -> -2031.0967 | S129: =IF(M129>=Q129,"SIM","Não") -> Não
A130: 45679 | B130: 0 | C130: 25224.87 | F130: 11230.29 | M130: =SUM(B130:L130) -> 36455.16 | N130: =IF(M130<>0,M130-M129,"") -> -573.8 | O130: =IF(N130<>"",(N130/M130),"") -> -0.015739884 | P130: =IF(N129<>"",AVERAGE(N127:N129),"") -> 686.66667 | Q130: =IF(M129>0,M129+P130,"") -> 37715.627 | R130: =IF(M130>0,M130-Q130,"") -> -1260.4667 | S130: =IF(M130>=Q130,"SIM","Não") -> Não
A131: 45710 | C131: 25329.8 | F131: 11277 | M131: =SUM(B131:L131) -> 36606.8 | N131: =IF(M131<>0,M131-M130,"") -> 151.64 | O131: =IF(N131<>"",(N131/M131),"") -> 0.0041423998 | P131: =IF(N130<>"",AVERAGE(N128:N130),"") -> -54.423333 | Q131: =IF(M130>0,M130+P131,"") -> 36400.737 | R131: =IF(M131>0,M131-Q131,"") -> 206.06333 | S131: =IF(M131>=Q131,"SIM","Não") -> SIM
A132: 45738 | C132: 283.71 | F132: 89.48 | M132: =SUM(B132:L132) -> 373.19 | N132: =IF(M132<>0,M132-M131,"") -> -36233.61 | O132: =IF(N132<>"",(N132/M132),"") -> -97.091589 | P132: =IF(N131<>"",AVERAGE(N129:N131),"") -> -392.58667 | Q132: =IF(M131>0,M131+P132,"") -> 36214.213 | R132: =IF(M132>0,M132-Q132,"") -> -35841.023 | S132: =IF(M132>=Q132,"SIM","Não") -> Não
A133: 45769 | C133: 284.72 | F133: 89.79 | M133: =SUM(B133:L133) -> 374.51 | N133: =IF(M133<>0,M133-M132,"") -> 1.32 | O133: =IF(N133<>"",(N133/M133),"") -> 0.0035246055 | P133: =IF(N132<>"",AVERAGE(N130:N132),"") -> -12218.59 | Q133: =IF(M132>0,M132+P133,"") -> -11845.4 | R133: =IF(M133>0,M133-Q133,"") -> 12219.91 | S133: =IF(M133>=Q133,"SIM","Não") -> SIM
A134: 45799 | C134: 285.9 | F134: 90.16 | M134: =SUM(B134:L134) -> 376.06 | N134: =IF(M134<>0,M134-M133,"") -> 1.55 | O134: =IF(N134<>"",(N134/M134),"") -> 0.0041216827 | P134: =IF(N133<>"",AVERAGE(N131:N133),"") -> -12026.883 | Q134: =IF(M133>0,M133+P134,"") -> -11652.373 | R134: =IF(M134>0,M134-Q134,"") -> 12028.433 | S134: =IF(M134>=Q134,"SIM","Não") -> SIM
A135: 45830 | C135: 287.09 | F135: 90.53 | M135: =SUM(B135:L135) -> 377.62 | N135: =IF(M135<>0,M135-M134,"") -> 1.56 | O135: =IF(N135<>"",(N135/M135),"") -> 0.0041311371 | P135: =IF(N134<>"",AVERAGE(N132:N134),"") -> -12076.913 | Q135: =IF(M134>0,M134+P135,"") -> -11700.853 | R135: =IF(M135>0,M135-Q135,"") -> 12078.473 | S135: =IF(M135>=Q135,"SIM","Não") -> SIM
A136: 45860 | C136: 288.28 | F136: 90.9 | M136: =SUM(B136:L136) -> 379.18 | N136: =IF(M136<>0,M136-M135,"") -> 1.56 | O136: =IF(N136<>"",(N136/M136),"") -> 0.004114141 | P136: =IF(N135<>"",AVERAGE(N133:N135),"") -> 1.4766667 | Q136: =IF(M135>0,M135+P136,"") -> 379.09667 | R136: =IF(M136>0,M136-Q136,"") -> 0.083333333 | S136: =IF(M136>=Q136,"SIM","Não") -> SIM
A137: 45891 | C137: 805.3 | F137: 320.92 | M137: =SUM(B137:L137) -> 1126.22 | N137: =IF(M137<>0,M137-M136,"") -> 747.04 | O137: =IF(N137<>"",(N137/M137),"") -> 0.66331623 | P137: =IF(N136<>"",AVERAGE(N134:N136),"") -> 1.5566667 | Q137: =IF(M136>0,M136+P137,"") -> 380.73667 | R137: =IF(M137>0,M137-Q137,"") -> 745.48333 | S137: =IF(M137>=Q137,"SIM","Não") -> SIM
A138: 45922 | C138: 808.67 | F138: 322.26 | M138: =SUM(B138:L138) -> 1130.93 | N138: =IF(M138<>0,M138-M137,"") -> 4.71 | O138: =IF(N138<>"",(N138/M138),"") -> 0.004164714 | P138: =IF(N137<>"",AVERAGE(N135:N137),"") -> 250.05333 | Q138: =IF(M137>0,M137+P138,"") -> 1376.2733 | R138: =IF(M138>0,M138-Q138,"") -> -245.34333 | S138: =IF(M138>=Q138,"SIM","Não") -> Não
A139: 45952 | C139: 812.07 | F139: 323.61 | M139: =SUM(B139:L139) -> 1135.68 | N139: =IF(M139<>0,M139-M138,"") -> 4.75 | O139: =IF(N139<>"",(N139/M139),"") -> 0.0041825162 | P139: =IF(N138<>"",AVERAGE(N136:N138),"") -> 251.10333 | Q139: =IF(M138>0,M138+P139,"") -> 1382.0333 | R139: =IF(M139>0,M139-Q139,"") -> -246.35333 | S139: =IF(M139>=Q139,"SIM","Não") -> Não
A140: 45983 | C140: 815.5 | F140: 324.97 | M140: =SUM(B140:L140) -> 1140.47 | N140: =IF(M140<>0,M140-M139,"") -> 4.79 | O140: =IF(N140<>"",(N140/M140),"") -> 0.0042000228 | P140: =IF(N139<>"",AVERAGE(N137:N139),"") -> 252.16667 | Q140: =IF(M139>0,M139+P140,"") -> 1387.8467 | R140: =IF(M140>0,M140-Q140,"") -> -247.37667 | S140: =IF(M140>=Q140,"SIM","Não") -> Não
A141: 46013 | C141: 818.84 | F141: 326.3 | M141: =SUM(B141:L141) -> 1145.14 | N141: =IF(M141<>0,M141-M140,"") -> 4.67 | O141: =IF(N141<>"",(N141/M141),"") -> 0.004078104 | P141: =IF(N140<>"",AVERAGE(N138:N140),"") -> 4.75 | Q141: =IF(M140>0,M140+P141,"") -> 1145.22 | R141: =IF(M141>0,M141-Q141,"") -> -0.08 | S141: =IF(M141>=Q141,"SIM","Não") -> Não
A142: 46044 | C142: 654.97 | F142: 0 | M142: =SUM(B142:L142) -> 654.97 | N142: =IF(M142<>0,M142-M141,"") -> -490.17 | O142: =IF(N142<>"",(N142/M142),"") -> -0.74838542 | P142: =IF(N141<>"",AVERAGE(N139:N141),"") -> 4.7366667 | Q142: =IF(M141>0,M141+P142,"") -> 1149.8767 | R142: =IF(M142>0,M142-Q142,"") -> -494.90667 | S142: =IF(M142>=Q142,"SIM","Não") -> Não
... A145: 46134 | C145: 662.89 | F145: 0 | M145: =SUM(B145:L145) -> 662.89 | N145: =IF(M145<>0,M145-M144,"") -> 2.77 | O145: =IF(N145<>"",(N145/M145),"") -> 0.0041786722 | P145: =IF(N144<>"",AVERAGE(N142:N144),"") -> -161.67333 | Q145: =IF(M144>0,M144+P145,"") -> 498.44667 | R145: =IF(M145>0,M145-Q145,"") -> 164.44333 | S145: =IF(M145>=Q145,"SIM","Não") -> SIM
A146: 46164 | N146: =IF(M146<>0,M146-M145,"") | O146: =IF(N146<>"",(N146/M146),"") | P146: =IF(N145<>"",AVERAGE(N143:N145),"") -> 2.64 | Q146: =IF(M145>0,M145+P146,"") -> 665.53 | R146: =IF(M146>0,M146-Q146,"")
A147: 46195 | N147: =IF(M147<>0,M147-M146,"") | O147: =IF(N147<>"",(N147/M147),"") | P147: =IF(N146<>"",AVERAGE(N144:N146),"") | Q147: =IF(M146>0,M146+P147,"") | R147: =IF(M147>0,M147-Q147,"")
A148: 46225 | N148: =IF(M148<>0,M148-M147,"") | O148: =IF(N148<>"",(N148/M148),"") | P148: =IF(N147<>"",AVERAGE(N145:N147),"") | Q148: =IF(M147>0,M147+P148,"") | R148: =IF(M148>0,M148-Q148,"")
A149: 46256 | N149: =IF(M149<>0,M149-M148,"") | O149: =IF(N149<>"",(N149/M149),"") | P149: =IF(N148<>"",AVERAGE(N146:N148),"") | Q149: =IF(M148>0,M148+P149,"") | R149: =IF(M149>0,M149-Q149,"")
A150: 46287 | N150: =IF(M150<>0,M150-M149,"") | O150: =IF(N150<>"",(N150/M150),"") | P150: =IF(N149<>"",AVERAGE(N147:N149),"") | Q150: =IF(M149>0,M149+P150,"") | R150: =IF(M150>0,M150-Q150,"")
A151: 46317 | N151: =IF(M151<>0,M151-M150,"") | O151: =IF(N151<>"",(N151/M151),"") | P151: =IF(N150<>"",AVERAGE(N148:N150),"") | Q151: =IF(M150>0,M150+P151,"") | R151: =IF(M151>0,M151-Q151,"")
A152: 46348 | N152: =IF(M152<>0,M152-M151,"") | O152: =IF(N152<>"",(N152/M152),"") | P152: =IF(N151<>"",AVERAGE(N149:N151),"") | Q152: =IF(M151>0,M151+P152,"") | R152: =IF(M152>0,M152-Q152,"")
A153: 46378 | N153: =IF(M153<>0,M153-M152,"") | O153: =IF(N153<>"",(N153/M153),"") | P153: =IF(N152<>"",AVERAGE(N150:N152),"") | Q153: =IF(M152>0,M152+P153,"") | R153: =IF(M153>0,M153-Q153,"")
...

Sheet Movimentações
B1: Credito | C1: Debito | D1: Saldo
A2: Real | B2: =Real!D580 -> 10158.79 | C2: =Real!E580 -> 10158.79 | D2: =B2-C2 -> 0
A3: Real Visa | B3: =RealVisa!D275 -> 4514.32 | C3: =RealVisa!E275 -> 4514.32 | D3: =B3-C3 -> 0
A4: HSBC | B4: =HSBC!D942 -> 38891.33 | C4: =HSBC!E942 -> 38891.33 | D4: =B4-C4 -> 0
A5: HSBC Visa | B5: =HSBCVisa!D91 -> 1845.94 | C5: =HSBCVisa!E91 -> 1845.94 | D5: =B5-C5 -> 0
A6: Carrefour | B6: =Carefour!D69 -> 2257.37 | C6: =Carefour!E69 -> 2257.37 | D6: =B6-C6 -> 0
A7: Banco1 | B7: =Banco1!D795 -> 44247.27 | C7: =Banco1!E795 -> 44247.27 | D7: =B7-C7 -> 0
A8: Banco1.Master | B8: =Banco1MasterCard!D158 -> 2829.59 | C8: =Banco1MasterCard!E158 -> 2829.59 | D8: =B8-C8 -> 0
A9: Banco1.Visa | B9: =UnibancoVisa!D63 -> 1905.75 | C9: =UnibancoVisa!E63 -> 1905.75 | D9: =B9-C9 -> 0
A10: citibank | B10: =CitiBank!D474 -> 28945.21 | C10: =CitiBank!E474 -> 28945.21 | D10: =B10-C10 -> 0
A11: citibank Visa | B11: =CitibankVisa!D207 -> 7455.72 | C11: =CitibankVisa!E207 -> 7455.72 | D11: =B11-C11 -> 0
A12: Citibank Master | B12: =CitiBankMastercard!D178 -> 5310.18 | C12: =CitiBankMastercard!E178 -> 5310.18 | D12: =B12-C12 -> 0
A13: Amex | B13: =Amex!D32 -> 442.7 | C13: =Amex!E32 -> 442.7 | D13: =B13-C13 -> 0
A14: ItaU MasteCard | B14: =ItauMasterCard!D470 -> 24384.9 | C14: =ItauMasterCard!E470 -> 24384.9 | D14: =B14-C14 -> 0
A15: ItaU | B15: =ItaU!D9367 -> 1872691 | C15: =ItaU!E9367 -> 1892501.9 | D15: =B15-C15 -> -19810.951
A16: Poupança ItaU | B16: =PoupanCaItau!D196 -> 139745.41 | C16: =PoupanCaItau!E196 -> 139745.41 | D16: =B16-C16 -> 0
A17: Real - 2007 | B17: =Real_2007!D4605 -> 673087.74 | C17: =Real_2007!E4605 -> 673087.74 | D17: =B17-C17 -> -1.1641532e-09
A18: Real Visa - 2007 | B18: =RealVisa_2007!D2255 -> 190723.43 | C18: =RealVisa_2007!E2255 -> 190729.14 | D18: =B18-C18 -> -5.7098157
A19: PortoSeguro VISA | B19: =PortoSeguroVisa!D643 -> 49038.59 | C19: =PortoSeguroVisa!E643 -> 49038.587 | D19: =B19-C19 -> 0.0033333333
A20: CEF | B20: =CEF!D285 -> 424467.48 | C20: =CEF!E285 -> 424467.48 | D20: =B20-C20 -> 0
A21: NuBank Master | B21: =NUBank_Master!D1702 -> 134463.31 | C21: =NUBank_Master!E1702 -> 139626.74 | D21: =B21-C21 -> -5163.431
A22: Santander Master | B22: =Santander_Master!D2431 -> 238340.2 | C22: =Santander_Master!E2431 -> 238340.2 | D22: =B22-C22 -> 0.0048020004
A23: Santander | B23: =Santander!D2191 -> 746283.04 | C23: =Santander!E2191 -> 746283.04 | D23: =B23-C23 -> 0.0039999995
A24: ItaU Visa | B24: =ItauVisa!D1422 -> 109180.68 | C24: =ItauVisa!E1422 -> 109180.68 | D24: =B24-C24 -> -0.0013333332
A25: Despesas | B25: =Despesas!D4129 -> 77078.54 | C25: =Despesas!E4129 -> 77078.54 | D25: =B25-C25 -> 0
B28: =SUM(B2:B27) -> 4828288.5 | C28: =SUM(C2:C27) -> 4853268.5 | D28: =B28-C28 -> -24980.081

Sheet ATIVAS
B2: Amazon_Master!A1

Sheet DadosBancarios
A1: BANCO | B1: Código Banco | C1: AGENCIA | D1: CONTA | E1: USUARIO | F1: SENHA Saque | G1: SENHA ELETRONICA | H1: OBS | I1: Chave PX
A2: Poupança caixa | B2: 104 | C2: 0333 | D2: 013.2073-0 | E2: CARLINLUIZ02 | F2: 2802 | G2: Sucker09 | H2: 513736 | I2: luiz_carlin@yahoo.com.br
B3: 104 | C3: 0333 | D3: 1288.000766611949 - 7 | E3: CARLINLUIZ02 | F3: 2802 | G3: Sucker09 | H3: 513736 | I3: luiz_carlin@yahoo.com.br
A4: XP Invest | B4: 102 | C4: 0001 | D4: 260167-6 | E4: 2601676 | F4: 143702 | G4: 14370231 | I4: luiz.carlin@icloud.com
A5: Itau Cristiane | B5: 341 | C5: 3094 | D5: 26295-7 | F5: 061405 | G5: 112805 | I5: 11982027012
A6: Itau - Global HITSS | B6: 341 | C6: 3094 | D6: 26917-6 | F6: 090506 | G6: 287931 | I6: luiz.carlin@outlook.com
A7: NuConta- NuBank | B7: 260 | C7: 0001 | D7: 8710072-4 | I7: luiz.carlin@gmail.com
A8: MercadoPago | B8: 323 | C8: 0001 | D8: 7389697285-9 | I8: luiz.carlin@proton.me
A9: Itau ITI | B9: 341 | C9: 0500 | D9: 00078708-5 | E9: CPF | F9: 287931 | I9: luiz.carlin@me.com
A10: Itau ITI | B10: 341 | C10: 7139 | D10: 0022923-6 | G10: 250879
A11: Santander | B11: 033 | C11: 4354 | D11: 02010899-5 | F11: 1930 | G11: 287931 / JFH | I11: luiz.carlin@protonmail.com
A12: BTG PACTUAL | B12: 208 | C12: 0020 | D12: 008026425 | G12: 287931 | I12: luiz.carlin@aol.com
A17: Caixa Economica | B17: 104 | C17: 4058 | D17: 001.22967-4 | E17: CARLINLUIZ02 | F17: 9230 | G17: Sucker09 | H17: 521862
A18: PP Santander | B18: 033 | C18: 0642 | D18: 60.011323.6
A19: Santander | B19: 033 | C19: 3294 | D19: 02.000297.2 | F19: 1793 | G19: 287931 / JFH
A20: Neon Conta | B20: 655 | C20: 0655 | D20: 2741278-4
A21: Itau Personnalité | B21: 341 | C21: 9688 | D21: 15563-0 | F21: 206210 | G21: 616274
A22: Santander | B22: 033 | C22: 3294 | D22: 01.000969.1 | E22: lcarlin | F22: 9230 | G22: Roubo!01 | H22: 0767
A23: Santander | B23: 033 | C23: 0642 | D23: 01.040528.2 | F23: 8770 | G23: 287931 / JFH
A24: Itau | B24: 341 | C24: 3094 | D24: 15563-1 | F24: 161230 | G24: 287931
A25: Real - 2007 | C25: 0294 | D25: 6029069-7 | E25: LCARLIN | F25: 0614 | G25: sync750v | H25: 0767
A26: Banco1.Net | C26: '0110 | D26: 100893-4
A27: Banco1.Net | C27: 7007 | D27: 105877-3 | F27: 6478 | G27: sync750v
A28: Citibank | C28: 008 | D28: 96923156 | F28: 2645 | G28: jaspion3
A29: HSBC | C29: 0364 | D29: 09004-34
A30: iTAU | C30: 2628 | D30: 04045-9
A31: Real
A32: Banespa
A33: Banco do brasil | C33: 3279-4 | D33: 22684-0 | I33: e3fcb9a8-8710-4e36-ae4c-cfb568e24216
A34: EasyInvest | B34: 140 | C34: 0001 | D34: 7843113-0 | E34: Email/CPF | F34: P!r0c4#93 | G34: 463b6b

Sheet Financ_AP_01
A1: # | B1: Data | C1: Lançamento | D1: Valor | E1: Diif Mes Ant | F1: Dt Pagamento | G1: Valor Pago | H1: % Paga | I1: Desconto | J1: Pago
A2: 1 | B2: 45775 | C2: ="Parcela (" &TEXT(A2,"000") & "/" & $D$30 &")" -> Parcela (001/385) | D2: 3808.76 | F2: 45775 | G2: 3808.76 | H2: =IF(G2<>"",G2/D2,"") -> 1 | I2: =IF(G2<>"",D2-G2,"") -> 0 | J2: =IF(G2>0,"X","") -> X | K2: =IF(J2="X",0,D2) -> 0
A3: 2 | B3: 45805 | C3: ="Parcela (" &TEXT(A3,"000") & "/" & $D$30 &")" -> Parcela (002/385) | D3: 3626.77 | E3: =IF(D3<>"",D2-D3,"") -> 181.99 | F3: 45805 | G3: 3626.77 | H3: =IF(G3<>"",G3/D3,"") -> 1 | I3: =IF(G3<>"",D3-G3,"") -> 0 | J3: =IF(G3>0,"X","") -> X | K3: =IF(J3="X",0,D3) -> 0
A4: 3 | B4: 45836 | C4: ="Parcela (" &TEXT(A4,"000") & "/" & $D$30 &")" -> Parcela (003/385) | D4: 3625.6 | E4: =IF(D4<>"",D3-D4,"") -> 1.17 | F4: 45838 | G4: 3625.6 | H4: =IF(G4<>"",G4/D4,"") -> 1 | I4: =IF(G4<>"",D4-G4,"") -> 0 | J4: =IF(G4>0,"X","") -> X | K4: =IF(J4="X",0,D4) -> 0
A5: 4 | B5: 45866 | C5: ="Parcela (" &TEXT(A5,"000") & "/" & $D$30 &")" -> Parcela (004/385) | D5: 3618.12 | E5: =IF(D5<>"",D4-D5,"") -> 7.48 | F5: 45866 | G5: 3624.26 | H5: =IF(G5<>"",G5/D5,"") -> 1.001697 | I5: =IF(G5<>"",D5-G5,"") -> -6.14 | J5: =IF(G5>0,"X","") -> X | K5: =IF(J5="X",0,D5) -> 0
A6: 5 | B6: 45897 | C6: ="Parcela (" &TEXT(A6,"000") & "/" & $D$30 &")" -> Parcela (005/385) | D6: 3615.59 | E6: =IF(D6<>"",D5-D6,"") -> 2.53 | F6: 45897 | G6: 3628.1 | H6: =IF(G6<>"",G6/D6,"") -> 1.00346 | I6: =IF(G6<>"",D6-G6,"") -> -12.51 | J6: =IF(G6>0,"X","") -> X | K6: =IF(J6="X",0,D6) -> 0
A7: 6 | B7: 45928 | C7: ="Parcela (" &TEXT(A7,"000") & "/" & $D$30 &")" -> Parcela (006/385) | D7: 3608.1 | E7: =IF(D7<>"",D6-D7,"") -> 7.49 | F7: 45929 | G7: 3626.89 | H7: =IF(G7<>"",G7/D7,"") -> 1.0052077 | I7: =IF(G7<>"",D7-G7,"") -> -18.79 | J7: =IF(G7>0,"X","") -> X | K7: =IF(J7="X",0,D7) -> 0
A8: 7 | B8: 45958 | C8: ="Parcela (" &TEXT(A8,"000") & "/" & $D$30 &")" -> Parcela (007/385) | D8: 3600.6 | E8: =IF(D8<>"",D7-D8,"") -> 7.5 | F8: 45958 | G8: 3625.58 | H8: =IF(G8<>"",G8/D8,"") -> 1.0069377 | I8: =IF(G8<>"",D8-G8,"") -> -24.98 | J8: =IF(G8>0,"X","") -> X | K8: =IF(J8="X",0,D8) -> 0
A9: 8 | B9: 45989 | C9: ="Parcela (" &TEXT(A9,"000") & "/" & $D$30 &")" -> Parcela (008/385) | D9: 3593.11 | E9: =IF(D9<>"",D8-D9,"") -> 7.49 | F9: 46019 | G9: 3624.33 | H9: =IF(G9<>"",G9/D9,"") -> 1.0086889 | I9: =IF(G9<>"",D9-G9,"") -> -31.22 | J9: =IF(G9>0,"X","") -> X | K9: =IF(J9="X",0,D9) -> 0
A10: 9 | B10: 46019 | C10: ="Parcela (" &TEXT(A10,"000") & "/" & $D$30 &")" -> Parcela (009/385) | D10: 3585.62 | E10: =IF(D10<>"",D9-D10,"") -> 7.49 | F10: 46020 | G10: 3622.93 | H10: =IF(G10<>"",G10/D10,"") -> 1.0104055 | I10: =IF(G10<>"",D10-G10,"") -> -37.31 | J10: =IF(G10>0,"X","") -> X | K10: =IF(J10="X",0,D10) -> 0
A11: 10 | B11: 46050 | C11: ="Parcela (" &TEXT(A11,"000") & "/" & $D$30 &")" -> Parcela (010/385) | D11: 3578.12 | E11: =IF(D11<>"",D10-D11,"") -> 7.5 | F11: 46050 | G11: 3621.58 | H11: =IF(G11<>"",G11/D11,"") -> 1.012146 | I11: =IF(G11<>"",D11-G11,"") -> -43.46 | J11: =IF(G11>0,"X","") -> X | K11: =IF(J11="X",0,D11) -> 0
A12: 11 | B12: 46081 | C12: ="Parcela (" &TEXT(A12,"000") & "/" & $D$30 &")" -> Parcela (011/385) | D12: 3582.06 | E12: =IF(D12<>"",D11-D12,"") -> -3.94 | F12: 46083 | G12: 3631.8 | H12: =IF(G12<>"",G12/D12,"") -> 1.0138859 | I12: =IF(G12<>"",D12-G12,"") -> -49.74 | J12: =IF(G12>0,"X","") -> X | K12: =IF(J12="X",0,D12) -> 0
A13: 12 | B13: 46109 | C13: ="Parcela (" &TEXT(A13,"000") & "/" & $D$30 &")" -> Parcela (012/385) | D13: 3574.53 | E13: =IF(D13<>"",D12-D13,"") -> 7.53 | F13: 46111 | G13: 3630.3 | H13: =IF(G13<>"",G13/D13,"") -> 1.0156021 | I13: =IF(G13<>"",D13-G13,"") -> -55.77 | J13: =IF(G13>0,"X","") -> X | K13: =IF(J13="X",0,D13) -> 0
A14: 13 | B14: 46140 | C14: ="Parcela (" &TEXT(A14,"000") & "/" & $D$30 &")" -> Parcela (013/385) | D14: 3567.01 | E14: =IF(D14<>"",D13-D14,"") -> 7.52 | F14: 46140 | G14: 3627.66 | H14: =IF(G14<>"",G14/D14,"") -> 1.017003 | I14: =IF(G14<>"",D14-G14,"") -> -60.65 | J14: =IF(G14>0,"X","") -> X | K14: =IF(J14="X",0,D14) -> 0
A15: 14 | B15: 46170 | C15: ="Parcela (" &TEXT(A15,"000") & "/" & $D$30 &")" -> Parcela (014/385) | D15: 3559.49 | E15: =IF(D15<>"",D14-D15,"") -> 7.52 | H15: =IF(G15<>"",G15/D15,"") | I15: =IF(G15<>"",D15-G15,"") | J15: =IF(G15>0,"X","") | K15: =IF(J15="X",0,D15) -> 3559.49
A16: 15 | B16: 46201 | C16: ="Parcela (" &TEXT(A16,"000") & "/" & $D$30 &")" -> Parcela (015/385) | D16: 3551.96 | E16: =IF(D16<>"",D15-D16,"") -> 7.53 | H16: =IF(G16<>"",G16/D16,"") | I16: =IF(G16<>"",D16-G16,"") | J16: =IF(G16>0,"X","") | K16: =IF(J16="X",0,D16) -> 3551.96
A17: 16 | B17: 46231 | C17: ="Parcela (" &TEXT(A17,"000") & "/" & $D$30 &")" -> Parcela (016/385) | D17: 3544.44 | E17: =IF(D17<>"",D16-D17,"") -> 7.52 | H17: =IF(G17<>"",G17/D17,"") | I17: =IF(G17<>"",D17-G17,"") | J17: =IF(G17>0,"X","") | K17: =IF(J17="X",0,D17) -> 3544.44
A18: 17 | B18: 46262 | C18: ="Parcela (" &TEXT(A18,"000") & "/" & $D$30 &")" -> Parcela (017/385) | D18: 3540.25 | E18: =IF(D18<>"",D17-D18,"") -> 4.19 | H18: =IF(G18<>"",G18/D18,"") | I18: =IF(G18<>"",D18-G18,"") | J18: =IF(G18>0,"X","") | K18: =IF(J18="X",0,D18) -> 3540.25
A19: 18 | B19: 46293 | C19: ="Parcela (" &TEXT(A19,"000") & "/" & $D$30 &")" -> Parcela (018/385) | D19: 3532.72 | E19: =IF(D19<>"",D18-D19,"") -> 7.53 | H19: =IF(G19<>"",G19/D19,"") | I19: =IF(G19<>"",D19-G19,"") | J19: =IF(G19>0,"X","") | K19: =IF(J19="X",0,D19) -> 3532.72
A20: 19 | B20: 46323 | C20: ="Parcela (" &TEXT(A20,"000") & "/" & $D$30 &")" -> Parcela (019/385) | D20: 3525.18 | E20: =IF(D20<>"",D19-D20,"") -> 7.54 | H20: =IF(G20<>"",G20/D20,"") | I20: =IF(G20<>"",D20-G20,"") | J20: =IF(G20>0,"X","") | K20: =IF(J20="X",0,D20) -> 3525.18
A21: 20 | B21: 46354 | C21: ="Parcela (" &TEXT(A21,"000") & "/" & $D$30 &")" -> Parcela (020/385) | D21: 3517.66 | E21: =IF(D21<>"",D20-D21,"") -> 7.52 | H21: =IF(G21<>"",G21/D21,"") | I21: =IF(G21<>"",D21-G21,"") | J21: =IF(G21>0,"X","") | K21: =IF(J21="X",0,D21) -> 3517.66
A22: 21 | B22: 46384 | C22: ="Parcela (" &TEXT(A22,"000") & "/" & $D$30 &")" -> Parcela (021/385) | D22: 3510.12 | E22: =IF(D22<>"",D21-D22,"") -> 7.54 | H22: =IF(G22<>"",G22/D22,"") | I22: =IF(G22<>"",D22-G22,"") | J22: =IF(G22>0,"X","") | K22: =IF(J22="X",0,D22) -> 3510.12
A23: 22 | B23: 46415 | C23: ="Parcela (" &TEXT(A23,"000") & "/" & $D$30 &")" -> Parcela (022/385) | D23: 3502.59 | E23: =IF(D23<>"",D22-D23,"") -> 7.53 | H23: =IF(G23<>"",G23/D23,"") | I23: =IF(G23<>"",D23-G23,"") | J23: =IF(G23>0,"X","") | K23: =IF(J23="X",0,D23) -> 3502.59
A24: 23 | B24: 46446 | C24: ="Parcela (" &TEXT(A24,"000") & "/" & $D$30 &")" -> Parcela (023/385) | D24: 3506.74 | E24: =IF(D24<>"",D23-D24,"") -> -4.15 | H24: =IF(G24<>"",G24/D24,"") | I24: =IF(G24<>"",D24-G24,"") | J24: =IF(G24>0,"X","") | K24: =IF(J24="X",0,D24) -> 3506.74
A25: 24 | B25: 46474 | C25: ="Parcela (" &TEXT(A25,"000") & "/" & $D$30 &")" -> Parcela (024/385) | D25: 3499.17 | E25: =IF(D25<>"",D24-D25,"") -> 7.57 | H25: =IF(G25<>"",G25/D25,"") | I25: =IF(G25<>"",D25-G25,"") | J25: =IF(G25>0,"X","") | K25: =IF(J25="X",0,D25) -> 3499.17
J26: =IF(G26>0,"X","")
J27: =IF(G27>0,"X","")
C29: Totais: | D29: =SUM(D2:D28) -> 85774.31 | E29: =SUM(E2:E28) -> 309.59 | G29: =SUM(G2:G28) -> 47324.56
C30: Total de Parcelas contratadas | D30: 385

Sheet CARTOES
A1: Tipo | B1: Numero | C1: D.V. | D1: Validade | E1: Senhas | F1: Vencimento | G1: Corte | H1: Limite | I1: Usado | J1: Disponivel | K1: Status
A2: Amazon Master | B2: 5373.6300.7124.3028 | C2: 796 | D2: 09/28 | E2: 2167 | F2: 01 | H2: 8800 | I2: =Amazon_Master!E1024 -> 56517.843 | J2: =H2+I2 -> 65317.843 | K2: Ativo
A3: Amazon Master | B3: 5373.6300.7124.3010 | C3: 187 | D3: 09/28 | E3: 2167 | F3: 01 | H3: 8800 | I3: =Amazon_Master!E1025 -> -5302.703 | J3: =H3+I3 -> 3497.297 | K3: Cancelado
A4: Amex | B4: 3764.727880.51008 | C4: 4899 | D4: 41548 | E4: 1612 | F4: 15 | H4: N/A | K4: Cancelado
A5: Banco1MasterCard | B5: 5547.7500.2325.9010 | D5: 38504 | H5: 1600 | K5: Cancelado
A6: CitiBankMastercard | B6: 5390.2856.1083.0048 | D6: 39356 | H6: 2600 | K6: Cancelado
A7: CitibankVisa | B7: 4002.2549.6566.8851 | D7: 39356 | H7: 3200 | K7: Cancelado
A8: CrediCard Visa Cristiane | B8: 4032.1760.0269.6526 | C8: 764 | D8: 43070 | E8: 3244 | K8: Cancelado
A9: CrediCard Visa Luiz | B9: 4032.1760.0272.2249 | C9: 598 | D9: 43070 | E9: 1486 | K9: Cancelado
A10: CrediCard Zero Master | B10: ​​5358.5002.2231.2080 | C10: 172 | D10: 01/26 | E10: 5302 | F10: 01 | G10: 24 / 25 | H10: 18800 | I10: =CrediCard_Master!E1010 -> 1829.4467 | J10: =H10+I10 -> 20629.447 | K10: Cancelado
A11: Credicard Zero Master - VIRTUAL | B11: 5358.5006.7213.9447 | C11: 276 | D11: 05/30 | G11: 24 / 25 | K11: Cancelado
A12: Digio Visa | B12: 4589.1974.8199.3231 | C12: 441 | D12: 11/21 | E12: 9238 | F12: 01 | G12: 25 | H12: 9100 | I12: =DigioVisa!E260 -> -0.0036666667 | J12: =H12+I12 -> 9099.9963 | K12: Cancelado
A13: HSBC VISA | B13: 4487.3309.1437.6129 | D13: 38292 | H13: 700 | K13: Cancelado
A14: Itau Master Cristiane | B14: 5448.5987.3959.3418 | C14: 334 | D14: 41852 | E14: 9230 | F14: 02 | G14: 22 / 23 | H14: 3400 | K14: Cancelado
A15: Itau Master Luiz | B15: 5448.5987.6327.6997 | C15: 371 | D15: 41852 | E15: 8013 | F15: 02 | G15: 22 / 23 | H15: 3400 | K15: Cancelado
A16: Itau Mastercard | B16: 5256.6318.0910.4435 | C16: 214 | D16: 11/27 | E16: 090506 | F16: 01 | G16: 21 / 22 | H16: 4000 | I16: =ItauMasterCard!E471 -> 0 | J16: =ItauMasterCard!F472 -> 4000 | K16: Cancelado
A17: Itau Personalitee Master Multiplo | B17: 5491.6702.9454.0674 | C17: 250 | D17: 43009 | E17: 206210 | F17: 01 | G17: 41599 | H17: 16500 | K17: Cancelado
A18: Itau Visa Cristiane | B18: 4032.4792.8392.2326 | C18: 666 | D18: 42339 | E18: 9230 | F18: 05 | G18: 25 / 26 | H18: 850 | K18: Cancelado
A19: Itau Visa Luiz | B19: 4032.4792.8689.5537 | C19: 821 | D19: 42339 | E19: 8013 | F19: 05 | G19: 25 / 26 | H19: 9500 | K19: Cancelado
A20: ItauCard 2.0 Cristiane | B20: 4593.1303.2233.6058 | C20: 845 | D20: 45047 | E20: 7233 | F20: 01 | G20: 21 / 22 | H20: 14800 | K20: Cancelado
A21: ItauCard 2.0 Cristiane | B21: 4593.1303.3758.6986 | C21: 692 | D21: 45047 | E21: 7233 | F21: 01 | G21: 21 / 22 | H21: 8500 | K21: Cancelado
A22: ItauCard 2.0 Luiz | B22: 4593.1303.3904.1717 | C22: 685 | D22: 45047 | E22: 8081 | F22: 01 | G22: 21 / 22 | H22: 14800 | I22: =ItauVisa!E1423 -> -0.0013333332 | J22: =H22+I22 -> 14799.999 | K22: Cancelado
A23: ItauUniClass Visa Fisico | B23: 4831.5004.3490.2033 | C23: 786 | D23: 02/30 | E23: 1605 | F23: 01 | G23: 25 / 26 | H23: 21400 | I23: =ItauUniclassVisa!E801 -> -2194.545 | J23: =H23+I23 -> 19205.455 | K23: Ativo
A24: ItauUniClass Visa Virtual | B24: 4831.5005.0882.2810 | C24: 044 | D24: 02/30 | F24: 01 | G24: 25 / 26 | K24: Ativo
A25: MagaLu Visa Platiniu | B25: 4985.5604.8873.1849 | C25: 351 | D25: 03/30 | E25: 7306 | F25: 01 | G25: 21 / 22 | H25: 0 | K25: Cancelado
A26: MercadoPago DEBITO | B26: 4174.0101.9005.0147 | C26: 168 | D26: 06/27 | K26: Ativo
A27: MercadoPago Visa | B27: 4078.4301.7048.9478 | C27: 131 | D27: 09/29 | F27: 04 | G27: 01 | H27: 25000 | I27: =MercadoPago_Visa!E184 -> 0 | J27: =H27+I27 -> 25000 | K27: Ativo
A28: Neon | B28: 4040.2500.5201.0258 | C28: 206 | D28: 09/24 | E28: 9230 | F28: 01 | G28: 25 | H28: 9300 | K28: Cancelado
A29: NU Bank - VIRTUAL | B29: 5162.9276.8422.4691 | C29: 640 | D29: 05/30 | G29: 25 | K29: Cancelado
A30: NU Bank Master | B30: 5162.2083.5489.3358 | C30: 419 | D30: 43525 | E30: 9230 | F30: 01 | G30: 25 | H30: 0 | I30: 0 | J30: =H30+I30 -> 0 | K30: Cancelado
A31: Nu Bank Master Patinum | B31: 5162.9256.3930.5284 | C31: 427 | D31: 01/28 | E31: 9230 | F31: 01 | G31: 25 | H31: 12900 | I31: =NUBank_Master!E1703 -> -5163.431 | J31: =H31+I31 -> 7736.569 | K31: Cancelado
A32: Nu Bank Master Patinum Fisico | B32: 5162.9230.0993.8032 | C32: 193 | D32: 04/29 | E32: 9230 | F32: 01 | G32: 25 | H32: 17900 | I32: =NUBank_Master!E1703 -> -5163.431 | J32: =H32+I32 -> 12736.569 | K32: Ativo
A33: Nu Bank Master Patinum Virtual | K33: Ativo
A34: Petrobras BB | B34: 4444.5650.8250.1360 | C34: 355 | D34: 44256 | E34: 801765 | F34: 01 | G34: 21 / 22 | H34: 1450 | K34: Cancelado
A35: Porto Seguro Masrer Luiz | B35: 5363.3701.0795.4211 | C35: 361 | D35: 44075 | E35: 3791 | F35: 03 | G35: 23 | H35: 6500 | K35: Cancelado
A36: Porto Seguro Master Cristiane | B36: 5365.3701.0795.4112 | C36: 988 | D36: 44075 | E36: 4620 | F36: 03 | G36: 23 | H36: 6500 | K36: Cancelado
A37: Porto Seguro Visa | B37: 4121.7701.4314.7118 | C37: 617 | D37: 40878 | E37: 3450 | F37: 03 | G37: 23 / 24 | H37: 2500 | K37: Cancelado
A38: Porto Seguro Visa Cristiane | B38: 4152.7405.1420.3115 | C38: 460 | D38: 42979 | E38: 1403 | F38: 03 | G38: 23 | H38: 11000 | K38: Cancelado
A39: Porto Seguro Visa Luiz | B39: 4152.7405.1420.3214 | C39: 070 | D39: 42979 | E39: 2012 | F39: 03 | G39: 23 | H39: 11000 | K39: Cancelado
A40: Real Mastercard Platinum | B40: 5316.5400.0216.2017 | C40: 351 | D40: 41944 | K40: Cancelado
A41: Real Mastercard Platinum Cris | B41: 5316.5400.0216.2025 | C41: 959 | D41: 41944 | K41: Cancelado
A42: Real Visa 2007 | B42: 4916.7466.7217.4045 | C42: 401 | D42: 40940 | E42: 0614 | F42: 01 | G42: 21 / 22 | H42: 17000 | K42: Cancelado
A43: Real Visa Cris | B43: 4916.7466.7217.4060 | C43: 805 | D43: 42248 | E43: 7233 | F43: 01 | G43: 21 / 22 | H43: 17000 | K43: Cancelado
A44: RealVisa | B44: 4916.7426.6613.0036 | D44: 37803 | H44: 375 | K44: Cancelado
A45: Santander Master Cristiane | B45: 5155.9003.8853.1850 | C45: 770 | D45: 07/23 | E45: 1816 | F45: 01 | G45: 21 / 22 | H45: =H44 -> 375 | K45: Cancelado
A46: Santander Master Luiz | B46: 5155.9012.8097.9726 | C46: 332 | D46: 01/28 | E46: 1793 | F46: 01 | G46: 21 / 22 | H46: 16500 | I46: =Santander_Master!E2432 -> 0.0048020004 | J46: =H46+I46 -> 16500.005 | K46: Cancelado
A47: Santander Visa | B47: 4916.7424.4138.8164 | C47: 693 | D47: 42583 | E47: 9230 | F47: 01 | G47: 21 / 22 | H47: 22000 | K47: Cancelado
A48: Santander Visa | B48: 4916.7432.4482.4975 | C48: 915 | D48: 43009 | E48: 9230 | F48: 01 | G48: 21 / 22 | H48: 24500 | K48: Cancelado
A49: Submarino | B49: 507860.18.00014.950320 | D49: 41730 | E49: 341177 | F49: 25 | G49: 15 / 16 | H49: 3000 | K49: Cancelado
A50: Trigg Visa | B50: 4722.8000.1104.2548 | C50: 674 | D50: 09/22 | E50: 9230 | F50: 01 | G50: 25 | H50: 6300 | I50: =Trigg_Visa!E56 -> 0 | J50: =H50+I50 -> 6300 | K50: Cancelado
A51: Unibanco Visa | B51: 4100.0105.4654.5013 | C51: 698 | D51: 38504 | F51: 02 | H51: 2000 | K51: Cancelado
A52: XP Investimentos Debito | B52: 4984.7300.4463.3323 | C52: 612 | D52: 10/27 | E52: 9230 | K52: Ativo
A53: XP Investimentos VISA Virtual | B53: 4998.1800.3019.7459 | C53: 229 | D53: 04/29 | E53: 9230 | F53: 01 | G53: 22 / 23 | H53: 0 | I53: =XP_Inv_Visa!E1487 -> 271.932 | J53: 0 | K53: Ativo
A54: ItauUniClass Visa Adicional | B54: 4179.3700.0339,2242 | D54: 09/33
H57: =H37+H38+H45+H49+H50 -> 23175 | I57: =I34+I37+I39+I36+I41 -> 0 | J57: =J39+J37+J34 -> 0

Sheet Faturas de Cartão
A1: Referencia | B1: Amazon Masters | C1: ItauUniclasV | D1: NuBank Master | E1: Xp Visa | F1: MercadoPagoVisa | G1: MagaLuVisaPlat | H1: CrediCard Master | I1: DUMMY | J1: Total | K1: Diferença
A2: Abril / 2021 | C2: 0 | D2: 0 | E2: 0 | F2: 0 | G2: 0 | H2: 0 | I2: 0 | J2: 5442.75
A3: Maio / 2021 | C3: 0 | E3: 0 | F3: 0 | H3: 0 | I3: 0 | J3: 3971.47 | K3: =J3-J2 -> -1471.28
A4: Junho/2021 | C4: 0 | D4: =NUBank_Master!F957 -> 714.49 | E4: =XP_Inv_Visa!F34 -> 1055.61 | F4: 0 | G4: 0 | H4: =CrediCard_Master!F424 -> 1876.17 | I4: 0 | J4: =SUM(B4:I4) -> 3646.27 | K4: =J4-J3 -> -325.2
A5: Julho/2021 | C5: 0 | D5: =NUBank_Master!F963 -> 261.11 | E5: =XP_Inv_Visa!F42 -> 907.5 | F5: 0 | G5: 0 | H5: =CrediCard_Master!F436 -> 1659.01 | I5: 0 | J5: =SUM(B5:I5) -> 2827.62 | K5: =J5-J4 -> -818.65
A6: Agosto/2021 | C6: 0 | D6: =NUBank_Master!F970 -> 261.11 | E6: =XP_Inv_Visa!F46 -> 48.6 | F6: 0 | G6: 0 | H6: =CrediCard_Master!F447 -> 1416.97 | I6: 0 | J6: =SUM(B6:I6) -> 1726.68 | K6: =J6-J5 -> -1100.94
A7: Setembro/2021 | C7: 0 | D7: =NUBank_Master!F976 -> 126.85 | E7: =XP_Inv_Visa!F53 -> 99.9 | F7: 0 | G7: 0 | H7: =CrediCard_Master!F459 -> 1409.69 | I7: 0 | J7: =SUM(B7:I7) -> 1636.44 | K7: =J7-J6 -> -90.24
A8: Outubro/2021 | C8: 0 | D8: =NUBank_Master!F981 -> 48.85 | E8: =XP_Inv_Visa!F61 -> 403.87 | F8: 0 | G8: 0 | H8: =CrediCard_Master!F471 -> 1125.66 | I8: 0 | J8: =SUM(B8:I8) -> 1578.38 | K8: =J8-J7 -> -58.06
A9: Novembro / 2021 | C9: 0 | D9: =NUBank_Master!F986 -> 48.85 | E9: =XP_Inv_Visa!F74 -> 644.41 | F9: 0 | G9: 0 | H9: =CrediCard_Master!F486 -> 1524.98 | I9: 0 | J9: =SUM(B9:I9) -> 2218.24 | K9: =J9-J8 -> 639.86
A10: Dezembro / 2021 | C10: 0 | D10: =NUBank_Master!F992 -> 48.85 | E10: =XP_Inv_Visa!F80 -> 302.71 | F10: 0 | G10: 0 | H10: =CrediCard_Master!F499 -> 1624.49 | I10: 0 | J10: =SUM(B10:I10) -> 1976.05 | K10: =J10-J9 -> -242.19
A11: Janeiro / 2022 | C11: 0 | D11: =NUBank_Master!F998 -> 76.75 | E11: =XP_Inv_Visa!F90 -> 440.6 | F11: 0 | G11: 0 | H11: =CrediCard_Master!F514 -> 1966.78 | I11: 0 | J11: =SUM(B11:I11) -> 2484.13 | K11: =J11-J10 -> 508.08
A12: Fevereiro / 2022 | C12: 0 | D12: =NUBank_Master!F1005 -> 76.75 | E12: =XP_Inv_Visa!F96 -> 271.93 | F12: 0 | G12: 0 | H12: =CrediCard_Master!F530 -> 1861.32 | I12: 0 | J12: =SUM(B12:I12) -> 2210 | K12: =J12-J11 -> -274.13
A13: Março / 2022 | C13: 0 | D13: =NUBank_Master!F1012 -> 196.73 | E13: =XP_Inv_Visa!F102 -> 129.88 | F13: 0 | G13: 0 | H13: =CrediCard_Master!F543 -> 1810.4 | I13: 0 | J13: =SUM(B13:I13) -> 2137.01 | K13: =J13-J12 -> -72.99
A14: Abril / 2022 | C14: 0 | D14: =NUBank_Master!F1020 -> 99.42 | E14: =XP_Inv_Visa!F108 -> 136.02 | F14: 0 | G14: 0 | H14: =CrediCard_Master!F559 -> 1933.48 | I14: 0 | J14: =SUM(B14:I14) -> 2168.92 | K14: =J14-J13 -> 31.91
A15: Maio / 2022 | C15: 0 | D15: =NUBank_Master!F1028 -> 76.75 | E15: =XP_Inv_Visa!F114 -> 497.61 | F15: 0 | G15: 0 | H15: =CrediCard_Master!F573 -> 1017.45 | I15: 0 | J15: =SUM(B15:I15) -> 1591.81 | K15: =J15-J14 -> -577.11
A16: Junho / 2022 | C16: 0 | D16: =NUBank_Master!F1034 -> 152.68 | E16: =XP_Inv_Visa!F126 -> 275.23 | F16: 0 | G16: 0 | H16: =CrediCard_Master!F590 -> 1348 | I16: 0 | J16: =SUM(B16:I16) -> 1775.91 | K16: =J16-J15 -> 184.1
A17: Julho / 2022 | C17: 0 | D17: =NUBank_Master!F1040 -> 76.75 | E17: =XP_Inv_Visa!F136 -> 376.8 | F17: =MercadoPago_Visa!F7 -> 0.01 | G17: =MagaLu_Visa_Plat!F11 -> 90.8 | H17: =CrediCard_Master!F605 -> 1679.86 | I17: 0 | J17: =SUM(B17:I17) -> 2224.22 | K17: =J17-J16 -> 448.31
A18: Agosto / 2022 | C18: 0 | D18: =NUBank_Master!F1047 -> 391.05 | E18: =XP_Inv_Visa!F145 -> 646.04 | F18: =MercadoPago_Visa!F18 -> 400.99 | G18: 0 | H18: =CrediCard_Master!F616 -> 1505.74 | I18: 0 | J18: =SUM(B18:I18) -> 2943.82 | K18: =J18-J17 -> 719.6
A19: Setembro / 2022 | C19: 0 | D19: =NUBank_Master!F1054 -> 76.75 | E19: =XP_Inv_Visa!F150 -> 114.88 | F19: 0 | G19: 0 | H19: =CrediCard_Master!F627 -> 1455.12 | I19: 0 | J19: =SUM(B19:I19) -> 1646.75 | K19: =J19-J18 -> -1297.07
A20: Outubro / 2022 | C20: 0 | D20: =NUBank_Master!F1063 -> 197.85 | E20: =XP_Inv_Visa!F155 -> 114.88 | F20: 0 | G20: 0 | H20: =CrediCard_Master!F640 -> 1361.97 | I20: 0 | J20: =SUM(B20:I20) -> 1674.7 | K20: =J20-J19 -> 27.95
A21: Novembro / 2022 | C21: 0 | D21: =NUBank_Master!F1076 -> 262.57 | E21: =XP_Inv_Visa!F162 -> 114.88 | F21: 0 | G21: =MagaLu_Visa_Plat!F21 -> 0 | H21: =CrediCard_Master!F657 -> 1586.59 | I21: 0 | J21: =SUM(B21:I21) -> 1964.04 | K21: =J21-J20 -> 289.34
A22: Dezembro / 2022 | C22: 0 | D22: =NUBank_Master!F1086 -> 703.22 | E22: =XP_Inv_Visa!F175 -> 289.91 | F22: 0 | G22: =MagaLu_Visa_Plat!F25 -> 41.14 | H22: =CrediCard_Master!F673 -> 1899.94 | I22: 0 | J22: =SUM(B22:I22) -> 2934.21 | K22: =J22-J21 -> 970.17
A23: Janeiro / 2023 | C23: 0 | D23: =NUBank_Master!F1095 -> 401.97 | E23: =XP_Inv_Visa!F195 -> 436.65 | F23: 0 | G23: =MagaLu_Visa_Plat!F31 -> 56.46 | H23: =CrediCard_Master!F691 -> 2703.55 | I23: 0 | J23: =SUM(B23:I23) -> 3598.63 | K23: =J23-J22 -> 664.42
A24: Fevereiro / 2023 | C24: 0 | D24: =NUBank_Master!F1104 -> 650.23 | E24: =XP_Inv_Visa!F206 -> 829.63 | F24: 0 | G24: =MagaLu_Visa_Plat!F42 -> 0 | H24: =CrediCard_Master!F706 -> 2336.43 | I24: 0 | J24: =SUM(B24:I24) -> 3816.29 | K24: =J24-J23 -> 217.66
A25: Março / 2023 | C25: =ItauUniclassVisa!F14 -> 128.8 | D25: =NUBank_Master!F1125 -> 3582.9 | E25: =XP_Inv_Visa!F211 -> 201.33 | F25: 0 | G25: 0 | H25: =CrediCard_Master!F717 -> 1927.42 | I25: 0 | J25: =SUM(B25:I25) -> 5840.45 | K25: =J25-J24 -> 2024.16
A26: Abril / 2023 | C26: =ItauUniclassVisa!F27 -> 129.45 | D26: =NUBank_Master!F1131 -> 136.85 | E26: =XP_Inv_Visa!F230 -> 100.27 | F26: 0 | G26: 0 | H26: =CrediCard_Master!F729 -> 1914.65 | I26: 0 | J26: =SUM(B26:I26) -> 2281.22 | K26: =J26-J25 -> -3559.23
A27: Maio / 2023 | C27: =ItauUniclassVisa!F36 -> 563.71 | D27: =NUBank_Master!F1140 -> 236.75 | E27: =XP_Inv_Visa!F239 -> 614.37 | F27: 0 | G27: 0 | H27: =CrediCard_Master!F738 -> 1280.1 | I27: 0 | J27: =SUM(B27:I27) -> 2694.93 | K27: =J27-J26 -> 413.71
A28: Junho / 2023 | C28: =ItauUniclassVisa!F52 -> 1279.84 | D28: =NUBank_Master!F1161 -> 535.93 | E28: =XP_Inv_Visa!F249 -> 417.03 | F28: 0 | G28: 0 | H28: =CrediCard_Master!F751 -> 979.47 | I28: 0 | J28: =SUM(B28:I28) -> 3212.27 | K28: =J28-J27 -> 517.34
A29: Julho / 2023 | C29: =ItauUniclassVisa!F56 -> 0 | D29: =NUBank_Master!F1169 -> 378.41 | E29: =XP_Inv_Visa!F263 -> 368.26 | H29: =CrediCard_Master!F760 -> 1112.06 | I29: 0 | J29: =SUM(B29:I29) -> 1858.73 | K29: =J29-J28 -> -1353.54
A30: Agosto / 2023 | C30: =ItauUniclassVisa!F60 -> 32.5 | D30: =NUBank_Master!F1210 -> 780.25 | E30: =XP_Inv_Visa!F280 -> 722.05 | H30: =CrediCard_Master!F773 -> 910.18 | I30: 0 | J30: =SUM(B30:I30) -> 2444.98 | K30: =J30-J29 -> 586.25
A31: Setembro / 2023 | D31: =NUBank_Master!F1224 -> 2897.9617 | E31: =XP_Inv_Visa!F299 -> 568.78 | H31: =CrediCard_Master!F792 -> 1001.29 | I31: 0 | J31: =SUM(B31:I31) -> 4468.0317 | K31: =J31-J30 -> 2023.0517
A32: Outubro / 2023 | D32: =NUBank_Master!F1246 -> 1326.8517 | E32: =XP_Inv_Visa!F316 -> 1667.76 | H32: =CrediCard_Master!F810 -> 1243.11 | I32: 0 | J32: =SUM(B32:I32) -> 4237.7217 | K32: =J32-J31 -> -230.31
A33: Novembro / 2023 | B33: =Amazon_Master!F17 -> 230.85 | C33: =ItauUniclassVisa!F68 -> 150 | D33: =NUBank_Master!F1268 -> 1590.0517 | E33: =XP_Inv_Visa!F351 -> 1000.75 | F33: =MercadoPago_Visa!F18 -> 400.99 | H33: =CrediCard_Master!F827 -> 1341.47 | I33: 0 | J33: =SUM(B33:I33) -> 4714.1117 | K33: =J33-J32 -> 476.39
A34: Dezembro / 2023 | B34: =Amazon_Master!F53 -> 0 | C34: =ItauUniclassVisa!F73 -> 50 | D34: =NUBank_Master!F1290 -> 2215.1817 | E34: =XP_Inv_Visa!F385 -> 3688.665 | F34: =MercadoPago_Visa!F23 -> 92 | H34: =CrediCard_Master!F840 -> 1761.52 | I34: 0 | J34: =SUM(B34:I34) -> 7807.3667 | K34: =J34-J33 -> 3093.255
A35: Janeiro / 2024 | B35: =Amazon_Master!F97 -> 3849.13 | C35: =ItauUniclassVisa!F80 -> 150 | D35: =NUBank_Master!F1308 -> 1796.6483 | E35: =XP_Inv_Visa!F425 -> 2477.27 | F35: =MercadoPago_Visa!F34 -> 260.77 | H35: =CrediCard_Master!F854 -> 1249.14 | I35: 0 | J35: =SUM(B35:I35) -> 9782.9583 | K35: =J35-J34 -> 1975.5917
A36: Fevereiro / 2024 | B36: =Amazon_Master!F130 -> 557.44 | C36: =ItauUniclassVisa!F87 -> 50 | D36: =NUBank_Master!F1323 -> 1654.3833 | E36: =XP_Inv_Visa!F457 -> 3006.87 | F36: =MercadoPago_Visa!F39 -> 178.2 | H36: =CrediCard_Master!F863 -> 1213.86 | I36: 0 | J36: =SUM(B36:I36) -> 6660.7533 | K36: =J36-J35 -> -3122.205
A37: Março / 2024 | B37: =Amazon_Master!F141 -> 1565.34 | C37: =ItauUniclassVisa!F94 -> 300 | D37: =NUBank_Master!F1336 -> 1511.05 | E37: =XP_Inv_Visa!F466 -> 2393.08 | F37: =MercadoPago_Visa!F45 -> 90.05 | H37: =CrediCard_Master!F872 -> 961.31 | I37: 0 | J37: =SUM(B37:I37) -> 6820.83 | K37: =J37-J36 -> 160.07667
A38: Abril / 2024 | B38: =Amazon_Master!F167 -> 413.7 | C38: =ItauUniclassVisa!F98 -> 0 | D38: =NUBank_Master!F1347 -> 1418.4983 | E38: =XP_Inv_Visa!F483 -> 522.52 | F38: =MercadoPago_Visa!F49 -> 0 | H38: =CrediCard_Master!F879 -> 1327.6 | I38: 0 | J38: =SUM(B38:I38) -> 3682.3183 | K38: =J38-J37 -> -3138.5117
A39: Maio / 2024 | B39: =Amazon_Master!F185 -> 1084.21 | C39: =ItauUniclassVisa!F103 -> 50 | D39: =NUBank_Master!F1362 -> 1586.6133 | E39: =XP_Inv_Visa!F524 -> 2322.58 | F39: =MercadoPago_Visa!F55 -> 57.04 | H39: =CrediCard_Master!F887 -> 1327.6 | I39: 0 | J39: =SUM(B39:I39) -> 6428.0433 | K39: =J39-J38 -> 2745.725
A40: Junho / 2024 | B40: =Amazon_Master!F199 -> 1059.85 | C40: =ItauUniclassVisa!F110 -> 150 | D40: =NUBank_Master!F1373 -> 1258.9433 | E40: =XP_Inv_Visa!F563 -> 4226.98 | F40: =MercadoPago_Visa!F60 -> 144.9 | H40: =CrediCard_Master!F887 -> 1327.6 | I40: 0 | J40: =SUM(B40:I40) -> 8168.2733 | K40: =J40-J39 -> 1740.23
A41: Julho / 2024 | B41: =Amazon_Master!F217 -> 1324.8533 | C41: =ItauUniclassVisa!F116 -> 0 | D41: =NUBank_Master!F1383 -> 1214.8033 | E41: =XP_Inv_Visa!F601 -> 2919.15 | F41: =MercadoPago_Visa!F65 -> 0 | H41: =CrediCard_Master!F896 -> 1153.55 | I41: 0 | J41: =SUM(B41:I41) -> 6612.3567 | K41: =J41-J40 -> -1555.9167
A42: Agosto / 2024 | B42: =Amazon_Master!F230 -> 866.22333 | C42: =ItauUniclassVisa!F122 -> 100 | D42: =NUBank_Master!F1396 -> 1818.9383 | E42: =XP_Inv_Visa!F646 -> 2702 | F42: =MercadoPago_Visa!F69 -> 0 | H42: =CrediCard_Master!F907 -> 957.01 | I42: 0 | J42: =SUM(B42:I42) -> 6444.1717 | K42: =J42-J41 -> -168.185
A43: Setembro / 2024 | B43: =Amazon_Master!F272 -> 1310.5633 | C43: =ItauUniclassVisa!F122 -> 100 | D43: =NUBank_Master!F1412 -> 2677.4483 | E43: =XP_Inv_Visa!F704 -> 5277.53 | F43: 0 | H43: =CrediCard_Master!F930 -> 1452.01 | I43: 0 | J43: =SUM(B43:I43) -> 10817.552 | K43: =J43-J42 -> 4373.38
A44: Outubro / 2024 | B44: =Amazon_Master!F319 -> 2712.6433 | C44: =ItauUniclassVisa!F131 -> 50 | D44: =NUBank_Master!F1423 -> 2146.0817 | E44: =XP_Inv_Visa!F736 -> 3471.41 | F44: =MercadoPago_Visa!F77 -> 354.12 | H44: =CrediCard_Master!F945 -> 2436.2 | I44: 0 | J44: =SUM(B44:I44) -> 11170.455 | K44: =J44-J43 -> 352.90333
A45: Novembro / 2024 | B45: =Amazon_Master!F371 -> 2098.1233 | C45: =ItauUniclassVisa!F135 -> 0 | D45: =NUBank_Master!F1432 -> 1420.8517 | E45: =XP_Inv_Visa!F789 -> 3338.51 | F45: =MercadoPago_Visa!F81 -> 0 | H45: =CrediCard_Master!F958 -> 2441.47 | I45: 0 | J45: =SUM(B45:I45) -> 9298.955 | K45: =J45-J44 -> -1871.5
A46: Dezembro / 2024 | B46: =Amazon_Master!F421 -> 2562.07 | C46: =ItauUniclassVisa!F139 -> 0 | D46: =NUBank_Master!F1440 -> 1277.5217 | E46: =XP_Inv_Visa!F857 -> 3449.09 | F46: =MercadoPago_Visa!F89 -> 144 | H46: =CrediCard_Master!F967 -> 1948.53 | I46: 0 | J46: =SUM(B46:I46) -> 9381.2117 | K46: =J46-J45 -> 82.256667
A47: Janeiro / 2025 | B47: =Amazon_Master!F458 -> 1636.81 | C47: =ItauUniclassVisa!F146 -> 100 | D47: =NUBank_Master!F1445 -> 604.12833 | E47: =XP_Inv_Visa!F933 -> 6540.5 | F47: =MercadoPago_Visa!F95 -> 134.3 | H47: =CrediCard_Master!F976 -> 1919.55 | I47: 0 | J47: =SUM(B47:I47) -> 10935.288 | K47: =J47-J46 -> 1554.0767
A48: Fevereiro / 2025 | B48: =Amazon_Master!F472 -> 2400.16 | C48: =ItauUniclassVisa!F152 -> 100 | D48: =NUBank_Master!F1450 -> 604.12833 | E48: =XP_Inv_Visa!F967 -> 6784.625 | F48: =MercadoPago_Visa!F103 -> 27.9 | H48: =CrediCard_Master!F983 -> 588.03 | I48: 0 | J48: =SUM(B48:I48) -> 10504.843 | K48: =J48-J47 -> -430.445
A49: Março / 2025 | B49: =Amazon_Master!F513 -> 707.78 | C49: =ItauUniclassVisa!F156 -> 50 | D49: =NUBank_Master!F1455 -> 604.12833 | E49: =XP_Inv_Visa!F1024 -> 3689.24 | F49: =MercadoPago_Visa!F108 -> 83.69 | H49: =CrediCard_Master!F989 -> 312.24 | I49: 0 | J49: =SUM(B49:I49) -> 5447.0783 | K49: =J49-J48 -> -5057.765
A50: Abril / 2025 | B50: =Amazon_Master!F549 -> 3090.56 | C50: =ItauUniclassVisa!F164 -> 200 | D50: =NUBank_Master!F1460 -> 604.12833 | E50: =XP_Inv_Visa!F1057 -> 2877.31 | F50: =MercadoPago_Visa!F113 -> 27.9 | H50: =CrediCard_Master!F993 -> 0 | I50: 0 | J50: =SUM(B50:I50) -> 6799.8983 | K50: =J50-J49 -> 1352.82
A51: Maio / 2025 | B51: =Amazon_Master!F570 -> 875.48 | C51: =ItauUniclassVisa!F168 -> 0 | D51: =NUBank_Master!F1465 -> 604.12833 | E51: =XP_Inv_Visa!F1099 -> 2599.58 | F51: =MercadoPago_Visa!F118 -> 27.9 | I51: 0 | J51: =SUM(B51:I51) -> 4107.0883 | K51: =J51-J50 -> -2692.81
A52: Junho / 2025 | B52: =Amazon_Master!F616 -> 1412.96 | C52: =ItauUniclassVisa!F173 -> 0 | D52: =NUBank_Master!F1472 -> 1608.63 | E52: =XP_Inv_Visa!F1157 -> 3755.14 | F52: =MercadoPago_Visa!F124 -> 200.9 | I52: 0 | J52: =SUM(B52:I52) -> 6977.63 | K52: =J52-J51 -> 2870.5417
A53: Julho / 2025 | B53: =Amazon_Master!F646 -> 2481.01 | C53: =ItauUniclassVisa!F178 -> 50 | D53: =NUBank_Master!F1480 -> 1796.55 | E53: =XP_Inv_Visa!F1231 -> 6117.83 | F53: =MercadoPago_Visa!F133 -> 182.32 | I53: 0 | J53: =SUM(B53:I53) -> 10627.71 | K53: =J53-J52 -> 3650.08
A54: Agosto / 2025 | B54: =Amazon_Master!F651 -> 1677.69 | C54: =ItauUniclassVisa!F188 -> 300 | D54: =NUBank_Master!F1487 -> 1192.43 | E54: =XP_Inv_Visa!F1323 -> 5981.362 | F54: =MercadoPago_Visa!F138 -> 67.8 | I54: 0 | J54: =SUM(B54:I54) -> 9219.282 | K54: =J54-J53 -> -1408.428
A55: Setembro / 2025 | B55: =Amazon_Master!F659 -> 431.39 | C55: =ItauUniclassVisa!F192 -> 0 | D55: =NUBank_Master!F1494 -> 1192.43 | E55: =XP_Inv_Visa!F1435 -> 7189.722 | F55: =MercadoPago_Visa!F142 -> 0 | I55: 0 | J55: =SUM(B55:I55) -> 8813.542 | K55: =J55-J54 -> -405.74
A56: Outubro / 2025 | B56: =Amazon_Master!F701 -> 2532.4 | C56: =ItauUniclassVisa!F243 -> 1226.77 | D56: =NUBank_Master!F1501 -> 1192.43 | E56: =XP_Inv_Visa!F1447 -> 4423.942 | F56: =MercadoPago_Visa!F146 -> 0 | I56: 0 | J56: =SUM(B56:I56) -> 9375.542 | K56: =J56-J55 -> 562
A57: Novembro / 2025 | B57: =Amazon_Master!F721 -> 994.87 | C57: =ItauUniclassVisa!F325 -> 6116.89 | D57: =NUBank_Master!F1509 -> 1630.43 | E57: =XP_Inv_Visa!F1453 -> 667.962 | F57: =MercadoPago_Visa!F150 -> 0 | I57: 0 | J57: =SUM(B57:I57) -> 9410.152 | K57: =J57-J56 -> 34.61
A58: Dezembro / 2025 | B58: =Amazon_Master!F743 -> 1201.2433 | C58: =ItauUniclassVisa!F405 -> 4769.7817 | D58: =NUBank_Master!F1517 -> 1414.91 | E58: =XP_Inv_Visa!F1459 -> 559.4 | F58: =MercadoPago_Visa!F154 -> 0 | I58: 0 | J58: =SUM(B58:I58) -> 7945.335 | K58: =J58-J57 -> -1464.817
A59: Janeiro / 2026 | B59: =Amazon_Master!F769 -> 1564.3233 | C59: =ItauUniclassVisa!F495 -> 5248.7317 | D59: =NUBank_Master!F1526 -> 1930.67 | E59: =XP_Inv_Visa!F1464 -> 246.9 | F59: =MercadoPago_Visa!F158 -> 0 | I59: 0 | J59: =SUM(B59:I59) -> 8990.625 | K59: =J59-J58 -> 1045.29
A60: Fevereiro / 2026 | B60: =Amazon_Master!F790 -> 1521.74 | C60: =ItauUniclassVisa!F572 -> 4311.9317 | D60: =NUBank_Master!F1536 -> 1930.6633 | E60: =XP_Inv_Visa!F1468 -> 0 | F60: 0 | I60: 0 | J60: =SUM(B60:I60) -> 7764.335 | K60: =J60-J59 -> -1226.29
A61: Março / 2026 | B61: =Amazon_Master!F816 -> 1248.44 | C61: =ItauUniclassVisa!F653 -> 4449.71 | D61: =NUBank_Master!F1553 -> 2121.76 | E61: 0 | F61: =MercadoPago_Visa!F166 -> 0 | I61: 0 | J61: =SUM(B61:I61) -> 7819.91 | K61: =J61-J60 -> 55.575
A62: Abril / 2026 | B62: =Amazon_Master!F869 -> 2123.46 | C62: =ItauUniclassVisa!F725 -> 4161.7 | D62: =NUBank_Master!F1564 -> 7213.91 | E62: 0 | F62: =MercadoPago_Visa!F170 -> 0 | J62: =SUM(B62:I62) -> 13499.07 | K62: =J62-J61 -> 5679.16
A63: Maio / 2026 | B63: =Amazon_Master!F951 -> 5481.56 | C63: =ItauUniclassVisa!F749 -> 719.34 | D63: =NUBank_Master!F1574 -> 2531.61 | E63: 0 | F63: 0 | J63: =SUM(B63:I63) -> 8732.51 | K63: =J63-J62 -> -4766.56
A64: Junho / 2026 | B64: =Amazon_Master!F1009 -> 4703.81 | C64: =ItauUniclassVisa!F779 -> 2194.54 | D64: =NUBank_Master!F1589 -> 1180.66 | J64: =SUM(B64:I64) -> 8079.01 | K64: =J64-J63 -> -653.5
A65: Julho / 2026 | B65: =Amazon_Master!F1018 -> 685.79967 | C65: =ItauUniclassVisa!F788 -> 0 | D65: =NUBank_Master!F1600 -> 1180.6667 | J65: =SUM(B65:I65) -> 1866.4663 | K65: =J65-J64 -> -6212.5437
A66: Agosto /2026 | D66: =NUBank_Master!F1611 -> 1011.6667 | J66: =SUM(B66:I66) -> 1011.6667 | K66: =J66-J65 -> -854.79967
A67: Setembro / 2026 | D67: =NUBank_Master!F1621 -> 573.66667 | J67: =SUM(B67:I67) -> 573.66667 | K67: =J67-J66 -> -438
A68: Outubro / 2026 | D68: =NUBank_Master!F1631 -> 573.66667
A69: Novembro / 2026 | D69: =NUBank_Master!F1641 -> 0
A70: Dezembro / 2026 | D70: =NUBank_Master!F1650 -> 0
A82: Diminuiu | I82: 0 | K82: =SUMIF(K3:K37,"<0") -> -14593.145
A83: Aumentou | I83: 0 | K83: =SUMIF(K2:K37,">0") -> 15971.225
A84: Limite/Mês desejado | B84: 400 | C84: 150 | D84: 500 | E84: 450 | F84: 400 | G84: 0 | H84: 800 | I84: 0 | J84: =H84+D84+E84+G84+F84+C84+B84 -> 2700

Sheet TiposLancamentos
A1: Código | B1: Descrição
A2: FIX001 | B2: Telefonia
A3: FIX002 | B3: Internet
A4: FIX003 | B4: Taxas Bancarias
A5: FIX004 | B5: Supermercado
A6: FIX005 | B6: Energia Eletrica
A7: FIX006 | B7: Apto. Proprio 01
A8: FIX007 | B8: Aluguel
A9: FIX008 | B9: Condominio
A10: FIX009 | B10: Distr. Água Municipal
A11: FIX010 | B11: Coleta Municipal Lixo
A12: FIX011 | B12: IPTU
... A105: TRA001 | B105: Transf. Bco

Sheet Amazon_Master
A1: Data | B1: TIPO | C1: DESCRICAO | D1: Credito | E1: Debito | F1: Subtotais | G1: Check
C2: Setembro/2023
A3: 45199 | B3: =TiposLancamentos!B78 -> Diferenças | C3: Teste In | D3: 0.01 | G3: X
A4: 45199 | B4: =TiposLancamentos!B78 -> Diferenças | C4: Teste Out | E4: 0.01 | G4: X
C5: /DEV/NULL
C6: CORTE DE FATURAMENTO | G6: ???
C7: /DEV/NULL
C8: Outubro / 2023 | F8: =SUM(E2:E6) -> 0.01
A9: 45207 | B9: =TiposLancamentos!B13 -> Moradia | C9: Amazon.com.br: Smart data Mini Liquidificador Portatil Mixer Portatil Shake Coqueteleira Eletrica Sem Fio Squeeze Recarregavel 400ml (verde azul rosa Roxo - enviado | E9: 16.89 | F9: =F8-F2 -> 0.01 | G9: X
A10: 45207 | B10: =TiposLancamentos!B60 -> Correio | C10: Frete: Amazon.com.br: Smart data Mini Liquidificador Portatil Mixer Portatil Shake Coqueteleira Eletrica Sem Fio Squeeze Recarregavel 400ml (verde azul rosa Roxo - enviado | E10: 23.47 | F10: 40.36 | G10: X
A11: 45207 | B11: =TiposLancamentos!B57 -> Informática | C11: Amazon.com.br: Controle Super Nintendo Snes USB Joystick Retrô com fio Video Game Pc Computador Notebook Mac Raspberry | E11: 39.9 | G11: X
A12: 45207 | B12: =TiposLancamentos!B13 -> Moradia | C12: Amazon.com.br: Relógio despertador digital, Relógio LED para quarto, Relógio eletrônico de mesa com visor de temperatura, brilho ajustável, | E12: 59.8 | G12: X
A13: 45207 | B13: =TiposLancamentos!B13 -> Moradia | C13: Amazon.com.br: Cabo Hdmi 2.1 áudio e vídeo Ultra Hd Speed 2m Hs8k20 Elg | E13: 90.79 | G13: X
A14: 45220 | C14: /DEV/NULL | D14: 0 | E14: 0
C15: CORTE DE FATURAMENTO | G15: ???
C16: /DEV/NULL
C17: Novembro / 2022 | F17: =SUM(E6:E15) -> 230.85
A18: 45231 | B18: =TiposLancamentos!B15 -> Cartões de Crédito | C18: Pagamento de Fatura | D18: 230.85 | G18: X
A19: 45236 | B19: =TiposLancamentos!B13 -> Moradia | C19: Amazon.com.br: Bomba Dispensador Elétrico Para Galão De Água Recarregável USB Premium Praticidade e Luxo na hidratação diária Cores Sortidas LCS Eletrônicos | E19: 0 | G19: X
C20: CORTE DE FATURAMENTO | G20: ???
A21: 45253 | B21: =TiposLancamentos!B45 -> Online Services | C21: iCloud+ 50GB Mensal | E21: 4.9 | G21: X
A22: 45253 | B22: =TiposLancamentos!B39 -> Playstation 5 | C22: MagazineLuiza.com.br: Controle Sony DualSense PS5, Sem Fio, Midnight Black | E22: 314.91 | G22: X
A23: 45253 | B23: =TiposLancamentos!B5 -> Supermercado | C23: O Carrefour mini de SCS | E23: 49.42 | G23: X
A24: 45255 | B24: =TiposLancamentos!B5 -> Supermercado | C24: o oXXo | E24: 16.68 | G24: X
A25: 45255 | B25: =TiposLancamentos!B22 -> Combustivel | C25: Gazzozza no Pejô GGM5 | E25: 150 | G25: X
A26: 45255 | B26: =TiposLancamentos!B56 -> Farmácia | C26: Eso-Meprazol e Donperidona | E26: 172.27 | G26: X
A27: 45255 | B27: =TiposLancamentos!B19 -> Restaurantes | C27: Jeronimos no Mapping | E27: 89.8 | G27: X
A28: 45255 | B28: =TiposLancamentos!B57 -> Informática | C28: Kalunga Shoppig Mapping: Pilhas Alcalinas AA | E28: 26.9 | G28: X
A29: 45255 | B29: =B24 -> Supermercado | C29: o oXXo | E29: 43.97 | G29: X
A30: 45255 | B30: =TiposLancamentos!B5 -> Supermercado | C30: No mercadinho do predio | E30: 17.78 | G30: X
A31: 45256 | B31: =TiposLancamentos!B19 -> Restaurantes | C31: Café no posto do patins em guarulhos | E31: 19.97 | G31: X
A32: 45256 | B32: =TiposLancamentos!B19 -> Restaurantes | C32: o Raggazzoo | E32: 139.04 | G32: X
A33: 45256 | B33: =TiposLancamentos!B56 -> Farmácia | C33: Remédios de dores de cabeças | E33: 35.69 | G33: X
A34: 45256 | B34: =TiposLancamentos!B19 -> Restaurantes | C34: iFood: Didios | E34: 90.9 | G34: X
A35: 45256 | B35: =TiposLancamentos!B5 -> Supermercado | C35: No mercadinho do predio | E35: 12.26 | G35: X
A36: 45257 | B36: =TiposLancamentos!B19 -> Restaurantes | C36: Trabalho: Café de manha na padoca | E36: 10 | G36: X
A37: 45257 | B37: =TiposLancamentos!B19 -> Restaurantes | C37: Trabalho: O Gallo´s | E37: 41.21 | G37: X
A38: 45257 | B38: =TiposLancamentos!B19 -> Restaurantes | C38: Trabalho: Caféz | E38: 11 | G38: X
A39: 45257 | B39: =TiposLancamentos!B19 -> Restaurantes | C39: Trabalho: Caféz | E39: 14.9 | G39: X
A40: 45257 | B40: =TiposLancamentos!B65 -> Taxi | C40: UBER pra ir pra estação | E40: 27.51 | G40: X
A41: 45257 | B41: =TiposLancamentos!B5 -> Supermercado | C41: Paccocca santa monicas | E41: 37.3 | G41: X
A42: 45258 | B42: =TiposLancamentos!B45 -> Online Services | C42: Assinatura Mensal Netflix (2 Telas FullHD) | E42: 39.9 | G42: X
A43: 45258 | B43: =TiposLancamentos!B45 -> Online Services | C43: Assinatura Mensal do Spotfy Familiar (5 Acessos) | E43: 34.9 | G43: X
A44: 45258 | B44: =TiposLancamentos!B19 -> Restaurantes | C44: O Primus | E44: 40 | G44: X
A45: 45258 | B45: =TiposLancamentos!B19 -> Restaurantes | C45: No mercadinho do predio | E45: 7.99 | G45: X
A46: 45258 | B46: =TiposLancamentos!B17 -> GATO | C46: Nova Bandeija de Coco, areia de coco e saches | E46: 71.6 | G46: X
A47: 45258 | B47: =TiposLancamentos!B24 -> Estacionamentos | C47: Maçonaria: Tres Pontos | E47: 18 | G47: X
A48: 45258 | B48: =TiposLancamentos!B19 -> Restaurantes | C48: Trabalho: A la carte do mineiro | E48: 25.9 | G48: X
A49: 45258 | B49: =TiposLancamentos!B5 -> Supermercado | C49: Trabalho: chocolates | E49: 8.99 | G49: X
A50: 45260 | B50: =TiposLancamentos!B45 -> Online Services | C50: Assinatura Mensal HBO Max | E50: 17.45 | G50: X
A51: 45260 | B51: =TiposLancamentos!B60 -> Correio | C51: Hometheater: AliExpress.com: LEDS RGBs | E51: =F52-E52 -> 29.13 | G51: X
A52: 45260 | B52: =TiposLancamentos!B13 -> Moradia | C52: Hometheater: AliExpress.com: LEDS RGBs | E52: 55.24 | F52: 84.37 | G52: X
C53: Dezembro / 2023 | F53: =SUM(E15:E20) -> 0
A54: 45261 | B54: =TiposLancamentos!B15 -> Cartões de Crédito | C54: Pagamento de Fatura | D54: 0 | F54: =F53-F17 -> -230.85
A55: 45261 | B55: =TiposLancamentos!B71 -> Itens Pessoais | C55: Cortar Cabelos | E55: 35 | G55: X
A56: 45262 | B56: =TiposLancamentos!B19 -> Restaurantes | C56: O Embaixador no centro | E56: 61 | G56: X
A57: 45262 | B57: =TiposLancamentos!B17 -> GATO | C57: Ração, Areia e saches | E57: 187.96 | G57: X
A58: 45263 | B58: =TiposLancamentos!B5 -> Supermercado | C58: A Coop da Industrial | E58: 332.78 | G58: X
A59: 45263 | B59: =TiposLancamentos!B19 -> Restaurantes | C59: iFood: The Burgues Galleries | E59: 95.4 | G59: X
A60: 45264 | B60: =TiposLancamentos!B54 -> Metro | C60: Trabalho: Creditos TOPs | E60: 96.8 | G60: X
C61: /DEV/NULL
A62: 45265 | B62: =TiposLancamentos!B37 -> Playstation 3 | C62: Aliexpress.com: Bateria para Sony PS3 Playstation 3, LIS1442, 4-180-962-01, controlador de navegação, CECH-ZCS1E, CECH-ZCS1U | E62: 60.89 | G62: X
A63: 45265 | B63: =TiposLancamentos!B60 -> Correio | C63: Frete: Bateria para Sony PS3 Playstation 3, LIS1442, 4-180-962-01, controlador de navegação, CECH-ZCS1E, CECH-ZCS1U | E63: =F63-E62 -> 31.77 | F63: 92.66 | G63: X
C64: /DEV/NULL
A65: 45266 | B65: =TiposLancamentos!B16 -> Cristiane | C65: Cremes intimos | E65: 44.59 | G65: X
A66: 45266 | B66: =TiposLancamentos!B56 -> Farmácia | C66: Termometros | E66: 24.79 | G66: X
A67: 45266 | B67: =TiposLancamentos!B18 -> Alimentacao | C67: chocolates | E67: 9.43 | F67: =SUM(E65:E67) -> 78.81 | G67: X
C68: /DEV/NULL
A69: 45268 | B69: =TiposLancamentos!B24 -> Estacionamentos | C69: Na laser ocular | E69: 18 | G69: X
A70: 45268 | B70: =TiposLancamentos!B19 -> Restaurantes | C70: iFood: Thew Burgues Galleries | E70: 90.4 | G70: X
A71: 45269 | B71: =TiposLancamentos!B72 -> Presentes | C71: Maçonaria: Presentes de finais de anos | E71: 143.93 | G71: X
A72: 45269 | B72: =TiposLancamentos!B19 -> Restaurantes | C72: Cafés no centro | E72: 35.5 | G72: X
A73: 45269 | B73: =TiposLancamentos!B22 -> Combustivel | C73: Gazozza no Pejo GGM5 | E73: 50 | G73: X
A74: 45270 | B74: =TiposLancamentos!B45 -> Online Services | C74: Assinatura Anual Amazon Prime | E74: 119 | G74: X
A75: 45270 | B75: =TiposLancamentos!B19 -> Restaurantes | C75: Almoço no Shopping são Pailo | E75: 120.6 | G75: X
A76: 45270 | B76: =TiposLancamentos!B24 -> Estacionamentos | C76: Estacionamento em Sp | E76: 20 | G76: X
A77: 45270 | B77: =TiposLancamentos!B19 -> Restaurantes | C77: iFood: Didios: | E77: 94.9 | G77: X
A78: 45272 | B78: =TiposLancamentos!B19 -> Restaurantes | C78: iFood: The Burguês Galleries | E78: 95.4 | G78: X
A79: 45273 | B79: =TiposLancamentos!B60 -> Correio | C79: Hometheater: AliExpress.com: LEDS RGBs (silver errado) | E79: =F80-E80 -> 34.76 | G79: X
A80: 45273 | B80: =TiposLancamentos!B13 -> Moradia | C80: Hometheater: AliExpress.com: LEDS RGBs (silver errado) | E80: 55.24 | F80: 90 | G80: X
C81: /DEV/NULL
A82: 45273 | B82: =TiposLancamentos!B60 -> Correio | C82: Hometheater: AliExpress.com: LEDS RGBs | E82: =F83-E83 -> 34.76 | G82: X
A83: 45273 | B83: =TiposLancamentos!B13 -> Moradia | C83: Hometheater: AliExpress.com: LEDS RGBs | E83: 55.24 | F83: 90 | G83: X
A84: 45275 | B84: =TiposLancamentos!B102 -> ESTORNO | C84: Hometheater: AliExpress.com: LEDS RGBs | D84: 90
A85: 45275 | B85: =TiposLancamentos!B17 -> GATO | C85: Areia de coco de gatos | E85: 32.98 | G85: X
A86: 45275 | B86: =TiposLancamentos!B19 -> Restaurantes | C86: iFood: The Burguês Galleries | E86: 90.4 | G86: X
A87: 45276 | B87: =TiposLancamentos!B19 -> Restaurantes | C87: o rancho 53 | E87: 41.6 | G87: X
A88: 45276 | B88: =TiposLancamentos!B19 -> Restaurantes | C88: a camponesa da castelo | E88: 48.9 | G88: X
A89: 45276 | B89: =TiposLancamentos!B19 -> Restaurantes | C89: tiquinhos sorveter's piraju | E89: 30 | G89: X
A90: 45277 | B90: =TiposLancamentos!B19 -> Restaurantes | C90: O Maristela gaarals | E90: 38.2 | G90: X
A91: 45277 | B91: =TiposLancamentos!B19 -> Restaurantes | C91: A quinta do marqiues do KM57 | E91: 33.4 | G91: X
C92: CORTE DE FATURAMENTO | G92: ???
A93: 45283 | B93: =TiposLancamentos!B45 -> Online Services | C93: iCloud+ 50GB Mensal | E93: 4.9 | G93: X
A94: 45288 | B94: =TiposLancamentos!B45 -> Online Services | C94: Assinatura Mensal Netflix (2 Telas FullHD) | E94: 39.9 | G94: X
A95: 45288 | B95: =TiposLancamentos!B45 -> Online Services | C95: Assinatura Mensal do Spotfy Familiar (5 Acessos) | E95: 34.9 | G95: X
A96: 45290 | B96: =TiposLancamentos!B45 -> Online Services | C96: Assinatura Mensal HBO Max | E96: 17.45 | G96: X
C97: Janeiro / 2024 | F97: =SUM(E20:E92)-D84 -> 3849.13
A98: 45292 | B98: =TiposLancamentos!B15 -> Cartões de Crédito | C98: Pagamento de Fatura | D98: 3849.13 | F98: =F97-F53 -> 3849.13 | G98: X
A99: 45297 | B99: =TiposLancamentos!B19 -> Restaurantes | C99: Go Coffee do centro | E99: 54 | G99: X
A100: 45300 | B100: =TiposLancamentos!B19 -> Restaurantes | C100: iFood: Netão´s | E100: 69.79 | G100: X
...

Sheet Despesas
A1: Data | B1: TIPO | C1: DESCRICAO | D1: Credito | E1: Debito | F1: Subtotais
C2: Junho / 2004
A3: 38139 | B3: =TiposLancamentos!B78 -> Diferenças | C3: Ajustes | E3: 21.29
A4: 38146 | B4: =TiposLancamentos!B95 -> Salarios | C4: Rec. Salario | D4: 1036
A5: 38146 | B5: =TiposLancamentos!B3 -> Internet | C5: Pagamento conectway | E5: 50
A6: 38146 | B6: =TiposLancamentos!B66 -> Faxineira | C6: Tia que LavaRopa | E6: 90
A7: 38146 | B7: =TiposLancamentos!B83 -> Artigos Moto | C7: Pagamento da Luva do maffei | E7: 7
A8: 38146 | B8: =TiposLancamentos!B105 -> Transf. Bco | C8: Deposito Salário Banco1 | E8: 883
A9: 38146 | B9: =TiposLancamentos!B99 -> Venda de algo | C9: Recebimento do Cristovão – Livro UML | D9: 40
A10: 38150 | B10: =TiposLancamentos!B69 -> Consertos | C10: Bateria do relógio | E10: 4
A11: 38150 | B11: =TiposLancamentos!B5 -> Supermercado | C11: Bolacha + leite + nescau | E11: 4.95
A12: 38152 | B12: =TiposLancamentos!B99 -> Venda de algo | C12: Recebimento do Diego – Livro S.D | D12: 30
A13: 38153 | B13: =TiposLancamentos!B24 -> Estacionamentos | C13: Estacionamento perto da labor | E13: 1.8
A14: 38155 | B14: =TiposLancamentos!B69 -> Consertos | C14: Conserto da Jaqueta | E14: 5
A15: 38155 | B15: =TiposLancamentos!B5 -> Supermercado | C15: Bolacha no mercado | E15: 1.99
A16: 38156 | B16: =TiposLancamentos!B33 -> Pedágios | C16: Pedágio | E16: 1.6
A17: 38156 | B17: =TiposLancamentos!B74 -> Noite | C17: Jantar | E17: 3
A18: 38156 | B18: =TiposLancamentos!B74 -> Noite | C18: Festa da junina | E18: 2
A19: 38158 | B19: =TiposLancamentos!B33 -> Pedágios | C19: Pedágio | E19: 1.6
A20: 38159 | B20: =TiposLancamentos!B8 -> Aluguel | C20: Aluguel | E20: 30
A21: 38160 | B21: =TiposLancamentos!B20 -> Saques | C21: SAQUE parea pagar o correio | D21: 10
A22: 38160 | B22: =TiposLancamentos!B60 -> Correio | C22: Postagem do prinmce of persia 3d | E22: 4
A23: 38160 | B23: =TiposLancamentos!B18 -> Alimentacao | C23: Compra de pão + mortandela | E23: 2
A24: 38161 | B24: =TiposLancamentos!B18 -> Alimentacao | C24: Pastel na feira + lanche do Robs | E24: 5
A25: 38168 | B25: =TiposLancamentos!B99 -> Venda de algo | C25: Recebimento de Venda dos livros (01/02) | D25: 100
A26: 38168 | B26: =TiposLancamentos!B18 -> Alimentacao | C26: Lanche do Robs | E26: 5.5
A27: 38168 | B27: =TiposLancamentos!B18 -> Alimentacao | C27: Bolachas do Bigatu´s | E27: 3
C28: Julho / 2004
A29: 38169 | B29: =TiposLancamentos!B57 -> Informática | C29: Pagamento dos CeDês Virge na InfoCia | E29: 15
A30: 38169 | B30: =TiposLancamentos!B22 -> Combustivel | C30: Gasolina na motoca | E30: 21.5
A31: 38169 | B31: =TiposLancamentos!B2 -> Telefonia | C31: Fatura Telefonica - Sercomtel | E31: 48.16
A32: 38169 | B32: =TiposLancamentos!B16 -> Cristiane | C32: Cristiane - Busão + encadernar | E32: 6.8
A33: 38169 | B33: =TiposLancamentos!B16 -> Cristiane | C33: Troco | D33: 3
A34: 38169 | B34: =TiposLancamentos!B99 -> Venda de algo | C34: Recebimento de Venda dos livros (02/02) | D34: 20
A35: 38169 | B35: =TiposLancamentos!B18 -> Alimentacao | C35: Pão com mortandela do Bigatu´s | E35: 4.2
A36: 38170 | B36: =TiposLancamentos!B5 -> Supermercado | C36: Produtos de Limpeza | E36: 14.24
A37: 38171 | B37: =TiposLancamentos!B33 -> Pedágios | C37: Pedágio | E37: 1.9
A38: 38172 | B38: =TiposLancamentos!B33 -> Pedágios | C38: Pedágio | E38: 1.9
A39: 38175 | B39: =TiposLancamentos!B95 -> Salarios | C39: Rec. Salário | D39: 1036
A40: 38175 | B40: =TiposLancamentos!B6 -> Energia Eletrica | C40: Copel | E40: 48.61
A41: 38175 | B41: =TiposLancamentos!B9 -> Condominio | C41: Condominio | E41: 99.25
A42: 38175 | B42: =TiposLancamentos!B82 -> CG Titan 125 | C42: Parc. Financiamento Moto (06/24) | E42: 133.1
A43: 38175 | B43: =TiposLancamentos!B19 -> Restaurantes | C43: Restaurante Doce café | E43: 87
A44: 38175 | B44: =TiposLancamentos!B24 -> Estacionamentos | C44: estacionamento perto do bradesco | E44: 1
A45: 38175 | B45: =TiposLancamentos!B18 -> Alimentacao | C45: Padaria | E45: 2.2
A46: 38178 | B46: =TiposLancamentos!B24 -> Estacionamentos | C46: Estacionamento | E46: 1
A47: 38178 | B47: =TiposLancamentos!B31 -> Action Figures | C47: Exterminador do Futuro | E47: 10
A48: 38178 | B48: =TiposLancamentos!B18 -> Alimentacao | C48: refrigerante pra janta | E48: 1.7
A49: 38179 | B49: =TiposLancamentos!B33 -> Pedágios | C49: Pedágio | E49: 1.9
A50: 38180 | B50: =TiposLancamentos!B83 -> Artigos Moto | C50: Chaveiro Algemas | E50: 3
A51: 38180 | B51: =TiposLancamentos!B13 -> Moradia | C51: Banqueta pra colocar o Porta Cedês | E51: 6.5
A52: 38180 | B52: =TiposLancamentos!B99 -> Venda de algo | C52: Recebimento do Diego - Xerox de Livro | D52: 15
A53: 38180 | B53: =TiposLancamentos!B5 -> Supermercado | C53: Bolachas | E53: 2
A54: 38181 | B54: =TiposLancamentos!B18 -> Alimentacao | C54: Pao + mortandela | E54: 2.2
A55: 38182 | B55: =TiposLancamentos!B18 -> Alimentacao | C55: Doce no restaurante do Jorjão | E55: 1.5
A56: 38182 | B56: =TiposLancamentos!B90 -> Locadora | C56: Locadora - Senhor dos Aneis - retorno... | E56: 2.5
A57: 38182 | B57: =TiposLancamentos!B5 -> Supermercado | C57: bolachas | E57: 2
A58: 38183 | B58: =TiposLancamentos!B15 -> Cartões de Crédito | C58: Pagamento Fatura Mastercard | E58: 140.1
A59: 38183 | B59: =TiposLancamentos!B56 -> Farmácia | C59: Farmácia - eno | E59: 0.9
A60: 38184 | B60: =TiposLancamentos!B22 -> Combustivel | C60: Gasolina na motoca | E60: 20
A61: 38184 | B61: =B31 -> Telefonia | C61: Fatura Telefonica - GVT | E61: 23.8
A62: 38184 | B62: =TiposLancamentos!B18 -> Alimentacao | C62: =C55 -> Doce no restaurante do Jorjão | E62: 1.5
A63: 38184 | B63: =TiposLancamentos!B16 -> Cristiane | C63: Pagamento dos Shampoos do mês passado | D63: 25
A64: 38185 | B64: =TiposLancamentos!B8 -> Aluguel | C64: Alugel | E64: 249.95
A65: 38185 | B65: =TiposLancamentos!B16 -> Cristiane | C65: cedê virge | E65: 2.5
A66: 38185 | B66: =B55 -> Alimentacao | C66: Pastel no cantinho do pastel | E66: 2
A67: 38185 | B67: =TiposLancamentos!B13 -> Moradia | C67: insenso | E67: 1.5
A68: 38185 | B68: =TiposLancamentos!B82 -> CG Titan 125 | C68: Lavagem | E68: 8
A69: 38186 | B69: =TiposLancamentos!B18 -> Alimentacao | C69: Bolacha do Bigatus | E69: 3.6
A70: 38187 | B70: =TiposLancamentos!B18 -> Alimentacao | C70: Doces no Jorjão | E70: 3
A71: 38187 | B71: =TiposLancamentos!B55 -> Onibus Urbano | C71: Buzão pra ir pro trabalho | E71: 1.6
A72: 38187 | B72: =TiposLancamentos!B5 -> Supermercado | C72: Leite + bolachas | E72: 3.6
A73: 38189 | B73: =TiposLancamentos!B18 -> Alimentacao | C73: Doces no jorjão | E73: 1.5
A74: 38189 | B74: =TiposLancamentos!B82 -> CG Titan 125 | C74: retrovisor e manopla da embreagem | E74: 6.65
A75: 38189 | B75: =TiposLancamentos!B90 -> Locadora | C75: Locadora - T3 + Uma saida de Mestre | E75: 5
A76: 38189 | B76: =TiposLancamentos!B5 -> Supermercado | C76: Bolachas | E76: 2
A77: 38191 | B77: =TiposLancamentos!B19 -> Restaurantes | C77: Pizzaria Happen | E77: 30.5
A78: 38192 | B78: =B69 -> Alimentacao | C78: Café da manhã na padaria | E78: 3.2
A79: 38192 | B79: =TiposLancamentos!B5 -> Supermercado | C79: Leite + bolachas | E79: 3.5
A80: 38192 | B80: =TiposLancamentos!B24 -> Estacionamentos | C80: Estacionamento | E80: 1
A81: 38192 | B81: =TiposLancamentos!B33 -> Pedágios | C81: Pedágio | E81: 1.9
A82: 38193 | B82: =TiposLancamentos!B33 -> Pedágios | C82: Pedágio | E82: 1.9
A83: 38193 | B83: =TiposLancamentos!B5 -> Supermercado | C83: Frutas + camisinhas | E83: 6.66
A84: 38193 | B84: =TiposLancamentos!B18 -> Alimentacao | C84: Padaria | E84: 2.25
A85: 38194 | B85: =TiposLancamentos!B90 -> Locadora | C85: Locadora - filhos de Duna | E85: 3.5
A86: 38194 | B86: =TiposLancamentos!B5 -> Supermercado | C86: Bolachas | E86: 2
A87: 38195 | B87: =TiposLancamentos!B18 -> Alimentacao | C87: Docê do Jorjão | E87: 1.5
A88: 38196 | B88: =TiposLancamentos!B18 -> Alimentacao | C88: Docê do Jorjão | E88: 1.5
A89: 38196 | B89: =TiposLancamentos!B90 -> Locadora | C89: Locadora - Neno + 21 Gramas | E89: 8
A90: 38196 | B90: =TiposLancamentos!B18 -> Alimentacao | C90: Padaria | E90: 2.1
A91: 38197 | B91: =TiposLancamentos!B5 -> Supermercado | C91: Q-boa | E91: 1.25
A92: 38197 | B92: =TiposLancamentos!B105 -> Transf. Bco | C92: Deposito no Banco1.net | E92: 20
A93: 38197 | B93: =TiposLancamentos!B5 -> Supermercado | C93: coisas pra janta | E93: 1.15
A94: 38198 | B94: =TiposLancamentos!B18 -> Alimentacao | C94: Lanche no bobs | E94: 4.8
A95: 38199 | B95: =TiposLancamentos!B26 -> LIVROS | C95: Livro Messia de Duna | E95: 4
A96: 38199 | B96: =TiposLancamentos!B18 -> Alimentacao | C96: Pastel | E96: 2
A97: 38199 | B97: =TiposLancamentos!B18 -> Alimentacao | C97: Sorvete | E97: 1.5
A98: 38199 | B98: =TiposLancamentos!B78 -> Diferenças | C98: Diferenças | D98: 0.03
A99: 38199 | B99: =TiposLancamentos!B5 -> Supermercado | C99: Mercado | E99: 5.05
C100: Agosto / 2004
...

Sheet ItaU
A1: Data | B1: TIPO | C1: DESCRICAO | D1: Credito | E1: Debito | F1: Subtotais | G1: Check
C2: Abril / 2005 | D2: 0 | E2: 0
A3: 38471 | B3: =TiposLancamentos!B95 -> Salarios | C3: CREDITO DE SALARIO UNITECH | D3: 2364.75
A4: 38471 | B4: =TiposLancamentos!B9 -> Condominio | C4: Pagamento Condominio | E4: 142.5
A5: 38471 | B5: =TiposLancamentos!B2 -> Telefonia | C5: Fatura Telefonica - BrT Fixa | E5: 140.56
A6: 38471 | B6: =TiposLancamentos!B3 -> Internet | C6: Fatura BrTurbo | E6: 59.9
A7: 38471 | B7: =TiposLancamentos!B15 -> Cartões de Crédito | C7: Pagamento Fatura Visa (CB) | E7: 573.74
A8: 38471 | B8: =TiposLancamentos!B15 -> Cartões de Crédito | C8: Pagamento Fatura Master Card (CB) | E8: 214.49
A9: 38471 | B9: =TiposLancamentos!B5 -> Supermercado | C9: Cheque Eletronico - Mercado | E9: 21.13
C10: Maio / 2005
A11: 38473 | B11: =TiposLancamentos!B20 -> Saques | C11: Saque | E11: 10
A12: 38474 | B12: =TiposLancamentos!B22 -> Combustivel | C12: Cheque Eletronico - Gasosa na motoca | E12: 25.41
A13: 38474 | B13: =TiposLancamentos!B5 -> Supermercado | C13: Cheque Eletronico - Mercado | E13: 22.9
A14: 38475 | B14: =TiposLancamentos!B56 -> Farmácia | C14: Cheque Eletronico - Farmácia pra cris | E14: 4.63
A15: 38475 | B15: =TiposLancamentos!B5 -> Supermercado | C15: Cheque Eletronico - Mercado | E15: 9.64
A16: 38475 | B16: =TiposLancamentos!B4 -> Taxas Bancarias | C16: TAR MAXICONTA MENS | E16: 8
A17: 38477 | B17: =TiposLancamentos!B17 -> GATO | C17: Cheque Eletronico - Coisas do Gato | E17: 69.7
A18: 38478 | B18: =TiposLancamentos!B4 -> Taxas Bancarias | C18: cpmfi | E18: 4.64
A19: 38479 | B19: =TiposLancamentos!B82 -> CG Titan 125 | C19: Cheque eletronico - Luvas da moto | E19: 6.63
A20: 38480 | B20: =TiposLancamentos!B5 -> Supermercado | C20: Cheque Eletronico - Mercado | E20: 7.67
A21: 38481 | B21: =TiposLancamentos!B19 -> Restaurantes | C21: Cheque Eletronico - Giraffas | E21: 11.5
A22: 38482 | B22: =TiposLancamentos!B82 -> CG Titan 125 | C22: Cheque eletronico - Revisao Moto | E22: 69.78
A23: 38483 | B23: =TiposLancamentos!B97 -> Deposito Terc. | C23: Deposito do conserto da moto | D23: 40
A24: 38485 | B24: =TiposLancamentos!B4 -> Taxas Bancarias | C24: cpmfi | E24: 0.6
A25: 38485 | B25: =TiposLancamentos!B8 -> Aluguel | C25: Cheque Eletronico - Aluguel Maio/2005 | E25: 797.76
A26: 38485 | B26: =TiposLancamentos!B17 -> GATO | C26: Cheque Eletronico - Raçao pro gato | E26: 49.6
A27: 38485 | B27: =TiposLancamentos!B19 -> Restaurantes | C27: Cheque Eletronico - Pizzaria | E27: 41.5
A28: 38488 | B28: =TiposLancamentos!B15 -> Cartões de Crédito | C28: Fatura unibanco Mastercard | E28: 49.9
A29: 38492 | B29: =TiposLancamentos!B4 -> Taxas Bancarias | C29: cpmfi | E29: 3.54
A30: 38492 | B30: =TiposLancamentos!B6 -> Energia Eletrica | C30: Fatura CEB | E30: 55.41
A31: 38499 | B31: =TiposLancamentos!B4 -> Taxas Bancarias | C31: cpmfi | E31: 0.21
A32: 38503 | B32: =TiposLancamentos!B95 -> Salarios | C32: CREDITO DE SALARIO UNITECH | D32: 2664.2
A33: 38503 | B33: =TiposLancamentos!B2 -> Telefonia | C33: Fatura Telefonica - BrT Fixa | E33: 169.73
A34: 38503 | B34: =TiposLancamentos!B3 -> Internet | C34: Fatura BrTurbo | E34: 59.9
A35: 38503 | B35: =TiposLancamentos!B2 -> Telefonia | C35: Fatura Telefonica - TIM | E35: 53.03
A36: 38503 | B36: =TiposLancamentos!B15 -> Cartões de Crédito | C36: Pagamento Fatura Master Card (CB) | E36: 184.8
A37: 38503 | B37: =TiposLancamentos!B15 -> Cartões de Crédito | C37: Pagamento Fatura Visa (CB) | E37: 902.81
A38: 38503 | B38: =TiposLancamentos!B22 -> Combustivel | C38: Cheque Eletronico - Gasolina na motoca | E38: 25
A39: 38503 | B39: =TiposLancamentos!B18 -> Alimentacao | C39: Cheque Eletronico - Mc Sorvete | E39: 7.2
A40: 38503 | B40: =TiposLancamentos!B9 -> Condominio | C40: Condominio | E40: 142.5
A41: 38503 | B41: =TiposLancamentos!B19 -> Restaurantes | C41: Cheque Eletronico - Giraffas | E41: 18.3
A42: 38503 | B42: =TiposLancamentos!B56 -> Farmácia | C42: Cheque Eletronico - Farmácia pra cris | E42: 27.03
C43: Junho / 2005
A44: 38504 | B44: =TiposLancamentos!B5 -> Supermercado | C44: Cheque Eletronico - Mercado | E44: 24.74
A45: 38505 | B45: =TiposLancamentos!B20 -> Saques | C45: Saque | E45: 30
A46: 38505 | B46: =TiposLancamentos!B19 -> Restaurantes | C46: Cheque eletronico - Mc Trash | E46: 23.9
A47: 38505 | B47: =TiposLancamentos!B4 -> Taxas Bancarias | C47: TAR MAXICONTA MENS 05/05 | E47: 7
A48: 38506 | B48: =TiposLancamentos!B19 -> Restaurantes | C48: Cheque Eletronico - Giraffas | E48: 12
A49: 38506 | B49: =TiposLancamentos!B4 -> Taxas Bancarias | C49: cpmfi | E49: 6.01
A50: 38507 | B50: =TiposLancamentos!B17 -> GATO | C50: Cheque Eletronico - Banho + afiador de Unhas | E50: 37
A51: 38513 | B51: =TiposLancamentos!B19 -> Restaurantes | C51: Cheque Eletronico - Giraffas | E51: 12
A52: 38513 | B52: =TiposLancamentos!B4 -> Taxas Bancarias | C52: cpmfi | E52: 0.49
A53: 38514 | B53: =TiposLancamentos!B17 -> GATO | C53: Cheuqe eletronico - Raçao pro gato | E53: 49.6
A54: 38514 | B54: =TiposLancamentos!B19 -> Restaurantes | C54: cheque eletronico - Bobs | E54: 18.8
A55: 38514 | B55: =TiposLancamentos!B19 -> Restaurantes | C55: Cheque eletronico - Milkshake bobs | E55: 8
A56: 38514 | B56: =TiposLancamentos!B5 -> Supermercado | C56: Cheque Eletronico - Mercado | E56: 9.06
A57: 38516 | B57: =TiposLancamentos!B22 -> Combustivel | C57: Gasosa na motoca | E57: 25.35
A58: 38516 | B58: =TiposLancamentos!B82 -> CG Titan 125 | C58: Moto (17/24) | E58: 133.1
A59: 38516 | B59: =TiposLancamentos!B105 -> Transf. Bco | C59: Transf Unibanco | D59: 133.1
A60: 38517 | B60: =TiposLancamentos!B8 -> Aluguel | C60: Pagamento Aluguel | E60: 797.76
A61: 38518 | B61: =TiposLancamentos!B56 -> Farmácia | C61: Cheque Eletronico - Farmácia | E61: 14.83
A62: 38520 | B62: =TiposLancamentos!B4 -> Taxas Bancarias | C62: cpmfi | E62: 3.97
A63: 38527 | B63: =TiposLancamentos!B4 -> Taxas Bancarias | C63: cpmfi | E63: 0.05
A64: 38532 | B64: =TiposLancamentos!B95 -> Salarios | C64: CREDITO DE SALARIO UNITECH | D64: 2331.76
A65: 38533 | B65: =TiposLancamentos!B2 -> Telefonia | C65: Fatura Telefonica - Brt Fixa | E65: 141.22
A66: 38533 | B66: =TiposLancamentos!B3 -> Internet | C66: Fatura BrTurbo | E66: 59.9
A67: 38533 | B67: =TiposLancamentos!B2 -> Telefonia | C67: Fatura Telefonica - TIM | E67: 78.8
A68: 38533 | B68: =TiposLancamentos!B9 -> Condominio | C68: condominio | E68: 142.5
A69: 38533 | B69: =TiposLancamentos!B15 -> Cartões de Crédito | C69: Pagamento Fatura Visa (CB) | E69: 1177.16
A70: 38533 | B70: =TiposLancamentos!B15 -> Cartões de Crédito | C70: Pagamento Fatura Master Card (CB) | E70: 184.8
C71: Julho / 2005
A72: 38534 | B72: =TiposLancamentos!B78 -> Diferenças | C72: Ajustes | D72: 0.01
A73: 38537 | B73: =TiposLancamentos!B20 -> Saques | C73: Saque | E73: 30
A74: 38537 | B74: =TiposLancamentos!B4 -> Taxas Bancarias | C74: TAR MAXICONTA MENS 06/05 | E74: 7
A75: 38537 | B75: =TiposLancamentos!B4 -> Taxas Bancarias | C75: TAR MAXCONTA EXCED 06/05 | E75: 1.2
A76: 38538 | B76: =TiposLancamentos!B82 -> CG Titan 125 | C76: Oleo na motoca | E76: 12.01
A77: 38538 | B77: =TiposLancamentos!B19 -> Restaurantes | C77: McAlmoço | E77: 11.95
A78: 38539 | B78: =TiposLancamentos!B20 -> Saques | C78: Pra Cris | E78: 10
A79: 38541 | B79: =TiposLancamentos!B4 -> Taxas Bancarias | C79: CPMFI | E79: 7.01
A80: 38544 | B80: =TiposLancamentos!B82 -> CG Titan 125 | C80: Moto(18/24) | E80: 133.1
A81: 38545 | B81: =TiposLancamentos!B105 -> Transf. Bco | C81: Transf Unibanco | D81: 133.1
A82: 38547 | B82: =TiposLancamentos!B8 -> Aluguel | C82: Aluguel | E82: 797.76
A83: 38548 | B83: =TiposLancamentos!B4 -> Taxas Bancarias | C83: CPMFI | E83: 0.5
A84: 38552 | B84: =TiposLancamentos!B16 -> Cristiane | C84: Credito no celular | E84: 25
A85: 38555 | B85: =TiposLancamentos!B4 -> Taxas Bancarias | C85: CPMFI | E85: 3.12
A86: 38556 | B86: =TiposLancamentos!B20 -> Saques | C86: Saque | E86: 40
A87: 38562 | B87: =TiposLancamentos!B4 -> Taxas Bancarias | C87: CPMFI | E87: 0.15
A88: 38562 | B88: =TiposLancamentos!B95 -> Salarios | C88: CREDITO DE SALARIO UNITECH | D88: 2401.18
A89: 38562 | B89: =TiposLancamentos!B2 -> Telefonia | C89: Fatura Telefonica - BrT Fixa | E89: 140.44
A90: 38562 | B90: =TiposLancamentos!B3 -> Internet | C90: Fatura BrTurbo | E90: 59.9
A91: 38562 | B91: =TiposLancamentos!B2 -> Telefonia | C91: Fatura Telefonica - TIM | E91: 77.08
A92: 38562 | B92: =TiposLancamentos!B9 -> Condominio | C92: Condominio | E92: 142.5
A93: 38562 | B93: =TiposLancamentos!B20 -> Saques | C93: Saque | E93: 10
A94: 38562 | B94: =TiposLancamentos!B15 -> Cartões de Crédito | C94: Pagamento Fatura Visa (CB) | E94: 1009.63
A95: 38562 | B95: =TiposLancamentos!B15 -> Cartões de Crédito | C95: Pagamento Fatura Master Card (CB) | E95: 314.53
A96: 38562 | B96: =TiposLancamentos!B16 -> Cristiane | C96: Fatura Telefonica - TIM | E96: 35
C97: Agosto / 2005
A98: 38565 | B98: =TiposLancamentos!B20 -> Saques | C98: Saque | E98: 70
A99: 38565 | B99: =TiposLancamentos!B4 -> Taxas Bancarias | C99: IOF | E99: 0.22
A100: 38565 | B100: =TiposLancamentos!B4 -> Taxas Bancarias | C100: COMISS VALOR LIBERADo | E100: 0.79
...

Sheet ItauUniclassVisa
A1: Data | B1: TIPO | C1: DESCRICAO | D1: Credito | E1: Debito | F1: Subtotais | G1: Check
C2: Jan/2023
A3: 44946 | B3: =TiposLancamentos!B77 -> Esporádico | C3: Teste | D3: 0.01 | G3: X
A4: 44946 | B4: =TiposLancamentos!B78 -> Diferenças | C4: Teste | E4: 0.01 | G4: X
C5: CORTE DE FATURAMENTO | G5: ???
C6: /DEV/NULL
C7: Fevereiro/2023
C8: /DEV/NULL
A9: 44968 | B9: =TiposLancamentos!B19 -> Restaurantes | C9: O Sukyia do centro | E9: 78.8 | G9: X
A10: 44968 | B10: =TiposLancamentos!B33 -> Pedágios | C10: Creditos PePago Conect Car Itau Tag | E10: 50 | G10: X
C11: /DEV/NULL
C12: CORTE DE FATURAMENTO | G12: ???
C13: /DEV/NULL
C14: 44986 | F14: =SUM(E5:E12) -> 128.8
A15: 44986 | B15: =TiposLancamentos!B15 -> Cartões de Crédito | C15: Pagamento de Fatura | D15: 128.8 | G15: X
A16: 44986 | B16: =TiposLancamentos!B102 -> ESTORNO | C16: Estono de pagamento errado | E16: 128.8 | G16: X
A17: 45000 | B17: =TiposLancamentos!B15 -> Cartões de Crédito | C17: PGTO MIN-ITAUCARD-2033 | D17: 19.32 | G17: X
A18: 45008 | B18: =TiposLancamentos!B4 -> Taxas Bancarias | C18: Juros De Financiamento | E18: 15.94 | G18: X
A19: 45008 | B19: =TiposLancamentos!B4 -> Taxas Bancarias | C19: Multa Por Atraso | E19: 2.58 | G19: X
A20: 45008 | B20: =TiposLancamentos!B4 -> Taxas Bancarias | C20: Juros De Mora | E20: 0.56 | G20: X
A21: 45008 | B21: =TiposLancamentos!B4 -> Taxas Bancarias | C21: Encargos De Atraso | E21: 0.89 | F21: =SUM(E18:E21) -> 19.97 | G21: X
C22: CORTE DE FATURAMENTO | G22: ???
A23: 45011 | B23: =TiposLancamentos!B5 -> Supermercado | C23: No mercadinho do predio | E23: 32.05 | G23: X
A24: 45013 | B24: =TiposLancamentos!B5 -> Supermercado | C24: A coop da indistrial | E24: 191.5 | G24: X
A25: 45013 | B25: =TiposLancamentos!B19 -> Restaurantes | C25: iFood: Rabibes | E25: 154.1 | G25: X
A26: 45014 | B26: =TiposLancamentos!B56 -> Farmácia | C26: coisas diversas | E26: 185.28 | G26: X
C27: 45017 | F27: =SUM(E12:E22)-D17 -> 129.45
A28: 45018 | B28: =TiposLancamentos!B15 -> Cartões de Crédito | C28: Pagamento de Fatura | D28: 129.45 | F28: =F27-F14 -> 0.65 | G28: X
A29: 45039 | B29: =TiposLancamentos!B4 -> Taxas Bancarias | C29: IOF de financiamento (0,38 % + 0,00820 % a.d.) | E29: 0.78 | G29: X
C30: CORTE DE FATURAMENTO | G30: ???
A31: 45040 | B31: =TiposLancamentos!B26 -> LIVROS | C31: Amazon.com: A Practical Guide to Qabalistic Symbolism Capa comum ; por Gareth Knight (Autor) | E31: 330.31 | G31: ???
A32: 45040 | B32: =TiposLancamentos!B4 -> Taxas Bancarias | C32: IOF: Amazon.com: A Practical Guide to Qabalistic Symbolism Capa comum ; por Gareth Knight (Autor) | E32: 17.76 | G32: ???
A33: 45042 | B33: =TiposLancamentos!B57 -> Informática | C33: Amazon.com.br: Linsoul Monitor de fone de ouvido intra-auricular HiFi com diafragma PET, 10 mm, com cabo OFC destacável para músicos e audiófilos (sem microfone, preto) | E33: 74 | G33: X
A34: 45044 | B34: =TiposLancamentos!B33 -> Pedágios | C34: Creditos PrePago Conect Car Itau Tag | E34: 50 | G34: X
A35: 45044 | B35: =TiposLancamentos!B33 -> Pedágios | C35: Creditos PrePago Conect Car Itau Tag | E35: 50 | G35: X
C36: 45047 | F36: =SUM(E22:E30) -> 563.71
A37: 45047 | B37: =TiposLancamentos!B33 -> Pedágios | C37: Creditos PrePago Conect Car Itau Tag | E37: 50 | F37: =F36-F27 -> 434.26 | G37: X
A38: 45047 | B38: =TiposLancamentos!B15 -> Cartões de Crédito | C38: Pagamento de Fatura | D38: 563.71 | G38: X
A39: 45059 | B39: =B32 -> Taxas Bancarias | C39: Anuidade diferenciada (01/12) | E39: 0 | F39: 53 | G39: ???
A40: 45063 | B40: =TiposLancamentos!B24 -> Estacionamentos | C40: Creditos PrePago Conect Car Itau Tag | E40: 50 | G40: X
C41: /DEV/NULL
A42: 45068 | B42: =TiposLancamentos!B37 -> Playstation 3 | C42: Game: MeuGameUsado.com.br: Alone In the Dark | E42: 64.44 | G42: X
A43: 45068 | B43: =TiposLancamentos!B37 -> Playstation 3 | C43: Game: MeuGameUsado.com.br: Blades od Time | E43: 139.89 | G43: X
A44: 45068 | B44: =TiposLancamentos!B37 -> Playstation 3 | C44: Game: MeuGameUsado.com.br: Enslaved: Odyssey to the West | E44: 69.9 | G44: X
A45: 45068 | B45: =TiposLancamentos!B37 -> Playstation 3 | C45: Game: MeuGameUsado.com.br: Untold Legend: dark Kingdom | E45: 90.89 | G45: X
A46: 45068 | B46: =TiposLancamentos!B37 -> Playstation 3 | C46: Game: MeuGameUsado.com.br: Venetica | E46: 101.9 | F46: =SUM(E42:E46) -> 467.02 | G46: X
A47: 45068 | B47: =TiposLancamentos!B60 -> Correio | C47: Frete: Game: MeuGameUsado.com.br: | E47: =F47-F46 -> 14.75 | F47: 481.77 | G47: X
C48: /DEV/NULL
A49: 45069 | B49: =TiposLancamentos!B33 -> Pedágios | C49: TecSan: manutenção do PS2 | E49: 176 | G49: X
C50: CORTE DE FATURAMENTO | G50: ???
C51: /DEV/NULL
C52: 45078 | F52: =SUM(E30:E50) -> 1279.84
A53: 45078 | B53: =TiposLancamentos!B15 -> Cartões de Crédito | C53: Pagamento de Fatura | D53: 1279.84 | F53: =F52-F36 -> 716.13
C54: /DEV/NULL
C55: CORTE DE FATURAMENTO | G55: ???
C56: 45108 | F56: =SUM(E50:E55) -> 0
A57: 45110 | B57: =TiposLancamentos!B57 -> Informática | C57: Amazon.com.br: Pano de fixação de microfibra de gerenciamento de abraçadeiras de cabo, alça de cabo ajustável com fecho de gancho e laço, preto. (15,24 cm 50 peças) | E57: 32.5 | F57: =F56-F52 -> -1279.84 | G57: X
C58: CORTE DE FATURAMENTO | G58: ???
C59: /DEV/NULL | F59: =SUM(E55:E58) -> 32.5
C60: Agosto / 2023 | F60: =SUM(E55:E58) -> 32.5
A61: 45139 | B61: =TiposLancamentos!B15 -> Cartões de Crédito | C61: Pagamento de Fatura | D61: 32.5 | F61: =F59-F56 -> 32.5
C62: CORTE DE FATURAMENTO | G62: ???
A63: 45211 | B63: =TiposLancamentos!B33 -> Pedágios | C63: Creditos PrePago Conect Car Itau Tag | E63: 50 | G63: X
A64: 45211 | B64: =TiposLancamentos!B33 -> Pedágios | C64: Creditos PrePago Conect Car Itau Tag | E64: 50 | G64: X
A65: 45214 | B65: =TiposLancamentos!B33 -> Pedágios | C65: Creditos PrePago Conect Car Itau Tag | E65: 50 | G65: X
C66: CORTE DE FATURAMENTO | G66: ???
C67: /DEV/NULL | F67: =SUM(E66:E66) -> 0
C68: Novembro / 2023 | F68: =SUM(E62:E66) -> 150
A69: 45231 | B69: =TiposLancamentos!B15 -> Cartões de Crédito | C69: Pagamento de Fatura | D69: 150 | G69: X
A70: 45250 | B70: =TiposLancamentos!B24 -> Estacionamentos | C70: Creditos PrePago Conect Car Itau Tag | E70: 50 | G70: X
C71: CORTE DE FATURAMENTO | G71: ???
C72: /DEV/NULL | F72: =SUM(E71:E71) -> 0
C73: Dezembro / 2023 | F73: =SUM(E66:E71) -> 50
A74: 45261 | B74: =TiposLancamentos!B15 -> Cartões de Crédito | C74: Pagamento de Fatura | D74: 50 | F74: =F73-F68 -> -100 | G74: X
A75: 45276 | B75: =TiposLancamentos!B33 -> Pedágios | C75: Creditos PrePago Conect Car Itau Tag | E75: 50 | G75: X
A76: 45276 | B76: =TiposLancamentos!B33 -> Pedágios | C76: Creditos PrePago Conect Car Itau Tag | E76: 50 | G76: X
A77: 45277 | B77: =TiposLancamentos!B33 -> Pedágios | C77: Creditos PrePago Conect Car Itau Tag | E77: 50 | G77: X
C78: CORTE DE FATURAMENTO | G78: ???
C79: /DEV/NULL
C80: Janeiro / 2024 | F80: =SUM(E71:E78) -> 150
A81: 45292 | B81: =TiposLancamentos!B15 -> Cartões de Crédito | C81: Pagamento de Fatura | D81: 150 | F81: =F80-F73 -> 100 | G81: X
A82: 45297 | B82: =TiposLancamentos!B24 -> Estacionamentos | C82: Creditos PrePago Conect Car Itau Tag | E82: 50 | G82: X
C83: CORTE DE FATURAMENTO | G83: ???
A84: 45316 | B84: =TiposLancamentos!B33 -> Pedágios | C84: Creditos PrePago Conect Car Itau Tag | E84: 50 | G84: X
A85: 45319 | B85: =TiposLancamentos!B33 -> Pedágios | C85: Creditos PrePago Conect Car Itau Tag | E85: 50 | G85: X
A86: 45319 | B86: =TiposLancamentos!B33 -> Pedágios | C86: Creditos PrePago Conect Car Itau Tag | E86: 50 | G86: X
C87: Fevereiro / 2024 | F87: =SUM(E78:E83) -> 50
A88: 45323 | B88: =TiposLancamentos!B15 -> Cartões de Crédito | C88: Pagamento de Fatura | D88: 50 | F88: =F80-F87 -> 100 | G88: X
A89: 45333 | B89: =TiposLancamentos!B33 -> Pedágios | C89: Creditos PrePago Conect Car Itau Tag | E89: 50 | G89: X
A90: 45333 | B90: =TiposLancamentos!B33 -> Pedágios | C90: Creditos PrePago Conect Car Itau Tag | E90: 50 | G90: X
A91: 45336 | B91: =TiposLancamentos!B33 -> Pedágios | C91: Creditos PrePago Conect Car Itau Tag | E91: 50 | G91: X
C92: CORTE DE FATURAMENTO | G92: ???
C93: /DEV/NULL
C94: Março / 2024 | F94: =SUM(E83:E92) -> 300
A95: 45352 | B95: =TiposLancamentos!B15 -> Cartões de Crédito | C95: Pagamento de Fatura | D95: 300 | F95: =F94-F87 -> 250
C96: CORTE DE FATURAMENTO | G96: ???
C97: /DEV/NULL
C98: Abril / 2024 | F98: =SUM(E92:E96) -> 0
A99: 45383 | B99: =TiposLancamentos!B15 -> Cartões de Crédito | C99: Pagamento de Fatura | D99: 0 | F99: =F98-F94 -> -300
A100: 45403 | B100: =TiposLancamentos!B33 -> Pedágios | C100: Creditos connect Cars | E100: 50 | G100: X
...

Sheet ITI_Itau_CC
A1: Data | B1: TIPO | C1: DESCRICAO | D1: Credito | E1: Debito | F1: Subtotais | G1: Check
A2: 44904 | B2: =TiposLancamentos!B105 -> Transf. Bco | C2: PIX: Do Itau | D2: 0.93
A3: 44963 | B3: =TiposLancamentos!B103 -> Juros_Corr. Poupança | C3: Juros e Corração no Periodo | D3: 0.01
A4: 44981 | B4: =TiposLancamentos!B103 -> Juros_Corr. Poupança | C4: Juros e Corração no Periodo | D4: 0.01
A5: 44999 | B5: =TiposLancamentos!B103 -> Juros_Corr. Poupança | C5: Juros e Corração no Periodo | D5: 0.01
A6: 45027 | B6: =TiposLancamentos!B103 -> Juros_Corr. Poupança | C6: Juros e Corração no Periodo | D6: 0.01
A7: 45048 | B7: =TiposLancamentos!B105 -> Transf. Bco | C7: PIX: Para o NuBank | E7: 0.04
A8: 45078 | B8: =TiposLancamentos!B103 -> Juros_Corr. Poupança | C8: Juros e Corração no Periodo | D8: 0.01
A9: 45106 | B9: =TiposLancamentos!B103 -> Juros_Corr. Poupança | C9: Juros e Corração no Periodo | D9: 0.01
A10: 45106 | B10: =TiposLancamentos!B105 -> Transf. Bco | C10: PIX: Para o MercadoPago | E10: 0.02
A11: 45126 | B11: =TiposLancamentos!B103 -> Juros_Corr. Poupança | C11: Juros e Corração no Periodo | D11: 0.01
A12: 45126 | B12: =TiposLancamentos!B105 -> Transf. Bco | C12: PIX: Para a conta Fantasma do B.B | E12: 0.01
A13: 45180 | B13: =TiposLancamentos!B103 -> Juros_Corr. Poupança | C13: Juros e Corração no Periodo | D13: 0.02
A14: 45182 | B14: =TiposLancamentos!B105 -> Transf. Bco | C14: PIX: da CEF | D14: 11.83
A15: 45215 | B15: =TiposLancamentos!B103 -> Juros_Corr. Poupança | C15: Juros e Corração no Periodo | D15: 0.09
A16: 45244 | B16: =TiposLancamentos!B105 -> Transf. Bco | C16: PIX: Para o NuBank | E16: 10
A17: 45264 | B17: =TiposLancamentos!B105 -> Transf. Bco | C17: PIX: Do XP Invest | D17: 1.86
A18: 45264 | B18: =TiposLancamentos!B105 -> Transf. Bco | C18: PIX: DO NuBank | D18: 0.22
A19: 45264 | B19: =TiposLancamentos!B105 -> Transf. Bco | C19: PIX: DO NuBank | D19: 0.2
A20: 45267 | B20: =TiposLancamentos!B105 -> Transf. Bco | C20: PIX: Do IMercadoPago | D20: 4.29
A21: 45294 | B21: =TiposLancamentos!B105 -> Transf. Bco | C21: PIX: para o MercadoPago CC | E21: 8.51
A22: 45665 | B22: =TiposLancamentos!B105 -> Transf. Bco | C22: PIX: para o MercadoPago CC | E22: 0.93
A23: 45856 | B23: =TiposLancamentos!B105 -> Transf. Bco | C23: PIX: do NuBANK | D23: 14.96
A24: 45856 | B24: =TiposLancamentos!B105 -> Transf. Bco | C24: PIX: Para o NuBank | E24: 14.96
G29: ???
C30: Totais: | D30: =SUM(D2:D29) -> 34.47 | E30: =SUM(E2:E29) -> 34.47
C31: Saldo Presumido | E31: =D30-E30 -> 0
E32: 0
E33: =IF(E32<>0,E31-E32,0) -> 0
E34: 0
E35: =E34+E31 -> 0
D37: Limite | E37: Posição | F37: Disponivel
B38: Valor Parcial da Fatura | E38: =E31 -> 0 | F38: =D38+E38 -> 0

Sheet MercadoPago_CC
A1: Data | B1: TIPO | C1: DESCRICAO | D1: Credito | E1: Debito | F1: Subtotais | G1: Check
A2: 44736 | B2: =TiposLancamentos!B105 -> Transf. Bco | C2: PIX: Da Caixa Poupança | D2: 3.45
A3: 44736 | B3: =TiposLancamentos!B105 -> Transf. Bco | C3: PIX: Para o XP CC | E3: 2.52
A4: 44919 | B4: =TiposLancamentos!B57 -> Informática | C4: HomeOffice: MercdoLIvre.com.br: Mouse Pad Gigante 90x40 | E4: 0.93
A5: 45012 | B5: =TiposLancamentos!B98 -> Restituições | C5: dinheiro perdido do Santander | D5: 0.68
A6: 45012 | B6: =TiposLancamentos!B98 -> Restituições | C6: PIX: Dinheiro perdiro de algum lugar | D6: 0.28
A7: 45106 | B7: =TiposLancamentos!B105 -> Transf. Bco | C7: PIX: DO Itau ITI | D7: 0.02
A8: 45107 | B8: =TiposLancamentos!B105 -> Transf. Bco | C8: PIX: DO Itau | D8: 29.7
A9: 45107 | B9: =TiposLancamentos!B57 -> Informática | C9: Cabo Adaptador Av Componente Tv Samsung Led Lcd P1 P2 5 Rca | E9: 16.5
A10: 45107 | B10: =TiposLancamentos!B60 -> Correio | C10: Mercado Frete do Cabo | E10: =F10-E9 -> 13.2 | F10: 29.7
A11: 45108 | B11: =TiposLancamentos!B105 -> Transf. Bco | C11: PIX: DO Itau | D11: 172
A12: 45108 | B12: =TiposLancamentos!B37 -> Playstation 3 | C12: Game: MercadoLivre.com.br: The Cursed Crusade | E12: 147
A13: 45108 | B13: =TiposLancamentos!B60 -> Correio | C13: Mercado Frete do Cabo | E13: 25 | F13: =SUM(E12:E13) -> 172
A14: 45110 | B14: =TiposLancamentos!B105 -> Transf. Bco | C14: PIX: do NuBank | D14: 700
A15: 45111 | B15: =TiposLancamentos!B36 -> Playstation 2 | C15: AliExpress.com: Kit Cabos SCART | E15: 114.25
A16: 45111 | B16: =TiposLancamentos!B60 -> Correio | C16: Frete Kit Cabos SCART | E16: 42.13 | F16: =SUM(E15:E16) -> 156.38
A17: 45111 | B17: =TiposLancamentos!B36 -> Playstation 2 | C17: AliExpress.com: RetroScaler-BlueRetro adaptador de controlador de jogo sem fio, Nintendo Switch, PSX, PS1, PS2 para IPX, PS4, PS5, 9076 | E17: 75.67
A18: 45116 | B18: =TiposLancamentos!B37 -> Playstation 3 | C18: Game: jp: Conan | E18: 81.5
A19: 45116 | B19: =TiposLancamentos!B37 -> Playstation 3 | C19: Game: jp: BioShock | E19: 81.2
A20: 45116 | B20: =TiposLancamentos!B60 -> Correio | C20: Frete Jogos JP | E20: 27.3 | F20: =SUM(E18:E20) -> 190
A21: 45117 | B21: =TiposLancamentos!B46 -> Maçonaria | C21: Maçonaria - Contribuição Mensal - Julho/2023 | E21: 210
A22: 45127 | B22: =TiposLancamentos!B37 -> Playstation 3 | C22: Game: MercadoShop.com.br: GlaukeraGames: Wet PS3 | E22: =F23-E23 -> 43.03
A23: 45127 | B23: =TiposLancamentos!B60 -> Correio | C23: Frete:Game: MercadoShop.com.br: GlaukeraGames: Wet PS3 | E23: 25.9 | F23: 68.93
A24: 45216 | B24: =TiposLancamentos!B105 -> Transf. Bco | C24: PIX: do NuBank | D24: 210
A25: 45216 | B25: =TiposLancamentos!B46 -> Maçonaria | C25: Maçonaria - Contribuição Mensal - Outubro/2023 | E25: 210
A26: 45267 | B26: =TiposLancamentos!B16 -> Cristiane | C26: PIX: da conta do ML | D26: 68.45
A27: 45267 | B27: =TiposLancamentos!B57 -> Informática | C27: MercadoLivre.com.br: Cabo Carregador Tipo C Para Lightning Essager Turbo 27w 1 M | E27: 53.91
A28: 45267 | B28: =TiposLancamentos!B60 -> Correio | C28: Frete: Cabo Carregador Tipo C Para Lightning Essager Turbo 27w 1 M | E28: 10.25
A29: 45267 | B29: =TiposLancamentos!B105 -> Transf. Bco | C29: PIX: Para o ITI CC | E29: 4.29
A30: 45294 | B30: =TiposLancamentos!B105 -> Transf. Bco | C30: PIX: Do NuBank CC | D30: 108.83
A31: 45294 | B31: =TiposLancamentos!B105 -> Transf. Bco | C31: pix: Do ITI CC | D31: 8.51
A32: 45294 | B32: =TiposLancamentos!B105 -> Transf. Bco | C32: PIX: do XP CC | D32: 130.6
A33: 45295 | B33: =TiposLancamentos!B81 -> Ferramentas gerais | C33: MercadoLivre.com.br: Serras para micro refitica | E33: 38.35
A34: 45295 | B34: =TiposLancamentos!B60 -> Correio | C34: Frete: Serras micro retifica | E34: 14.46 | F34: =SUM(E33:E34) -> 52.81
C35: /dev/null
A36: 45295 | B36: =TiposLancamentos!B37 -> Playstation 3 | C36: MercadoLivre.com.br: Controle Original Playstation 3 , Totalmente Original!!!! | E36: 163.9
A37: 45295 | B37: =TiposLancamentos!B60 -> Correio | C37: Frete: Controle Original Playstation 3 , Totalmente Original!!!! | E37: 19.8 | F37: =SUM(E36:E37) -> 183.7
C38: /dev/null
A39: 45313 | B39: =TiposLancamentos!B41 -> PSP Slim 3k | C39: MercadoLivre.com.br: Carregador de BATERIADAS do PSP Slim 3k | E39: 11.55
A40: 45313 | B40: =TiposLancamentos!B103 -> Juros_Corr. Poupança | C40: Rendimento no periodo | D40: 0.12
A41: 45324 | B41: =TiposLancamentos!B105 -> Transf. Bco | C41: PIX: do XP CC | D41: 5633.8
A42: 45324 | B42: =TiposLancamentos!B16 -> Cristiane | C42: PIX: para implantes de Hormonios | E42: 4517.25
A43: 45324 | B43: =TiposLancamentos!B13 -> Moradia | C43: PIX: Agua mineral | E43: 16
A44: 45330 | B44: =TiposLancamentos!B40 -> PS Vita Slim 2k | C44: GameTechZone: conserto + bateria nova | E44: 350
A45: 45331 | B45: =TiposLancamentos!B105 -> Transf. Bco | C45: PIX: do ItaU | D45: 10850.95
A46: 45331 | B46: =TiposLancamentos!B13 -> Moradia | C46: PIX: Agua mineral | E46: 16
A47: 45331 | B47: =TiposLancamentos!B42 -> PSP FAT 1K | C47: PIX: Para o Anderson | E47: 475
A48: 45332 | B48: =TiposLancamentos!B46 -> Maçonaria | C48: Maçonaria - Contribuição Mensal - fevereiro/2024 | E48: 210
A49: 45336 | B49: =TiposLancamentos!B103 -> Juros_Corr. Poupança | C49: REND PAGO APLIC AUT APR | D49: 5.35
A50: 45337 | B50: =TiposLancamentos!B105 -> Transf. Bco | C50: PIX: Para o Itau | E50: 488.38
A51: 45337 | B51: =TiposLancamentos!B2 -> Telefonia | C51: Fatura Claro Celular | E51: 65.5
A52: 45340 | B52: =TiposLancamentos!B19 -> Restaurantes | C52: The Burgues MAPs | E52: 216.96
A53: 45340 | B53: =TiposLancamentos!B5 -> Supermercado | C53: o oXXO | E53: 56.76
A54: 45341 | B54: =TiposLancamentos!B103 -> Juros_Corr. Poupança | C54: REND PAGO APLIC AUT APR | D54: 10.5
A55: 45341 | B55: =TiposLancamentos!B57 -> Informática | C55: PIX: GorilaShield: 02 cordões de celulares | E55: 39.94
A56: 45341 | B56: =TiposLancamentos!B60 -> Correio | C56: PIX: Frete da gorilla Shield | E56: =F56-E55 -> 12.99 | F56: 52.93
C57: /DEV/NULL
A58: 45342 | B58: =TiposLancamentos!B8 -> Aluguel | C58: Aluguel BS House + Taxas (30/30) | E58: =F64-SUM(E59:E64) -> 1631.83
A59: 45342 | B59: =TiposLancamentos!B12 -> IPTU | C59: IPTU Del Piano (30/30) | E59: 62.93
A60: 45342 | B60: =TiposLancamentos!B12 -> IPTU | C60: IPTU Valor cobrado menor Venc 20/01 | E60: 28.43
A61: 45342 | B61: =TiposLancamentos!B10 -> Distr. Água Municipal | C61: SEMASA - Agua Potavel | E61: 76.69
A62: 45342 | B62: =TiposLancamentos!B11 -> Coleta Municipal Lixo | C62: TX de Coleta de Esgoto Municipal | E62: 57.43
A63: 45342 | B63: =TiposLancamentos!B8 -> Aluguel | C63: Taxa de Boletos | E63: 8
A64: 45342 | B64: =TiposLancamentos!B9 -> Condominio | C64: Condominio Del Piano | E64: 616.37 | F64: 2481.68
C65: /DEV/NULL
A66: 45342 | B66: =TiposLancamentos!B24 -> Estacionamentos | C66: Maçonaria: Tres Pontos | E66: 18
A67: 45343 | B67: =TiposLancamentos!B56 -> Farmácia | C67: DonPeridona/Motilium 10mg | E67: 75.69
A68: 45343 | B68: =TiposLancamentos!B6 -> Energia Eletrica | C68: Fatura Enel - Fevereiro - 2024 | E68: 160.64
A69: 45344 | B69: =TiposLancamentos!B57 -> Informática | C69: MercadoLivre.com.br: Roteador Gigabit Ax5400 Tp-link Archer Ax73 Cor Preto | E69: 815.28
A70: 45345 | B70: =TiposLancamentos!B103 -> Juros_Corr. Poupança | C70: REND PAGO APLIC AUT APR | D70: 7.64
A71: 45345 | B71: =TiposLancamentos!B13 -> Moradia | C71: PIX: agua coqueiros | E71: 16
A72: 45345 | B72: =TiposLancamentos!B36 -> Playstation 2 | C72: PIX: AliExpress.Com:Mini roteador Wi-Fi sem fio com antena interna, OPENVPN, repetidor Wi-PIX: Fi, USB, MT300N-v2, MTK7628N, 802.11n, 300Mbps, MT300N-v2 | E72: 115.49
A73: 45345 | B73: =TiposLancamentos!B60 -> Correio | C73: PIX: Frete Mini Router AliXpress | E73: 32.47 | F73: =SUM(E72:E73) -> 147.96
A74: 45345 | B74: =TiposLancamentos!B17 -> GATO | C74: Areia de coco e saches | E74: 38.44
A75: 45346 | B75: =TiposLancamentos!B5 -> Supermercado | C75: o oXXo | E75: 83.53
A76: 45347 | B76: =TiposLancamentos!B5 -> Supermercado | C76: No mercadinho do predio | E76: 13.49
A77: 45347 | B77: =TiposLancamentos!B5 -> Supermercado | C77: No mercadinho do predio | E77: 13.88
A78: 45347 | B78: =TiposLancamentos!B5 -> Supermercado | C78: No mercadinho do predio | E78: 7.77
A79: 45348 | B79: =TiposLancamentos!B19 -> Restaurantes | C79: Trabalho: Café da Manhas | E79: 10.5
A80: 45348 | B80: =TiposLancamentos!B19 -> Restaurantes | C80: Trabalho: Gallo´s | E80: 42.55
A81: 45348 | B81: =TiposLancamentos!B13 -> Moradia | C81: Tomadas novas para rotreadores | E81: 34.2
A82: 45348 | B82: =TiposLancamentos!B56 -> Farmácia | C82: PIX: DrogariaSP Verbo Divino: Lexapro 10MG | E82: 329.01
A83: 45348 | B83: =TiposLancamentos!B102 -> ESTORNO | C83: PIX: DrogariaSP Verbo Divino: Lexapro 10MG | D83: 329.01
A84: 45348 | B84: =TiposLancamentos!B56 -> Farmácia | C84: PIX: Drogasil SCS Barcelona: Lexapro 10MG | E84: 329.01
A85: 45348 | B85: =TiposLancamentos!B56 -> Farmácia | C85: Losartana 50Mg, Hidrocloritiazida 25mg, Sinvastatina 20mg | E85: =F86-E86 -> 19.25
A86: 45348 | B86: =TiposLancamentos!B16 -> Cristiane | C86: pasta de dentes e sabonete intimus | E86: =14.9+19.6 -> 34.5 | F86: 53.75
A87: 45349 | B87: =TiposLancamentos!B13 -> Moradia | C87: PIX: Material e mão de obra pro Leandro do predio Ref AS tomadas do roteador novo | E87: 200
A88: 45349 | B88: =TiposLancamentos!B24 -> Estacionamentos | C88: Maçonaria: Tres pontos | E88: 18
A89: 45349 | B89: =TiposLancamentos!B103 -> Juros_Corr. Poupança | C89: REND PAGO APLIC AUT APR | D89: 6.17
A90: 45350 | B90: =TiposLancamentos!B24 -> Estacionamentos | C90: Grazziel Pizzeria | E90: 30
A91: 45350 | B91: =TiposLancamentos!B103 -> Juros_Corr. Poupança | C91: REND PAGO APLIC AUT APR | D91: 1.86
A92: 45351 | B92: =TiposLancamentos!B105 -> Transf. Bco | C92: PIX: do ItaU | D92: 8000
A93: 45351 | B93: =TiposLancamentos!B105 -> Transf. Bco | C93: PIX: Para o ItaU | E93: 4.24
A94: 45351 | B94: =TiposLancamentos!B103 -> Juros_Corr. Poupança | C94: REND PAGO APLIC AUT APR | D94: 1.86
A95: 45352 | B95: =TiposLancamentos!B15 -> Cartões de Crédito | C95: Fatura CrediCard Masters | E95: 961.31
A96: 45352 | B96: =TiposLancamentos!B15 -> Cartões de Crédito | C96: Fatura NuBank Masters | E96: 1511.05
A97: 45352 | B97: =TiposLancamentos!B15 -> Cartões de Crédito | C97: Fatura XP Visa | E97: 2393.08
A98: 45352 | B98: =TiposLancamentos!B15 -> Cartões de Crédito | C98: Fatura ItauUniClass Visa | E98: 300
A99: 45352 | B99: =TiposLancamentos!B15 -> Cartões de Crédito | C99: Fatura MercadoPago Visa | E99: 90.05
A100: 45352 | B100: =TiposLancamentos!B15 -> Cartões de Crédito | C100: Fatura Amazon Visa | E100: 1565.34
...

Sheet MercadoPago_Visa
A1: Data | B1: TIPO | C1: DESCRICAO | D1: Credito | E1: Debito | F1: Subtotais | G1: Check
C2: Junho / 2022
A3: 44743 | B3: =TiposLancamentos!B78 -> Diferenças | C3: Teste In | D3: 0.01 | G3: X
A4: 44744 | B4: =TiposLancamentos!B78 -> Diferenças | C4: Teste Out | E4: 0.01 | G4: X
C5: CORTE DE FATURAMENTO | G5: ???
C6: /DEV/NULL
C7: Outubro / 2023 | F7: =SUM(E2:E5) -> 0.01
A8: 45203 | B8: =TiposLancamentos!B37 -> Playstation 3 | C8: Game: MercadoLivre.com.br: Ressonanse of Faith | E8: 72 | F8: =F7-F2 -> 0.01 | G8: X
A9: 45203 | B9: =TiposLancamentos!B60 -> Correio | C9: Game: MercadoLivre.com.br: Ressonanse of Faith | E9: 13.5 | F9: =SUM(E8:E9) -> 85.5 | G9: X
A10: 45203 | B10: =TiposLancamentos!B38 -> Playstation 4 | C10: Game: MercadoLivre.com.br: Nier: Automata Nier Game Of The Yorha Edition Square Enix Ps4 Físico | E10: 149.02 | G10: X
A11: 45203 | B11: =TiposLancamentos!B38 -> Playstation 4 | C11: Game: MercadoLivre.com.br: Hellblade Senua's Sacrifice Ps4 Físico Lacrado | E11: 70.22 | G11: X
A12: 45203 | B12: =TiposLancamentos!B60 -> Correio | C12: Game: MercadoLivre.com.br: Hellblade Senua's Sacrifice Ps4 Físico Lacrado | E12: 13.52 | F12: =SUM(E11:E12) -> 83.74 | G12: X
A13: 45203 | B13: =TiposLancamentos!B37 -> Playstation 3 | C13: Game: MercadoLivre.com.br:Bound by Fire | E13: 69.21 | G13: X
A14: 45203 | B14: =TiposLancamentos!B60 -> Correio | C14: Game: MercadoLivre.com.br:Bound by Fire | E14: 13.52 | F14: =SUM(E13:E14) -> 82.73 | G14: X
C15: /DEV/NULL
C16: CORTE DE FATURAMENTO | G16: ???
C17: /DEV/NULL
C18: Novembro / 2023 | F18: =SUM(E5:E16) -> 400.99
A19: 45231 | B19: =TiposLancamentos!B15 -> Cartões de Crédito | C19: Pagamento de Fatura | D19: 400.99
A20: 45236 | B20: =TiposLancamentos!B13 -> Moradia | C20: MercadoLivre.combr: Bandeja Cantinho Do Café Dolce Gusto Gaveta Porta 32 Capsula | E20: 92
C21: CORTE DE FATURAMENTO | G21: ???
C22: /DEV/NULL
C23: Dezembro / 2023 | F23: =SUM(E16:E21) -> 92
A24: 45261 | B24: =TiposLancamentos!B15 -> Cartões de Crédito | C24: Pagamento de Fatura | D24: 92 | F24: =F23-F18 -> -308.99 | G24: X
A25: 45263 | B25: =TiposLancamentos!B16 -> Cristiane | C25: Coisas no Mercado Livre | E25: 63.9 | G25: X
